Workbook

Sheet Clasificación común
A1: Clasificación común a TVN, Canal 13, Mega y Chilevisión
A2: Nivel 1 = la partición más básica. Nivel 2 = la partición más fina que los cuatro canales permiten sin supuestos. Cifras de las notas de ingresos de los EEFF (hoja 'Líneas codificadas', columnas N y O).
A4: NIVEL 1 — Básico (% de ingresos de actividades ordinarias)
A5: Canal | B5: Categoría | C5: FY2024 | D5: FY2025 | E5: H1 2025 | F5: H1 2026
A6: TVN | B6: Publicidad | C6: =IF(SUMIFS('Líneas codificadas'!$E$2:$E$49,'Líneas codificadas'!$A$2:$A$49,"TVN",'Líneas codificadas'!$B$2:$B$49,"FY2024")=0,"n.d.",SUMIFS('Líneas codificadas'!$E$2:$E$49,'Líneas codificadas'!$A$2:$A$49,"TVN",'Líneas codificadas'!$B$2:$B$49,"FY2024",'Líneas codificadas'!$N$2:$N$49,"Publicidad")/SUMIFS('Líneas codificadas'!$E$2:$E$49,'Líneas codificadas'!$A$2:$A$49,"TVN",'Líneas codificadas'!$B$2:$B$49,"FY2024")) -> 0.63528699 | D6: =IF(SUMIFS('Líneas codificadas'!$E$2:$E$49,'Líneas codificadas'!$A$2:$A$49,"TVN",'Líneas codificadas'!$B$2:$B$49,"FY2025")=0,"n.d.",SUMIFS('Líneas codificadas'!$E$2:$E$49,'Líneas codificadas'!$A$2:$A$49,"TVN",'Líneas codificadas'!$B$2:$B$49,"FY2025",'Líneas codificadas'!$N$2:$N$49,"Publicidad")/SUMIFS('Líneas codificadas'!$E$2:$E$49,'Líneas codificadas'!$A$2:$A$49,"TVN",'Líneas codificadas'!$B$2:$B$49,"FY2025")) -> 0.60080217 | E6: =IF(SUMIFS('Líneas codificadas'!$E$2:$E$49,'Líneas codificadas'!$A$2:$A$49,"TVN",'Líneas codificadas'!$B$2:$B$49,"H1 2025")=0,"n.d.",SUMIFS('Líneas codificadas'!$E$2:$E$49,'Líneas codificadas'!$A$2:$A$49,"TVN",'Líneas codificadas'!$B$2:$B$49,"H1 2025",'Líneas codificadas'!$N$2:$N$49,"Publicidad")/SUMIFS('Líneas codificadas'!$E$2:$E$49,'Líneas codificadas'!$A$2:$A$49,"TVN",'Líneas codificadas'!$B$2:$B$49,"H1 2025")) -> 0.58156218 | F6: =IF(SUMIFS('Líneas codificadas'!$E$2:$E$49,'Líneas codificadas'!$A$2:$A$49,"TVN",'Líneas codificadas'!$B$2:$B$49,"H1 2026")=0,"n.d.",SUMIFS('Líneas codificadas'!$E$2:$E$49,'Líneas codificadas'!$A$2:$A$49,"TVN",'Líneas codificadas'!$B$2:$B$49,"H1 2026",'Líneas codificadas'!$N$2:$N$49,"Publicidad")/SUMIFS('Líneas codificadas'!$E$2:$E$49,'Líneas codificadas'!$A$2:$A$49,"TVN",'Líneas codificadas'!$B$2:$B$49,"H1 2026")) -> 0.56508885
B7: Otros ingresos | C7: =IF(SUMIFS('Líneas codificadas'!$E$2:$E$49,'Líneas codificadas'!$A$2:$A$49,"TVN",'Líneas codificadas'!$B$2:$B$49,"FY2024")=0,"n.d.",SUMIFS('Líneas codificadas'!$E$2:$E$49,'Líneas codificadas'!$A$2:$A$49,"TVN",'Líneas codificadas'!$B$2:$B$49,"FY2024",'Líneas codificadas'!$N$2:$N$49,"Otros ingresos")/SUMIFS('Líneas codificadas'!$E$2:$E$49,'Líneas codificadas'!$A$2:$A$49,"TVN",'Líneas codificadas'!$B$2:$B$49,"FY2024")) -> 0.36471301 | D7: =IF(SUMIFS('Líneas codificadas'!$E$2:$E$49,'Líneas codificadas'!$A$2:$A$49,"TVN",'Líneas codificadas'!$B$2:$B$49,"FY2025")=0,"n.d.",SUMIFS('Líneas codificadas'!$E$2:$E$49,'Líneas codificadas'!$A$2:$A$49,"TVN",'Líneas codificadas'!$B$2:$B$49,"FY2025",'Líneas codificadas'!$N$2:$N$49,"Otros ingresos")/SUMIFS('Líneas codificadas'!$E$2:$E$49,'Líneas codificadas'!$A$2:$A$49,"TVN",'Líneas codificadas'!$B$2:$B$49,"FY2025")) -> 0.39919783 | E7: =IF(SUMIFS('Líneas codificadas'!$E$2:$E$49,'Líneas codificadas'!$A$2:$A$49,"TVN",'Líneas codificadas'!$B$2:$B$49,"H1 2025")=0,"n.d.",SUMIFS('Líneas codificadas'!$E$2:$E$49,'Líneas codificadas'!$A$2:$A$49,"TVN",'Líneas codificadas'!$B$2:$B$49,"H1 2025",'Líneas codificadas'!$N$2:$N$49,"Otros ingresos")/SUMIFS('Líneas codificadas'!$E$2:$E$49,'Líneas codificadas'!$A$2:$A$49,"TVN",'Líneas codificadas'!$B$2:$B$49,"H1 2025")) -> 0.41843782 | F7: =IF(SUMIFS('Líneas codificadas'!$E$2:$E$49,'Líneas codificadas'!$A$2:$A$49,"TVN",'Líneas codificadas'!$B$2:$B$49,"H1 2026")=0,"n.d.",SUMIFS('Líneas codificadas'!$E$2:$E$49,'Líneas codificadas'!$A$2:$A$49,"TVN",'Líneas codificadas'!$B$2:$B$49,"H1 2026",'Líneas codificadas'!$N$2:$N$49,"Otros ingresos")/SUMIFS('Líneas codificadas'!$E$2:$E$49,'Líneas codificadas'!$A$2:$A$49,"TVN",'Líneas codificadas'!$B$2:$B$49,"H1 2026")) -> 0.43491115
B8: Total | C8: =IF(SUMIFS('Líneas codificadas'!$E$2:$E$49,'Líneas codificadas'!$A$2:$A$49,"TVN",'Líneas codificadas'!$B$2:$B$49,"FY2024")=0,"n.d.",SUMIFS('Líneas codificadas'!$E$2:$E$49,'Líneas codificadas'!$A$2:$A$49,"TVN",'Líneas codificadas'!$B$2:$B$49,"FY2024")/SUMIFS('Líneas codificadas'!$E$2:$E$49,'Líneas codificadas'!$A$2:$A$49,"TVN",'Líneas codificadas'!$B$2:$B$49,"FY2024")) -> 1 | D8: =IF(SUMIFS('Líneas codificadas'!$E$2:$E$49,'Líneas codificadas'!$A$2:$A$49,"TVN",'Líneas codificadas'!$B$2:$B$49,"FY2025")=0,"n.d.",SUMIFS('Líneas codificadas'!$E$2:$E$49,'Líneas codificadas'!$A$2:$A$49,"TVN",'Líneas codificadas'!$B$2:$B$49,"FY2025")/SUMIFS('Líneas codificadas'!$E$2:$E$49,'Líneas codificadas'!$A$2:$A$49,"TVN",'Líneas codificadas'!$B$2:$B$49,"FY2025")) -> 1 | E8: =IF(SUMIFS('Líneas codificadas'!$E$2:$E$49,'Líneas codificadas'!$A$2:$A$49,"TVN",'Líneas codificadas'!$B$2:$B$49,"H1 2025")=0,"n.d.",SUMIFS('Líneas codificadas'!$E$2:$E$49,'Líneas codificadas'!$A$2:$A$49,"TVN",'Líneas codificadas'!$B$2:$B$49,"H1 2025")/SUMIFS('Líneas codificadas'!$E$2:$E$49,'Líneas codificadas'!$A$2:$A$49,"TVN",'Líneas codificadas'!$B$2:$B$49,"H1 2025")) -> 1 | F8: =IF(SUMIFS('Líneas codificadas'!$E$2:$E$49,'Líneas codificadas'!$A$2:$A$49,"TVN",'Líneas codificadas'!$B$2:$B$49,"H1 2026")=0,"n.d.",SUMIFS('Líneas codificadas'!$E$2:$E$49,'Líneas codificadas'!$A$2:$A$49,"TVN",'Líneas codificadas'!$B$2:$B$49,"H1 2026")/SUMIFS('Líneas codificadas'!$E$2:$E$49,'Líneas codificadas'!$A$2:$A$49,"TVN",'Líneas codificadas'!$B$2:$B$49,"H1 2026")) -> 1
A9: Canal 13 | B9: Publicidad | C9: =IF(SUMIFS('Líneas codificadas'!$E$2:$E$49,'Líneas codificadas'!$A$2:$A$49,"Canal 13",'Líneas codificadas'!$B$2:$B$49,"FY2024")=0,"n.d.",SUMIFS('Líneas codificadas'!$E$2:$E$49,'Líneas codificadas'!$A$2:$A$49,"Canal 13",'Líneas codificadas'!$B$2:$B$49,"FY2024",'Líneas codificadas'!$N$2:$N$49,"Publicidad")/SUMIFS('Líneas codificadas'!$E$2:$E$49,'Líneas codificadas'!$A$2:$A$49,"Canal 13",'Líneas codificadas'!$B$2:$B$49,"FY2024")) -> 0.75965797 | D9: =IF(SUMIFS('Líneas codificadas'!$E$2:$E$49,'Líneas codificadas'!$A$2:$A$49,"Canal 13",'Líneas codificadas'!$B$2:$B$49,"FY2025")=0,"n.d.",SUMIFS('Líneas codificadas'!$E$2:$E$49,'Líneas codificadas'!$A$2:$A$49,"Canal 13",'Líneas codificadas'!$B$2:$B$49,"FY2025",'Líneas codificadas'!$N$2:$N$49,"Publicidad")/SUMIFS('Líneas codificadas'!$E$2:$E$49,'Líneas codificadas'!$A$2:$A$49,"Canal 13",'Líneas codificadas'!$B$2:$B$49,"FY2025")) -> 0.76724611 | E9: =IF(SUMIFS('Líneas codificadas'!$E$2:$E$49,'Líneas codificadas'!$A$2:$A$49,"Canal 13",'Líneas codificadas'!$B$2:$B$49,"H1 2025")=0,"n.d.",SUMIFS('Líneas codificadas'!$E$2:$E$49,'Líneas codificadas'!$A$2:$A$49,"Canal 13",'Líneas codificadas'!$B$2:$B$49,"H1 2025",'Líneas codificadas'!$N$2:$N$49,"Publicidad")/SUMIFS('Líneas codificadas'!$E$2:$E$49,'Líneas codificadas'!$A$2:$A$49,"Canal 13",'Líneas codificadas'!$B$2:$B$49,"H1 2025")) -> 0.75688188 | F9: =IF(SUMIFS('Líneas codificadas'!$E$2:$E$49,'Líneas codificadas'!$A$2:$A$49,"Canal 13",'Líneas codificadas'!$B$2:$B$49,"H1 2026")=0,"n.d.",SUMIFS('Líneas codificadas'!$E$2:$E$49,'Líneas codificadas'!$A$2:$A$49,"Canal 13",'Líneas codificadas'!$B$2:$B$49,"H1 2026",'Líneas codificadas'!$N$2:$N$49,"Publicidad")/SUMIFS('Líneas codificadas'!$E$2:$E$49,'Líneas codificadas'!$A$2:$A$49,"Canal 13",'Líneas codificadas'!$B$2:$B$49,"H1 2026")) -> 0.70870179
B10: Otros ingresos | C10: =IF(SUMIFS('Líneas codificadas'!$E$2:$E$49,'Líneas codificadas'!$A$2:$A$49,"Canal 13",'Líneas codificadas'!$B$2:$B$49,"FY2024")=0,"n.d.",SUMIFS('Líneas codificadas'!$E$2:$E$49,'Líneas codificadas'!$A$2:$A$49,"Canal 13",'Líneas codificadas'!$B$2:$B$49,"FY2024",'Líneas codificadas'!$N$2:$N$49,"Otros ingresos")/SUMIFS('Líneas codificadas'!$E$2:$E$49,'Líneas codificadas'!$A$2:$A$49,"Canal 13",'Líneas codificadas'!$B$2:$B$49,"FY2024")) -> 0.24034203 | D10: =IF(SUMIFS('Líneas codificadas'!$E$2:$E$49,'Líneas codificadas'!$A$2:$A$49,"Canal 13",'Líneas codificadas'!$B$2:$B$49,"FY2025")=0,"n.d.",SUMIFS('Líneas codificadas'!$E$2:$E$49,'Líneas codificadas'!$A$2:$A$49,"Canal 13",'Líneas codificadas'!$B$2:$B$49,"FY2025",'Líneas codificadas'!$N$2:$N$49,"Otros ingresos")/SUMIFS('Líneas codificadas'!$E$2:$E$49,'Líneas codificadas'!$A$2:$A$49,"Canal 13",'Líneas codificadas'!$B$2:$B$49,"FY2025")) -> 0.23275389 | E10: =IF(SUMIFS('Líneas codificadas'!$E$2:$E$49,'Líneas codificadas'!$A$2:$A$49,"Canal 13",'Líneas codificadas'!$B$2:$B$49,"H1 2025")=0,"n.d.",SUMIFS('Líneas codificadas'!$E$2:$E$49,'Líneas codificadas'!$A$2:$A$49,"Canal 13",'Líneas codificadas'!$B$2:$B$49,"H1 2025",'Líneas codificadas'!$N$2:$N$49,"Otros ingresos")/SUMIFS('Líneas codificadas'!$E$2:$E$49,'Líneas codificadas'!$A$2:$A$49,"Canal 13",'Líneas codificadas'!$B$2:$B$49,"H1 2025")) -> 0.24311812 | F10: =IF(SUMIFS('Líneas codificadas'!$E$2:$E$49,'Líneas codificadas'!$A$2:$A$49,"Canal 13",'Líneas codificadas'!$B$2:$B$49,"H1 2026")=0,"n.d.",SUMIFS('Líneas codificadas'!$E$2:$E$49,'Líneas codificadas'!$A$2:$A$49,"Canal 13",'Líneas codificadas'!$B$2:$B$49,"H1 2026",'Líneas codificadas'!$N$2:$N$49,"Otros ingresos")/SUMIFS('Líneas codificadas'!$E$2:$E$49,'Líneas codificadas'!$A$2:$A$49,"Canal 13",'Líneas codificadas'!$B$2:$B$49,"H1 2026")) -> 0.29129821
B11: Total | C11: =IF(SUMIFS('Líneas codificadas'!$E$2:$E$49,'Líneas codificadas'!$A$2:$A$49,"Canal 13",'Líneas codificadas'!$B$2:$B$49,"FY2024")=0,"n.d.",SUMIFS('Líneas codificadas'!$E$2:$E$49,'Líneas codificadas'!$A$2:$A$49,"Canal 13",'Líneas codificadas'!$B$2:$B$49,"FY2024")/SUMIFS('Líneas codificadas'!$E$2:$E$49,'Líneas codificadas'!$A$2:$A$49,"Canal 13",'Líneas codificadas'!$B$2:$B$49,"FY2024")) -> 1 | D11: =IF(SUMIFS('Líneas codificadas'!$E$2:$E$49,'Líneas codificadas'!$A$2:$A$49,"Canal 13",'Líneas codificadas'!$B$2:$B$49,"FY2025")=0,"n.d.",SUMIFS('Líneas codificadas'!$E$2:$E$49,'Líneas codificadas'!$A$2:$A$49,"Canal 13",'Líneas codificadas'!$B$2:$B$49,"FY2025")/SUMIFS('Líneas codificadas'!$E$2:$E$49,'Líneas codificadas'!$A$2:$A$49,"Canal 13",'Líneas codificadas'!$B$2:$B$49,"FY2025")) -> 1 | E11: =IF(SUMIFS('Líneas codificadas'!$E$2:$E$49,'Líneas codificadas'!$A$2:$A$49,"Canal 13",'Líneas codificadas'!$B$2:$B$49,"H1 2025")=0,"n.d.",SUMIFS('Líneas codificadas'!$E$2:$E$49,'Líneas codificadas'!$A$2:$A$49,"Canal 13",'Líneas codificadas'!$B$2:$B$49,"H1 2025")/SUMIFS('Líneas codificadas'!$E$2:$E$49,'Líneas codificadas'!$A$2:$A$49,"Canal 13",'Líneas codificadas'!$B$2:$B$49,"H1 2025")) -> 1 | F11: =IF(SUMIFS('Líneas codificadas'!$E$2:$E$49,'Líneas codificadas'!$A$2:$A$49,"Canal 13",'Líneas codificadas'!$B$2:$B$49,"H1 2026")=0,"n.d.",SUMIFS('Líneas codificadas'!$E$2:$E$49,'Líneas codificadas'!$A$2:$A$49,"Canal 13",'Líneas codificadas'!$B$2:$B$49,"H1 2026")/SUMIFS('Líneas codificadas'!$E$2:$E$49,'Líneas codificadas'!$A$2:$A$49,"Canal 13",'Líneas codificadas'!$B$2:$B$49,"H1 2026")) -> 1
A12: Mega | B12: Publicidad | C12: =IF(SUMIFS('Líneas codificadas'!$E$2:$E$49,'Líneas codificadas'!$A$2:$A$49,"Mega",'Líneas codificadas'!$B$2:$B$49,"FY2024")=0,"n.d.",SUMIFS('Líneas codificadas'!$E$2:$E$49,'Líneas codificadas'!$A$2:$A$49,"Mega",'Líneas codificadas'!$B$2:$B$49,"FY2024",'Líneas codificadas'!$N$2:$N$49,"Publicidad")/SUMIFS('Líneas codificadas'!$E$2:$E$49,'Líneas codificadas'!$A$2:$A$49,"Mega",'Líneas codificadas'!$B$2:$B$49,"FY2024")) -> 0.75694926 | D12: =IF(SUMIFS('Líneas codificadas'!$E$2:$E$49,'Líneas codificadas'!$A$2:$A$49,"Mega",'Líneas codificadas'!$B$2:$B$49,"FY2025")=0,"n.d.",SUMIFS('Líneas codificadas'!$E$2:$E$49,'Líneas codificadas'!$A$2:$A$49,"Mega",'Líneas codificadas'!$B$2:$B$49,"FY2025",'Líneas codificadas'!$N$2:$N$49,"Publicidad")/SUMIFS('Líneas codificadas'!$E$2:$E$49,'Líneas codificadas'!$A$2:$A$49,"Mega",'Líneas codificadas'!$B$2:$B$49,"FY2025")) -> 0.78894747 | E12: =IF(SUMIFS('Líneas codificadas'!$E$2:$E$49,'Líneas codificadas'!$A$2:$A$49,"Mega",'Líneas codificadas'!$B$2:$B$49,"H1 2025")=0,"n.d.",SUMIFS('Líneas codificadas'!$E$2:$E$49,'Líneas codificadas'!$A$2:$A$49,"Mega",'Líneas codificadas'!$B$2:$B$49,"H1 2025",'Líneas codificadas'!$N$2:$N$49,"Publicidad")/SUMIFS('Líneas codificadas'!$E$2:$E$49,'Líneas codificadas'!$A$2:$A$49,"Mega",'Líneas codificadas'!$B$2:$B$49,"H1 2025")) -> 0.72585315 | F12: =IF(SUMIFS('Líneas codificadas'!$E$2:$E$49,'Líneas codificadas'!$A$2:$A$49,"Mega",'Líneas codificadas'!$B$2:$B$49,"H1 2026")=0,"n.d.",SUMIFS('Líneas codificadas'!$E$2:$E$49,'Líneas codificadas'!$A$2:$A$49,"Mega",'Líneas codificadas'!$B$2:$B$49,"H1 2026",'Líneas codificadas'!$N$2:$N$49,"Publicidad")/SUMIFS('Líneas codificadas'!$E$2:$E$49,'Líneas codificadas'!$A$2:$A$49,"Mega",'Líneas codificadas'!$B$2:$B$49,"H1 2026")) -> 0.82096326
B13: Otros ingresos | C13: =IF(SUMIFS('Líneas codificadas'!$E$2:$E$49,'Líneas codificadas'!$A$2:$A$49,"Mega",'Líneas codificadas'!$B$2:$B$49,"FY2024")=0,"n.d.",SUMIFS('Líneas codificadas'!$E$2:$E$49,'Líneas codificadas'!$A$2:$A$49,"Mega",'Líneas codificadas'!$B$2:$B$49,"FY2024",'Líneas codificadas'!$N$2:$N$49,"Otros ingresos")/SUMIFS('Líneas codificadas'!$E$2:$E$49,'Líneas codificadas'!$A$2:$A$49,"Mega",'Líneas codificadas'!$B$2:$B$49,"FY2024")) -> 0.24305074 | D13: =IF(SUMIFS('Líneas codificadas'!$E$2:$E$49,'Líneas codificadas'!$A$2:$A$49,"Mega",'Líneas codificadas'!$B$2:$B$49,"FY2025")=0,"n.d.",SUMIFS('Líneas codificadas'!$E$2:$E$49,'Líneas codificadas'!$A$2:$A$49,"Mega",'Líneas codificadas'!$B$2:$B$49,"FY2025",'Líneas codificadas'!$N$2:$N$49,"Otros ingresos")/SUMIFS('Líneas codificadas'!$E$2:$E$49,'Líneas codificadas'!$A$2:$A$49,"Mega",'Líneas codificadas'!$B$2:$B$49,"FY2025")) -> 0.21105253 | E13: =IF(SUMIFS('Líneas codificadas'!$E$2:$E$49,'Líneas codificadas'!$A$2:$A$49,"Mega",'Líneas codificadas'!$B$2:$B$49,"H1 2025")=0,"n.d.",SUMIFS('Líneas codificadas'!$E$2:$E$49,'Líneas codificadas'!$A$2:$A$49,"Mega",'Líneas codificadas'!$B$2:$B$49,"H1 2025",'Líneas codificadas'!$N$2:$N$49,"Otros ingresos")/SUMIFS('Líneas codificadas'!$E$2:$E$49,'Líneas codificadas'!$A$2:$A$49,"Mega",'Líneas codificadas'!$B$2:$B$49,"H1 2025")) -> 0.27414685 | F13: =IF(SUMIFS('Líneas codificadas'!$E$2:$E$49,'Líneas codificadas'!$A$2:$A$49,"Mega",'Líneas codificadas'!$B$2:$B$49,"H1 2026")=0,"n.d.",SUMIFS('Líneas codificadas'!$E$2:$E$49,'Líneas codificadas'!$A$2:$A$49,"Mega",'Líneas codificadas'!$B$2:$B$49,"H1 2026",'Líneas codificadas'!$N$2:$N$49,"Otros ingresos")/SUMIFS('Líneas codificadas'!$E$2:$E$49,'Líneas codificadas'!$A$2:$A$49,"Mega",'Líneas codificadas'!$B$2:$B$49,"H1 2026")) -> 0.17903674
B14: Total | C14: =IF(SUMIFS('Líneas codificadas'!$E$2:$E$49,'Líneas codificadas'!$A$2:$A$49,"Mega",'Líneas codificadas'!$B$2:$B$49,"FY2024")=0,"n.d.",SUMIFS('Líneas codificadas'!$E$2:$E$49,'Líneas codificadas'!$A$2:$A$49,"Mega",'Líneas codificadas'!$B$2:$B$49,"FY2024")/SUMIFS('Líneas codificadas'!$E$2:$E$49,'Líneas codificadas'!$A$2:$A$49,"Mega",'Líneas codificadas'!$B$2:$B$49,"FY2024")) -> 1 | D14: =IF(SUMIFS('Líneas codificadas'!$E$2:$E$49,'Líneas codificadas'!$A$2:$A$49,"Mega",'Líneas codificadas'!$B$2:$B$49,"FY2025")=0,"n.d.",SUMIFS('Líneas codificadas'!$E$2:$E$49,'Líneas codificadas'!$A$2:$A$49,"Mega",'Líneas codificadas'!$B$2:$B$49,"FY2025")/SUMIFS('Líneas codificadas'!$E$2:$E$49,'Líneas codificadas'!$A$2:$A$49,"Mega",'Líneas codificadas'!$B$2:$B$49,"FY2025")) -> 1 | E14: =IF(SUMIFS('Líneas codificadas'!$E$2:$E$49,'Líneas codificadas'!$A$2:$A$49,"Mega",'Líneas codificadas'!$B$2:$B$49,"H1 2025")=0,"n.d.",SUMIFS('Líneas codificadas'!$E$2:$E$49,'Líneas codificadas'!$A$2:$A$49,"Mega",'Líneas codificadas'!$B$2:$B$49,"H1 2025")/SUMIFS('Líneas codificadas'!$E$2:$E$49,'Líneas codificadas'!$A$2:$A$49,"Mega",'Líneas codificadas'!$B$2:$B$49,"H1 2025")) -> 1 | F14: =IF(SUMIFS('Líneas codificadas'!$E$2:$E$49,'Líneas codificadas'!$A$2:$A$49,"Mega",'Líneas codificadas'!$B$2:$B$49,"H1 2026")=0,"n.d.",SUMIFS('Líneas codificadas'!$E$2:$E$49,'Líneas codificadas'!$A$2:$A$49,"Mega",'Líneas codificadas'!$B$2:$B$49,"H1 2026")/SUMIFS('Líneas codificadas'!$E$2:$E$49,'Líneas codificadas'!$A$2:$A$49,"Mega",'Líneas codificadas'!$B$2:$B$49,"H1 2026")) -> 1
A15: Chilevisión | B15: Publicidad | C15: =IF(SUMIFS('Líneas codificadas'!$E$2:$E$49,'Líneas codificadas'!$A$2:$A$49,"Chilevisión",'Líneas codificadas'!$B$2:$B$49,"FY2024")=0,"n.d.",SUMIFS('Líneas codificadas'!$E$2:$E$49,'Líneas codificadas'!$A$2:$A$49,"Chilevisión",'Líneas codificadas'!$B$2:$B$49,"FY2024",'Líneas codificadas'!$N$2:$N$49,"Publicidad")/SUMIFS('Líneas codificadas'!$E$2:$E$49,'Líneas codificadas'!$A$2:$A$49,"Chilevisión",'Líneas codificadas'!$B$2:$B$49,"FY2024")) -> 0.91045902 | D15: =IF(SUMIFS('Líneas codificadas'!$E$2:$E$49,'Líneas codificadas'!$A$2:$A$49,"Chilevisión",'Líneas codificadas'!$B$2:$B$49,"FY2025")=0,"n.d.",SUMIFS('Líneas codificadas'!$E$2:$E$49,'Líneas codificadas'!$A$2:$A$49,"Chilevisión",'Líneas codificadas'!$B$2:$B$49,"FY2025",'Líneas codificadas'!$N$2:$N$49,"Publicidad")/SUMIFS('Líneas codificadas'!$E$2:$E$49,'Líneas codificadas'!$A$2:$A$49,"Chilevisión",'Líneas codificadas'!$B$2:$B$49,"FY2025")) -> 0.89632396 | E15: =IF(SUMIFS('Líneas codificadas'!$E$2:$E$49,'Líneas codificadas'!$A$2:$A$49,"Chilevisión",'Líneas codificadas'!$B$2:$B$49,"H1 2025")=0,"n.d.",SUMIFS('Líneas codificadas'!$E$2:$E$49,'Líneas codificadas'!$A$2:$A$49,"Chilevisión",'Líneas codificadas'!$B$2:$B$49,"H1 2025",'Líneas codificadas'!$N$2:$N$49,"Publicidad")/SUMIFS('Líneas codificadas'!$E$2:$E$49,'Líneas codificadas'!$A$2:$A$49,"Chilevisión",'Líneas codificadas'!$B$2:$B$49,"H1 2025")) -> 0.95082266 | F15: =IF(SUMIFS('Líneas codificadas'!$E$2:$E$49,'Líneas codificadas'!$A$2:$A$49,"Chilevisión",'Líneas codificadas'!$B$2:$B$49,"H1 2026")=0,"n.d.",SUMIFS('Líneas codificadas'!$E$2:$E$49,'Líneas codificadas'!$A$2:$A$49,"Chilevisión",'Líneas codificadas'!$B$2:$B$49,"H1 2026",'Líneas codificadas'!$N$2:$N$49,"Publicidad")/SUMIFS('Líneas codificadas'!$E$2:$E$49,'Líneas codificadas'!$A$2:$A$49,"Chilevisión",'Líneas codificadas'!$B$2:$B$49,"H1 2026")) -> 0.9089824
B16: Otros ingresos | C16: =IF(SUMIFS('Líneas codificadas'!$E$2:$E$49,'Líneas codificadas'!$A$2:$A$49,"Chilevisión",'Líneas codificadas'!$B$2:$B$49,"FY2024")=0,"n.d.",SUMIFS('Líneas codificadas'!$E$2:$E$49,'Líneas codificadas'!$A$2:$A$49,"Chilevisión",'Líneas codificadas'!$B$2:$B$49,"FY2024",'Líneas codificadas'!$N$2:$N$49,"Otros ingresos")/SUMIFS('Líneas codificadas'!$E$2:$E$49,'Líneas codificadas'!$A$2:$A$49,"Chilevisión",'Líneas codificadas'!$B$2:$B$49,"FY2024")) -> 0.089540978 | D16: =IF(SUMIFS('Líneas codificadas'!$E$2:$E$49,'Líneas codificadas'!$A$2:$A$49,"Chilevisión",'Líneas codificadas'!$B$2:$B$49,"FY2025")=0,"n.d.",SUMIFS('Líneas codificadas'!$E$2:$E$49,'Líneas codificadas'!$A$2:$A$49,"Chilevisión",'Líneas codificadas'!$B$2:$B$49,"FY2025",'Líneas codificadas'!$N$2:$N$49,"Otros ingresos")/SUMIFS('Líneas codificadas'!$E$2:$E$49,'Líneas codificadas'!$A$2:$A$49,"Chilevisión",'Líneas codificadas'!$B$2:$B$49,"FY2025")) -> 0.10367604 | E16: =IF(SUMIFS('Líneas codificadas'!$E$2:$E$49,'Líneas codificadas'!$A$2:$A$49,"Chilevisión",'Líneas codificadas'!$B$2:$B$49,"H1 2025")=0,"n.d.",SUMIFS('Líneas codificadas'!$E$2:$E$49,'Líneas codificadas'!$A$2:$A$49,"Chilevisión",'Líneas codificadas'!$B$2:$B$49,"H1 2025",'Líneas codificadas'!$N$2:$N$49,"Otros ingresos")/SUMIFS('Líneas codificadas'!$E$2:$E$49,'Líneas codificadas'!$A$2:$A$49,"Chilevisión",'Líneas codificadas'!$B$2:$B$49,"H1 2025")) -> 0.049177343 | F16: =IF(SUMIFS('Líneas codificadas'!$E$2:$E$49,'Líneas codificadas'!$A$2:$A$49,"Chilevisión",'Líneas codificadas'!$B$2:$B$49,"H1 2026")=0,"n.d.",SUMIFS('Líneas codificadas'!$E$2:$E$49,'Líneas codificadas'!$A$2:$A$49,"Chilevisión",'Líneas codificadas'!$B$2:$B$49,"H1 2026",'Líneas codificadas'!$N$2:$N$49,"Otros ingresos")/SUMIFS('Líneas codificadas'!$E$2:$E$49,'Líneas codificadas'!$A$2:$A$49,"Chilevisión",'Líneas codificadas'!$B$2:$B$49,"H1 2026")) -> 0.091017596
B17: Total | C17: =IF(SUMIFS('Líneas codificadas'!$E$2:$E$49,'Líneas codificadas'!$A$2:$A$49,"Chilevisión",'Líneas codificadas'!$B$2:$B$49,"FY2024")=0,"n.d.",SUMIFS('Líneas codificadas'!$E$2:$E$49,'Líneas codificadas'!$A$2:$A$49,"Chilevisión",'Líneas codificadas'!$B$2:$B$49,"FY2024")/SUMIFS('Líneas codificadas'!$E$2:$E$49,'Líneas codificadas'!$A$2:$A$49,"Chilevisión",'Líneas codificadas'!$B$2:$B$49,"FY2024")) -> 1 | D17: =IF(SUMIFS('Líneas codificadas'!$E$2:$E$49,'Líneas codificadas'!$A$2:$A$49,"Chilevisión",'Líneas codificadas'!$B$2:$B$49,"FY2025")=0,"n.d.",SUMIFS('Líneas codificadas'!$E$2:$E$49,'Líneas codificadas'!$A$2:$A$49,"Chilevisión",'Líneas codificadas'!$B$2:$B$49,"FY2025")/SUMIFS('Líneas codificadas'!$E$2:$E$49,'Líneas codificadas'!$A$2:$A$49,"Chilevisión",'Líneas codificadas'!$B$2:$B$49,"FY2025")) -> 1 | E17: =IF(SUMIFS('Líneas codificadas'!$E$2:$E$49,'Líneas codificadas'!$A$2:$A$49,"Chilevisión",'Líneas codificadas'!$B$2:$B$49,"H1 2025")=0,"n.d.",SUMIFS('Líneas codificadas'!$E$2:$E$49,'Líneas codificadas'!$A$2:$A$49,"Chilevisión",'Líneas codificadas'!$B$2:$B$49,"H1 2025")/SUMIFS('Líneas codificadas'!$E$2:$E$49,'Líneas codificadas'!$A$2:$A$49,"Chilevisión",'Líneas codificadas'!$B$2:$B$49,"H1 2025")) -> 1 | F17: =IF(SUMIFS('Líneas codificadas'!$E$2:$E$49,'Líneas codificadas'!$A$2:$A$49,"Chilevisión",'Líneas codificadas'!$B$2:$B$49,"H1 2026")=0,"n.d.",SUMIFS('Líneas codificadas'!$E$2:$E$49,'Líneas codificadas'!$A$2:$A$49,"Chilevisión",'Líneas codificadas'!$B$2:$B$49,"H1 2026")/SUMIFS('Líneas codificadas'!$E$2:$E$49,'Líneas codificadas'!$A$2:$A$49,"Chilevisión",'Líneas codificadas'!$B$2:$B$49,"H1 2026")) -> 1
A19: NIVEL 2 — Común máximo (% de ingresos de actividades ordinarias)
A20: Canal | B20: Categoría | C20: FY2024 | D20: FY2025 | E20: H1 2025 | F20: H1 2026
A21: TVN | B21: Publicidad | C21: =IF(SUMIFS('Líneas codificadas'!$E$2:$E$49,'Líneas codificadas'!$A$2:$A$49,"TVN",'Líneas codificadas'!$B$2:$B$49,"FY2024")=0,"n.d.",SUMIFS('Líneas codificadas'!$E$2:$E$49,'Líneas codificadas'!$A$2:$A$49,"TVN",'Líneas codificadas'!$B$2:$B$49,"FY2024",'Líneas codificadas'!$O$2:$O$49,"Publicidad")/SUMIFS('Líneas codificadas'!$E$2:$E$49,'Líneas codificadas'!$A$2:$A$49,"TVN",'Líneas codificadas'!$B$2:$B$49,"FY2024")) -> 0.63528699 | D21: =IF(SUMIFS('Líneas codificadas'!$E$2:$E$49,'Líneas codificadas'!$A$2:$A$49,"TVN",'Líneas codificadas'!$B$2:$B$49,"FY2025")=0,"n.d.",SUMIFS('Líneas codificadas'!$E$2:$E$49,'Líneas codificadas'!$A$2:$A$49,"TVN",'Líneas codificadas'!$B$2:$B$49,"FY2025",'Líneas codificadas'!$O$2:$O$49,"Publicidad")/SUMIFS('Líneas codificadas'!$E$2:$E$49,'Líneas codificadas'!$A$2:$A$49,"TVN",'Líneas codificadas'!$B$2:$B$49,"FY2025")) -> 0.60080217 | E21: =IF(SUMIFS('Líneas codificadas'!$E$2:$E$49,'Líneas codificadas'!$A$2:$A$49,"TVN",'Líneas codificadas'!$B$2:$B$49,"H1 2025")=0,"n.d.",SUMIFS('Líneas codificadas'!$E$2:$E$49,'Líneas codificadas'!$A$2:$A$49,"TVN",'Líneas codificadas'!$B$2:$B$49,"H1 2025",'Líneas codificadas'!$O$2:$O$49,"Publicidad")/SUMIFS('Líneas codificadas'!$E$2:$E$49,'Líneas codificadas'!$A$2:$A$49,"TVN",'Líneas codificadas'!$B$2:$B$49,"H1 2025")) -> 0.58156218 | F21: =IF(SUMIFS('Líneas codificadas'!$E$2:$E$49,'Líneas codificadas'!$A$2:$A$49,"TVN",'Líneas codificadas'!$B$2:$B$49,"H1 2026")=0,"n.d.",SUMIFS('Líneas codificadas'!$E$2:$E$49,'Líneas codificadas'!$A$2:$A$49,"TVN",'Líneas codificadas'!$B$2:$B$49,"H1 2026",'Líneas codificadas'!$O$2:$O$49,"Publicidad")/SUMIFS('Líneas codificadas'!$E$2:$E$49,'Líneas codificadas'!$A$2:$A$49,"TVN",'Líneas codificadas'!$B$2:$B$49,"H1 2026")) -> 0.56508885
B22: Otros ingresos operacionales | C22: =IF(SUMIFS('Líneas codificadas'!$E$2:$E$49,'Líneas codificadas'!$A$2:$A$49,"TVN",'Líneas codificadas'!$B$2:$B$49,"FY2024")=0,"n.d.",SUMIFS('Líneas codificadas'!$E$2:$E$49,'Líneas codificadas'!$A$2:$A$49,"TVN",'Líneas codificadas'!$B$2:$B$49,"FY2024",'Líneas codificadas'!$O$2:$O$49,"Otros ingresos operacionales")/SUMIFS('Líneas codificadas'!$E$2:$E$49,'Líneas codificadas'!$A$2:$A$49,"TVN",'Líneas codificadas'!$B$2:$B$49,"FY2024")) -> 0.36471301 | D22: =IF(SUMIFS('Líneas codificadas'!$E$2:$E$49,'Líneas codificadas'!$A$2:$A$49,"TVN",'Líneas codificadas'!$B$2:$B$49,"FY2025")=0,"n.d.",SUMIFS('Líneas codificadas'!$E$2:$E$49,'Líneas codificadas'!$A$2:$A$49,"TVN",'Líneas codificadas'!$B$2:$B$49,"FY2025",'Líneas codificadas'!$O$2:$O$49,"Otros ingresos operacionales")/SUMIFS('Líneas codificadas'!$E$2:$E$49,'Líneas codificadas'!$A$2:$A$49,"TVN",'Líneas codificadas'!$B$2:$B$49,"FY2025")) -> 0.3574576 | E22: =IF(SUMIFS('Líneas codificadas'!$E$2:$E$49,'Líneas codificadas'!$A$2:$A$49,"TVN",'Líneas codificadas'!$B$2:$B$49,"H1 2025")=0,"n.d.",SUMIFS('Líneas codificadas'!$E$2:$E$49,'Líneas codificadas'!$A$2:$A$49,"TVN",'Líneas codificadas'!$B$2:$B$49,"H1 2025",'Líneas codificadas'!$O$2:$O$49,"Otros ingresos operacionales")/SUMIFS('Líneas codificadas'!$E$2:$E$49,'Líneas codificadas'!$A$2:$A$49,"TVN",'Líneas codificadas'!$B$2:$B$49,"H1 2025")) -> 0.33592015 | F22: =IF(SUMIFS('Líneas codificadas'!$E$2:$E$49,'Líneas codificadas'!$A$2:$A$49,"TVN",'Líneas codificadas'!$B$2:$B$49,"H1 2026")=0,"n.d.",SUMIFS('Líneas codificadas'!$E$2:$E$49,'Líneas codificadas'!$A$2:$A$49,"TVN",'Líneas codificadas'!$B$2:$B$49,"H1 2026",'Líneas codificadas'!$O$2:$O$49,"Otros ingresos operacionales")/SUMIFS('Líneas codificadas'!$E$2:$E$49,'Líneas codificadas'!$A$2:$A$49,"TVN",'Líneas codificadas'!$B$2:$B$49,"H1 2026")) -> 0.35848105
B23: Transferencias del Estado | C23: =IF(SUMIFS('Líneas codificadas'!$E$2:$E$49,'Líneas codificadas'!$A$2:$A$49,"TVN",'Líneas codificadas'!$B$2:$B$49,"FY2024")=0,"n.d.",SUMIFS('Líneas codificadas'!$E$2:$E$49,'Líneas codificadas'!$A$2:$A$49,"TVN",'Líneas codificadas'!$B$2:$B$49,"FY2024",'Líneas codificadas'!$O$2:$O$49,"Transferencias del Estado")/SUMIFS('Líneas codificadas'!$E$2:$E$49,'Líneas codificadas'!$A$2:$A$49,"TVN",'Líneas codificadas'!$B$2:$B$49,"FY2024")) -> 0 | D23: =IF(SUMIFS('Líneas codificadas'!$E$2:$E$49,'Líneas codificadas'!$A$2:$A$49,"TVN",'Líneas codificadas'!$B$2:$B$49,"FY2025")=0,"n.d.",SUMIFS('Líneas codificadas'!$E$2:$E$49,'Líneas codificadas'!$A$2:$A$49,"TVN",'Líneas codificadas'!$B$2:$B$49,"FY2025",'Líneas codificadas'!$O$2:$O$49,"Transferencias del Estado")/SUMIFS('Líneas codificadas'!$E$2:$E$49,'Líneas codificadas'!$A$2:$A$49,"TVN",'Líneas codificadas'!$B$2:$B$49,"FY2025")) -> 0.041740236 | E23: =IF(SUMIFS('Líneas codificadas'!$E$2:$E$49,'Líneas codificadas'!$A$2:$A$49,"TVN",'Líneas codificadas'!$B$2:$B$49,"H1 2025")=0,"n.d.",SUMIFS('Líneas codificadas'!$E$2:$E$49,'Líneas codificadas'!$A$2:$A$49,"TVN",'Líneas codificadas'!$B$2:$B$49,"H1 2025",'Líneas codificadas'!$O$2:$O$49,"Transferencias del Estado")/SUMIFS('Líneas codificadas'!$E$2:$E$49,'Líneas codificadas'!$A$2:$A$49,"TVN",'Líneas codificadas'!$B$2:$B$49,"H1 2025")) -> 0.08251767 | F23: =IF(SUMIFS('Líneas codificadas'!$E$2:$E$49,'Líneas codificadas'!$A$2:$A$49,"TVN",'Líneas codificadas'!$B$2:$B$49,"H1 2026")=0,"n.d.",SUMIFS('Líneas codificadas'!$E$2:$E$49,'Líneas codificadas'!$A$2:$A$49,"TVN",'Líneas codificadas'!$B$2:$B$49,"H1 2026",'Líneas codificadas'!$O$2:$O$49,"Transferencias del Estado")/SUMIFS('Líneas codificadas'!$E$2:$E$49,'Líneas codificadas'!$A$2:$A$49,"TVN",'Líneas codificadas'!$B$2:$B$49,"H1 2026")) -> 0.076430101
B24: Total | C24: =IF(SUMIFS('Líneas codificadas'!$E$2:$E$49,'Líneas codificadas'!$A$2:$A$49,"TVN",'Líneas codificadas'!$B$2:$B$49,"FY2024")=0,"n.d.",SUMIFS('Líneas codificadas'!$E$2:$E$49,'Líneas codificadas'!$A$2:$A$49,"TVN",'Líneas codificadas'!$B$2:$B$49,"FY2024")/SUMIFS('Líneas codificadas'!$E$2:$E$49,'Líneas codificadas'!$A$2:$A$49,"TVN",'Líneas codificadas'!$B$2:$B$49,"FY2024")) -> 1 | D24: =IF(SUMIFS('Líneas codificadas'!$E$2:$E$49,'Líneas codificadas'!$A$2:$A$49,"TVN",'Líneas codificadas'!$B$2:$B$49,"FY2025")=0,"n.d.",SUMIFS('Líneas codificadas'!$E$2:$E$49,'Líneas codificadas'!$A$2:$A$49,"TVN",'Líneas codificadas'!$B$2:$B$49,"FY2025")/SUMIFS('Líneas codificadas'!$E$2:$E$49,'Líneas codificadas'!$A$2:$A$49,"TVN",'Líneas codificadas'!$B$2:$B$49,"FY2025")) -> 1 | E24: =IF(SUMIFS('Líneas codificadas'!$E$2:$E$49,'Líneas codificadas'!$A$2:$A$49,"TVN",'Líneas codificadas'!$B$2:$B$49,"H1 2025")=0,"n.d.",SUMIFS('Líneas codificadas'!$E$2:$E$49,'Líneas codificadas'!$A$2:$A$49,"TVN",'Líneas codificadas'!$B$2:$B$49,"H1 2025")/SUMIFS('Líneas codificadas'!$E$2:$E$49,'Líneas codificadas'!$A$2:$A$49,"TVN",'Líneas codificadas'!$B$2:$B$49,"H1 2025")) -> 1 | F24: =IF(SUMIFS('Líneas codificadas'!$E$2:$E$49,'Líneas codificadas'!$A$2:$A$49,"TVN",'Líneas codificadas'!$B$2:$B$49,"H1 2026")=0,"n.d.",SUMIFS('Líneas codificadas'!$E$2:$E$49,'Líneas codificadas'!$A$2:$A$49,"TVN",'Líneas codificadas'!$B$2:$B$49,"H1 2026")/SUMIFS('Líneas codificadas'!$E$2:$E$49,'Líneas codificadas'!$A$2:$A$49,"TVN",'Líneas codificadas'!$B$2:$B$49,"H1 2026")) -> 1
A25: Canal 13 | B25: Publicidad | C25: =IF(SUMIFS('Líneas codificadas'!$E$2:$E$49,'Líneas codificadas'!$A$2:$A$49,"Canal 13",'Líneas codificadas'!$B$2:$B$49,"FY2024")=0,"n.d.",SUMIFS('Líneas codificadas'!$E$2:$E$49,'Líneas codificadas'!$A$2:$A$49,"Canal 13",'Líneas codificadas'!$B$2:$B$49,"FY2024",'Líneas codificadas'!$O$2:$O$49,"Publicidad")/SUMIFS('Líneas codificadas'!$E$2:$E$49,'Líneas codificadas'!$A$2:$A$49,"Canal 13",'Líneas codificadas'!$B$2:$B$49,"FY2024")) -> 0.75965797 | D25: =IF(SUMIFS('Líneas codificadas'!$E$2:$E$49,'Líneas codificadas'!$A$2:$A$49,"Canal 13",'Líneas codificadas'!$B$2:$B$49,"FY2025")=0,"n.d.",SUMIFS('Líneas codificadas'!$E$2:$E$49,'Líneas codificadas'!$A$2:$A$49,"Canal 13",'Líneas codificadas'!$B$2:$B$49,"FY2025",'Líneas codificadas'!$O$2:$O$49,"Publicidad")/SUMIFS('Líneas codificadas'!$E$2:$E$49,'Líneas codificadas'!$A$2:$A$49,"Canal 13",'Líneas codificadas'!$B$2:$B$49,"FY2025")) -> 0.76724611 | E25: =IF(SUMIFS('Líneas codificadas'!$E$2:$E$49,'Líneas codificadas'!$A$2:$A$49,"Canal 13",'Líneas codificadas'!$B$2:$B$49,"H1 2025")=0,"n.d.",SUMIFS('Líneas codificadas'!$E$2:$E$49,'Líneas codificadas'!$A$2:$A$49,"Canal 13",'Líneas codificadas'!$B$2:$B$49,"H1 2025",'Líneas codificadas'!$O$2:$O$49,"Publicidad")/SUMIFS('Líneas codificadas'!$E$2:$E$49,'Líneas codificadas'!$A$2:$A$49,"Canal 13",'Líneas codificadas'!$B$2:$B$49,"H1 2025")) -> 0.75688188 | F25: =IF(SUMIFS('Líneas codificadas'!$E$2:$E$49,'Líneas codificadas'!$A$2:$A$49,"Canal 13",'Líneas codificadas'!$B$2:$B$49,"H1 2026")=0,"n.d.",SUMIFS('Líneas codificadas'!$E$2:$E$49,'Líneas codificadas'!$A$2:$A$49,"Canal 13",'Líneas codificadas'!$B$2:$B$49,"H1 2026",'Líneas codificadas'!$O$2:$O$49,"Publicidad")/SUMIFS('Líneas codificadas'!$E$2:$E$49,'Líneas codificadas'!$A$2:$A$49,"Canal 13",'Líneas codificadas'!$B$2:$B$49,"H1 2026")) -> 0.70870179
B26: Otros ingresos operacionales | C26: =IF(SUMIFS('Líneas codificadas'!$E$2:$E$49,'Líneas codificadas'!$A$2:$A$49,"Canal 13",'Líneas codificadas'!$B$2:$B$49,"FY2024")=0,"n.d.",SUMIFS('Líneas codificadas'!$E$2:$E$49,'Líneas codificadas'!$A$2:$A$49,"Canal 13",'Líneas codificadas'!$B$2:$B$49,"FY2024",'Líneas codificadas'!$O$2:$O$49,"Otros ingresos operacionales")/SUMIFS('Líneas codificadas'!$E$2:$E$49,'Líneas codificadas'!$A$2:$A$49,"Canal 13",'Líneas codificadas'!$B$2:$B$49,"FY2024")) -> 0.24034203 | D26: =IF(SUMIFS('Líneas codificadas'!$E$2:$E$49,'Líneas codificadas'!$A$2:$A$49,"Canal 13",'Líneas codificadas'!$B$2:$B$49,"FY2025")=0,"n.d.",SUMIFS('Líneas codificadas'!$E$2:$E$49,'Líneas codificadas'!$A$2:$A$49,"Canal 13",'Líneas codificadas'!$B$2:$B$49,"FY2025",'Líneas codificadas'!$O$2:$O$49,"Otros ingresos operacionales")/SUMIFS('Líneas codificadas'!$E$2:$E$49,'Líneas codificadas'!$A$2:$A$49,"Canal 13",'Líneas codificadas'!$B$2:$B$49,"FY2025")) -> 0.23275389 | E26: =IF(SUMIFS('Líneas codificadas'!$E$2:$E$49,'Líneas codificadas'!$A$2:$A$49,"Canal 13",'Líneas codificadas'!$B$2:$B$49,"H1 2025")=0,"n.d.",SUMIFS('Líneas codificadas'!$E$2:$E$49,'Líneas codificadas'!$A$2:$A$49,"Canal 13",'Líneas codificadas'!$B$2:$B$49,"H1 2025",'Líneas codificadas'!$O$2:$O$49,"Otros ingresos operacionales")/SUMIFS('Líneas codificadas'!$E$2:$E$49,'Líneas codificadas'!$A$2:$A$49,"Canal 13",'Líneas codificadas'!$B$2:$B$49,"H1 2025")) -> 0.24311812 | F26: =IF(SUMIFS('Líneas codificadas'!$E$2:$E$49,'Líneas codificadas'!$A$2:$A$49,"Canal 13",'Líneas codificadas'!$B$2:$B$49,"H1 2026")=0,"n.d.",SUMIFS('Líneas codificadas'!$E$2:$E$49,'Líneas codificadas'!$A$2:$A$49,"Canal 13",'Líneas codificadas'!$B$2:$B$49,"H1 2026",'Líneas codificadas'!$O$2:$O$49,"Otros ingresos operacionales")/SUMIFS('Líneas codificadas'!$E$2:$E$49,'Líneas codificadas'!$A$2:$A$49,"Canal 13",'Líneas codificadas'!$B$2:$B$49,"H1 2026")) -> 0.29129821
B27: Transferencias del Estado | C27: =IF(SUMIFS('Líneas codificadas'!$E$2:$E$49,'Líneas codificadas'!$A$2:$A$49,"Canal 13",'Líneas codificadas'!$B$2:$B$49,"FY2024")=0,"n.d.",SUMIFS('Líneas codificadas'!$E$2:$E$49,'Líneas codificadas'!$A$2:$A$49,"Canal 13",'Líneas codificadas'!$B$2:$B$49,"FY2024",'Líneas codificadas'!$O$2:$O$49,"Transferencias del Estado")/SUMIFS('Líneas codificadas'!$E$2:$E$49,'Líneas codificadas'!$A$2:$A$49,"Canal 13",'Líneas codificadas'!$B$2:$B$49,"FY2024")) -> 0 | D27: =IF(SUMIFS('Líneas codificadas'!$E$2:$E$49,'Líneas codificadas'!$A$2:$A$49,"Canal 13",'Líneas codificadas'!$B$2:$B$49,"FY2025")=0,"n.d.",SUMIFS('Líneas codificadas'!$E$2:$E$49,'Líneas codificadas'!$A$2:$A$49,"Canal 13",'Líneas codificadas'!$B$2:$B$49,"FY2025",'Líneas codificadas'!$O$2:$O$49,"Transferencias del Estado")/SUMIFS('Líneas codificadas'!$E$2:$E$49,'Líneas codificadas'!$A$2:$A$49,"Canal 13",'Líneas codificadas'!$B$2:$B$49,"FY2025")) -> 0 | E27: =IF(SUMIFS('Líneas codificadas'!$E$2:$E$49,'Líneas codificadas'!$A$2:$A$49,"Canal 13",'Líneas codificadas'!$B$2:$B$49,"H1 2025")=0,"n.d.",SUMIFS('Líneas codificadas'!$E$2:$E$49,'Líneas codificadas'!$A$2:$A$49,"Canal 13",'Líneas codificadas'!$B$2:$B$49,"H1 2025",'Líneas codificadas'!$O$2:$O$49,"Transferencias del Estado")/SUMIFS('Líneas codificadas'!$E$2:$E$49,'Líneas codificadas'!$A$2:$A$49,"Canal 13",'Líneas codificadas'!$B$2:$B$49,"H1 2025")) -> 0 | F27: =IF(SUMIFS('Líneas codificadas'!$E$2:$E$49,'Líneas codificadas'!$A$2:$A$49,"Canal 13",'Líneas codificadas'!$B$2:$B$49,"H1 2026")=0,"n.d.",SUMIFS('Líneas codificadas'!$E$2:$E$49,'Líneas codificadas'!$A$2:$A$49,"Canal 13",'Líneas codificadas'!$B$2:$B$49,"H1 2026",'Líneas codificadas'!$O$2:$O$49,"Transferencias del Estado")/SUMIFS('Líneas codificadas'!$E$2:$E$49,'Líneas codificadas'!$A$2:$A$49,"Canal 13",'Líneas codificadas'!$B$2:$B$49,"H1 2026")) -> 0
B28: Total | C28: =IF(SUMIFS('Líneas codificadas'!$E$2:$E$49,'Líneas codificadas'!$A$2:$A$49,"Canal 13",'Líneas codificadas'!$B$2:$B$49,"FY2024")=0,"n.d.",SUMIFS('Líneas codificadas'!$E$2:$E$49,'Líneas codificadas'!$A$2:$A$49,"Canal 13",'Líneas codificadas'!$B$2:$B$49,"FY2024")/SUMIFS('Líneas codificadas'!$E$2:$E$49,'Líneas codificadas'!$A$2:$A$49,"Canal 13",'Líneas codificadas'!$B$2:$B$49,"FY2024")) -> 1 | D28: =IF(SUMIFS('Líneas codificadas'!$E$2:$E$49,'Líneas codificadas'!$A$2:$A$49,"Canal 13",'Líneas codificadas'!$B$2:$B$49,"FY2025")=0,"n.d.",SUMIFS('Líneas codificadas'!$E$2:$E$49,'Líneas codificadas'!$A$2:$A$49,"Canal 13",'Líneas codificadas'!$B$2:$B$49,"FY2025")/SUMIFS('Líneas codificadas'!$E$2:$E$49,'Líneas codificadas'!$A$2:$A$49,"Canal 13",'Líneas codificadas'!$B$2:$B$49,"FY2025")) -> 1 | E28: =IF(SUMIFS('Líneas codificadas'!$E$2:$E$49,'Líneas codificadas'!$A$2:$A$49,"Canal 13",'Líneas codificadas'!$B$2:$B$49,"H1 2025")=0,"n.d.",SUMIFS('Líneas codificadas'!$E$2:$E$49,'Líneas codificadas'!$A$2:$A$49,"Canal 13",'Líneas codificadas'!$B$2:$B$49,"H1 2025")/SUMIFS('Líneas codificadas'!$E$2:$E$49,'Líneas codificadas'!$A$2:$A$49,"Canal 13",'Líneas codificadas'!$B$2:$B$49,"H1 2025")) -> 1 | F28: =IF(SUMIFS('Líneas codificadas'!$E$2:$E$49,'Líneas codificadas'!$A$2:$A$49,"Canal 13",'Líneas codificadas'!$B$2:$B$49,"H1 2026")=0,"n.d.",SUMIFS('Líneas codificadas'!$E$2:$E$49,'Líneas codificadas'!$A$2:$A$49,"Canal 13",'Líneas codificadas'!$B$2:$B$49,"H1 2026")/SUMIFS('Líneas codificadas'!$E$2:$E$49,'Líneas codificadas'!$A$2:$A$49,"Canal 13",'Líneas codificadas'!$B$2:$B$49,"H1 2026")) -> 1
A29: Mega | B29: Publicidad | C29: =IF(SUMIFS('Líneas codificadas'!$E$2:$E$49,'Líneas codificadas'!$A$2:$A$49,"Mega",'Líneas codificadas'!$B$2:$B$49,"FY2024")=0,"n.d.",SUMIFS('Líneas codificadas'!$E$2:$E$49,'Líneas codificadas'!$A$2:$A$49,"Mega",'Líneas codificadas'!$B$2:$B$49,"FY2024",'Líneas codificadas'!$O$2:$O$49,"Publicidad")/SUMIFS('Líneas codificadas'!$E$2:$E$49,'Líneas codificadas'!$A$2:$A$49,"Mega",'Líneas codificadas'!$B$2:$B$49,"FY2024")) -> 0.75694926 | D29: =IF(SUMIFS('Líneas codificadas'!$E$2:$E$49,'Líneas codificadas'!$A$2:$A$49,"Mega",'Líneas codificadas'!$B$2:$B$49,"FY2025")=0,"n.d.",SUMIFS('Líneas codificadas'!$E$2:$E$49,'Líneas codificadas'!$A$2:$A$49,"Mega",'Líneas codificadas'!$B$2:$B$49,"FY2025",'Líneas codificadas'!$O$2:$O$49,"Publicidad")/SUMIFS('Líneas codificadas'!$E$2:$E$49,'Líneas codificadas'!$A$2:$A$49,"Mega",'Líneas codificadas'!$B$2:$B$49,"FY2025")) -> 0.78894747 | E29: =IF(SUMIFS('Líneas codificadas'!$E$2:$E$49,'Líneas codificadas'!$A$2:$A$49,"Mega",'Líneas codificadas'!$B$2:$B$49,"H1 2025")=0,"n.d.",SUMIFS('Líneas codificadas'!$E$2:$E$49,'Líneas codificadas'!$A$2:$A$49,"Mega",'Líneas codificadas'!$B$2:$B$49,"H1 2025",'Líneas codificadas'!$O$2:$O$49,"Publicidad")/SUMIFS('Líneas codificadas'!$E$2:$E$49,'Líneas codificadas'!$A$2:$A$49,"Mega",'Líneas codificadas'!$B$2:$B$49,"H1 2025")) -> 0.72585315 | F29: =IF(SUMIFS('Líneas codificadas'!$E$2:$E$49,'Líneas codificadas'!$A$2:$A$49,"Mega",'Líneas codificadas'!$B$2:$B$49,"H1 2026")=0,"n.d.",SUMIFS('Líneas codificadas'!$E$2:$E$49,'Líneas codificadas'!$A$2:$A$49,"Mega",'Líneas codificadas'!$B$2:$B$49,"H1 2026",'Líneas codificadas'!$O$2:$O$49,"Publicidad")/SUMIFS('Líneas codificadas'!$E$2:$E$49,'Líneas codificadas'!$A$2:$A$49,"Mega",'Líneas codificadas'!$B$2:$B$49,"H1 2026")) -> 0.82096326
B30: Otros ingresos operacionales | C30: =IF(SUMIFS('Líneas codificadas'!$E$2:$E$49,'Líneas codificadas'!$A$2:$A$49,"Mega",'Líneas codificadas'!$B$2:$B$49,"FY2024")=0,"n.d.",SUMIFS('Líneas codificadas'!$E$2:$E$49,'Líneas codificadas'!$A$2:$A$49,"Mega",'Líneas codificadas'!$B$2:$B$49,"FY2024",'Líneas codificadas'!$O$2:$O$49,"Otros ingresos operacionales")/SUMIFS('Líneas codificadas'!$E$2:$E$49,'Líneas codificadas'!$A$2:$A$49,"Mega",'Líneas codificadas'!$B$2:$B$49,"FY2024")) -> 0.24305074 | D30: =IF(SUMIFS('Líneas codificadas'!$E$2:$E$49,'Líneas codificadas'!$A$2:$A$49,"Mega",'Líneas codificadas'!$B$2:$B$49,"FY2025")=0,"n.d.",SUMIFS('Líneas codificadas'!$E$2:$E$49,'Líneas codificadas'!$A$2:$A$49,"Mega",'Líneas codificadas'!$B$2:$B$49,"FY2025",'Líneas codificadas'!$O$2:$O$49,"Otros ingresos operacionales")/SUMIFS('Líneas codificadas'!$E$2:$E$49,'Líneas codificadas'!$A$2:$A$49,"Mega",'Líneas codificadas'!$B$2:$B$49,"FY2025")) -> 0.21105253 | E30: =IF(SUMIFS('Líneas codificadas'!$E$2:$E$49,'Líneas codificadas'!$A$2:$A$49,"Mega",'Líneas codificadas'!$B$2:$B$49,"H1 2025")=0,"n.d.",SUMIFS('Líneas codificadas'!$E$2:$E$49,'Líneas codificadas'!$A$2:$A$49,"Mega",'Líneas codificadas'!$B$2:$B$49,"H1 2025",'Líneas codificadas'!$O$2:$O$49,"Otros ingresos operacionales")/SUMIFS('Líneas codificadas'!$E$2:$E$49,'Líneas codificadas'!$A$2:$A$49,"Mega",'Líneas codificadas'!$B$2:$B$49,"H1 2025")) -> 0.27414685 | F30: =IF(SUMIFS('Líneas codificadas'!$E$2:$E$49,'Líneas codificadas'!$A$2:$A$49,"Mega",'Líneas codificadas'!$B$2:$B$49,"H1 2026")=0,"n.d.",SUMIFS('Líneas codificadas'!$E$2:$E$49,'Líneas codificadas'!$A$2:$A$49,"Mega",'Líneas codificadas'!$B$2:$B$49,"H1 2026",'Líneas codificadas'!$O$2:$O$49,"Otros ingresos operacionales")/SUMIFS('Líneas codificadas'!$E$2:$E$49,'Líneas codificadas'!$A$2:$A$49,"Mega",'Líneas codificadas'!$B$2:$B$49,"H1 2026")) -> 0.17903674
B31: Transferencias del Estado | C31: =IF(SUMIFS('Líneas codificadas'!$E$2:$E$49,'Líneas codificadas'!$A$2:$A$49,"Mega",'Líneas codificadas'!$B$2:$B$49,"FY2024")=0,"n.d.",SUMIFS('Líneas codificadas'!$E$2:$E$49,'Líneas codificadas'!$A$2:$A$49,"Mega",'Líneas codificadas'!$B$2:$B$49,"FY2024",'Líneas codificadas'!$O$2:$O$49,"Transferencias del Estado")/SUMIFS('Líneas codificadas'!$E$2:$E$49,'Líneas codificadas'!$A$2:$A$49,"Mega",'Líneas codificadas'!$B$2:$B$49,"FY2024")) -> 0 | D31: =IF(SUMIFS('Líneas codificadas'!$E$2:$E$49,'Líneas codificadas'!$A$2:$A$49,"Mega",'Líneas codificadas'!$B$2:$B$49,"FY2025")=0,"n.d.",SUMIFS('Líneas codificadas'!$E$2:$E$49,'Líneas codificadas'!$A$2:$A$49,"Mega",'Líneas codificadas'!$B$2:$B$49,"FY2025",'Líneas codificadas'!$O$2:$O$49,"Transferencias del Estado")/SUMIFS('Líneas codificadas'!$E$2:$E$49,'Líneas codificadas'!$A$2:$A$49,"Mega",'Líneas codificadas'!$B$2:$B$49,"FY2025")) -> 0 | E31: =IF(SUMIFS('Líneas codificadas'!$E$2:$E$49,'Líneas codificadas'!$A$2:$A$49,"Mega",'Líneas codificadas'!$B$2:$B$49,"H1 2025")=0,"n.d.",SUMIFS('Líneas codificadas'!$E$2:$E$49,'Líneas codificadas'!$A$2:$A$49,"Mega",'Líneas codificadas'!$B$2:$B$49,"H1 2025",'Líneas codificadas'!$O$2:$O$49,"Transferencias del Estado")/SUMIFS('Líneas codificadas'!$E$2:$E$49,'Líneas codificadas'!$A$2:$A$49,"Mega",'Líneas codificadas'!$B$2:$B$49,"H1 2025")) -> 0 | F31: =IF(SUMIFS('Líneas codificadas'!$E$2:$E$49,'Líneas codificadas'!$A$2:$A$49,"Mega",'Líneas codificadas'!$B$2:$B$49,"H1 2026")=0,"n.d.",SUMIFS('Líneas codificadas'!$E$2:$E$49,'Líneas codificadas'!$A$2:$A$49,"Mega",'Líneas codificadas'!$B$2:$B$49,"H1 2026",'Líneas codificadas'!$O$2:$O$49,"Transferencias del Estado")/SUMIFS('Líneas codificadas'!$E$2:$E$49,'Líneas codificadas'!$A$2:$A$49,"Mega",'Líneas codificadas'!$B$2:$B$49,"H1 2026")) -> 0
B32: Total | C32: =IF(SUMIFS('Líneas codificadas'!$E$2:$E$49,'Líneas codificadas'!$A$2:$A$49,"Mega",'Líneas codificadas'!$B$2:$B$49,"FY2024")=0,"n.d.",SUMIFS('Líneas codificadas'!$E$2:$E$49,'Líneas codificadas'!$A$2:$A$49,"Mega",'Líneas codificadas'!$B$2:$B$49,"FY2024")/SUMIFS('Líneas codificadas'!$E$2:$E$49,'Líneas codificadas'!$A$2:$A$49,"Mega",'Líneas codificadas'!$B$2:$B$49,"FY2024")) -> 1 | D32: =IF(SUMIFS('Líneas codificadas'!$E$2:$E$49,'Líneas codificadas'!$A$2:$A$49,"Mega",'Líneas codificadas'!$B$2:$B$49,"FY2025")=0,"n.d.",SUMIFS('Líneas codificadas'!$E$2:$E$49,'Líneas codificadas'!$A$2:$A$49,"Mega",'Líneas codificadas'!$B$2:$B$49,"FY2025")/SUMIFS('Líneas codificadas'!$E$2:$E$49,'Líneas codificadas'!$A$2:$A$49,"Mega",'Líneas codificadas'!$B$2:$B$49,"FY2025")) -> 1 | E32: =IF(SUMIFS('Líneas codificadas'!$E$2:$E$49,'Líneas codificadas'!$A$2:$A$49,"Mega",'Líneas codificadas'!$B$2:$B$49,"H1 2025")=0,"n.d.",SUMIFS('Líneas codificadas'!$E$2:$E$49,'Líneas codificadas'!$A$2:$A$49,"Mega",'Líneas codificadas'!$B$2:$B$49,"H1 2025")/SUMIFS('Líneas codificadas'!$E$2:$E$49,'Líneas codificadas'!$A$2:$A$49,"Mega",'Líneas codificadas'!$B$2:$B$49,"H1 2025")) -> 1 | F32: =IF(SUMIFS('Líneas codificadas'!$E$2:$E$49,'Líneas codificadas'!$A$2:$A$49,"Mega",'Líneas codificadas'!$B$2:$B$49,"H1 2026")=0,"n.d.",SUMIFS('Líneas codificadas'!$E$2:$E$49,'Líneas codificadas'!$A$2:$A$49,"Mega",'Líneas codificadas'!$B$2:$B$49,"H1 2026")/SUMIFS('Líneas codificadas'!$E$2:$E$49,'Líneas codificadas'!$A$2:$A$49,"Mega",'Líneas codificadas'!$B$2:$B$49,"H1 2026")) -> 1
A33: Chilevisión | B33: Publicidad | C33: =IF(SUMIFS('Líneas codificadas'!$E$2:$E$49,'Líneas codificadas'!$A$2:$A$49,"Chilevisión",'Líneas codificadas'!$B$2:$B$49,"FY2024")=0,"n.d.",SUMIFS('Líneas codificadas'!$E$2:$E$49,'Líneas codificadas'!$A$2:$A$49,"Chilevisión",'Líneas codificadas'!$B$2:$B$49,"FY2024",'Líneas codificadas'!$O$2:$O$49,"Publicidad")/SUMIFS('Líneas codificadas'!$E$2:$E$49,'Líneas codificadas'!$A$2:$A$49,"Chilevisión",'Líneas codificadas'!$B$2:$B$49,"FY2024")) -> 0.91045902 | D33: =IF(SUMIFS('Líneas codificadas'!$E$2:$E$49,'Líneas codificadas'!$A$2:$A$49,"Chilevisión",'Líneas codificadas'!$B$2:$B$49,"FY2025")=0,"n.d.",SUMIFS('Líneas codificadas'!$E$2:$E$49,'Líneas codificadas'!$A$2:$A$49,"Chilevisión",'Líneas codificadas'!$B$2:$B$49,"FY2025",'Líneas codificadas'!$O$2:$O$49,"Publicidad")/SUMIFS('Líneas codificadas'!$E$2:$E$49,'Líneas codificadas'!$A$2:$A$49,"Chilevisión",'Líneas codificadas'!$B$2:$B$49,"FY2025")) -> 0.89632396 | E33: =IF(SUMIFS('Líneas codificadas'!$E$2:$E$49,'Líneas codificadas'!$A$2:$A$49,"Chilevisión",'Líneas codificadas'!$B$2:$B$49,"H1 2025")=0,"n.d.",SUMIFS('Líneas codificadas'!$E$2:$E$49,'Líneas codificadas'!$A$2:$A$49,"Chilevisión",'Líneas codificadas'!$B$2:$B$49,"H1 2025",'Líneas codificadas'!$O$2:$O$49,"Publicidad")/SUMIFS('Líneas codificadas'!$E$2:$E$49,'Líneas codificadas'!$A$2:$A$49,"Chilevisión",'Líneas codificadas'!$B$2:$B$49,"H1 2025")) -> 0.95082266 | F33: =IF(SUMIFS('Líneas codificadas'!$E$2:$E$49,'Líneas codificadas'!$A$2:$A$49,"Chilevisión",'Líneas codificadas'!$B$2:$B$49,"H1 2026")=0,"n.d.",SUMIFS('Líneas codificadas'!$E$2:$E$49,'Líneas codificadas'!$A$2:$A$49,"Chilevisión",'Líneas codificadas'!$B$2:$B$49,"H1 2026",'Líneas codificadas'!$O$2:$O$49,"Publicidad")/SUMIFS('Líneas codificadas'!$E$2:$E$49,'Líneas codificadas'!$A$2:$A$49,"Chilevisión",'Líneas codificadas'!$B$2:$B$49,"H1 2026")) -> 0.9089824
B34: Otros ingresos operacionales | C34: =IF(SUMIFS('Líneas codificadas'!$E$2:$E$49,'Líneas codificadas'!$A$2:$A$49,"Chilevisión",'Líneas codificadas'!$B$2:$B$49,"FY2024")=0,"n.d.",SUMIFS('Líneas codificadas'!$E$2:$E$49,'Líneas codificadas'!$A$2:$A$49,"Chilevisión",'Líneas codificadas'!$B$2:$B$49,"FY2024",'Líneas codificadas'!$O$2:$O$49,"Otros ingresos operacionales")/SUMIFS('Líneas codificadas'!$E$2:$E$49,'Líneas codificadas'!$A$2:$A$49,"Chilevisión",'Líneas codificadas'!$B$2:$B$49,"FY2024")) -> 0.089540978 | D34: =IF(SUMIFS('Líneas codificadas'!$E$2:$E$49,'Líneas codificadas'!$A$2:$A$49,"Chilevisión",'Líneas codificadas'!$B$2:$B$49,"FY2025")=0,"n.d.",SUMIFS('Líneas codificadas'!$E$2:$E$49,'Líneas codificadas'!$A$2:$A$49,"Chilevisión",'Líneas codificadas'!$B$2:$B$49,"FY2025",'Líneas codificadas'!$O$2:$O$49,"Otros ingresos operacionales")/SUMIFS('Líneas codificadas'!$E$2:$E$49,'Líneas codificadas'!$A$2:$A$49,"Chilevisión",'Líneas codificadas'!$B$2:$B$49,"FY2025")) -> 0.10367604 | E34: =IF(SUMIFS('Líneas codificadas'!$E$2:$E$49,'Líneas codificadas'!$A$2:$A$49,"Chilevisión",'Líneas codificadas'!$B$2:$B$49,"H1 2025")=0,"n.d.",SUMIFS('Líneas codificadas'!$E$2:$E$49,'Líneas codificadas'!$A$2:$A$49,"Chilevisión",'Líneas codificadas'!$B$2:$B$49,"H1 2025",'Líneas codificadas'!$O$2:$O$49,"Otros ingresos operacionales")/SUMIFS('Líneas codificadas'!$E$2:$E$49,'Líneas codificadas'!$A$2:$A$49,"Chilevisión",'Líneas codificadas'!$B$2:$B$49,"H1 2025")) -> 0.049177343 | F34: =IF(SUMIFS('Líneas codificadas'!$E$2:$E$49,'Líneas codificadas'!$A$2:$A$49,"Chilevisión",'Líneas codificadas'!$B$2:$B$49,"H1 2026")=0,"n.d.",SUMIFS('Líneas codificadas'!$E$2:$E$49,'Líneas codificadas'!$A$2:$A$49,"Chilevisión",'Líneas codificadas'!$B$2:$B$49,"H1 2026",'Líneas codificadas'!$O$2:$O$49,"Otros ingresos operacionales")/SUMIFS('Líneas codificadas'!$E$2:$E$49,'Líneas codificadas'!$A$2:$A$49,"Chilevisión",'Líneas codificadas'!$B$2:$B$49,"H1 2026")) -> 0.091017596
B35: Transferencias del Estado | C35: =IF(SUMIFS('Líneas codificadas'!$E$2:$E$49,'Líneas codificadas'!$A$2:$A$49,"Chilevisión",'Líneas codificadas'!$B$2:$B$49,"FY2024")=0,"n.d.",SUMIFS('Líneas codificadas'!$E$2:$E$49,'Líneas codificadas'!$A$2:$A$49,"Chilevisión",'Líneas codificadas'!$B$2:$B$49,"FY2024",'Líneas codificadas'!$O$2:$O$49,"Transferencias del Estado")/SUMIFS('Líneas codificadas'!$E$2:$E$49,'Líneas codificadas'!$A$2:$A$49,"Chilevisión",'Líneas codificadas'!$B$2:$B$49,"FY2024")) -> 0 | D35: =IF(SUMIFS('Líneas codificadas'!$E$2:$E$49,'Líneas codificadas'!$A$2:$A$49,"Chilevisión",'Líneas codificadas'!$B$2:$B$49,"FY2025")=0,"n.d.",SUMIFS('Líneas codificadas'!$E$2:$E$49,'Líneas codificadas'!$A$2:$A$49,"Chilevisión",'Líneas codificadas'!$B$2:$B$49,"FY2025",'Líneas codificadas'!$O$2:$O$49,"Transferencias del Estado")/SUMIFS('Líneas codificadas'!$E$2:$E$49,'Líneas codificadas'!$A$2:$A$49,"Chilevisión",'Líneas codificadas'!$B$2:$B$49,"FY2025")) -> 0 | E35: =IF(SUMIFS('Líneas codificadas'!$E$2:$E$49,'Líneas codificadas'!$A$2:$A$49,"Chilevisión",'Líneas codificadas'!$B$2:$B$49,"H1 2025")=0,"n.d.",SUMIFS('Líneas codificadas'!$E$2:$E$49,'Líneas codificadas'!$A$2:$A$49,"Chilevisión",'Líneas codificadas'!$B$2:$B$49,"H1 2025",'Líneas codificadas'!$O$2:$O$49,"Transferencias del Estado")/SUMIFS('Líneas codificadas'!$E$2:$E$49,'Líneas codificadas'!$A$2:$A$49,"Chilevisión",'Líneas codificadas'!$B$2:$B$49,"H1 2025")) -> 0 | F35: =IF(SUMIFS('Líneas codificadas'!$E$2:$E$49,'Líneas codificadas'!$A$2:$A$49,"Chilevisión",'Líneas codificadas'!$B$2:$B$49,"H1 2026")=0,"n.d.",SUMIFS('Líneas codificadas'!$E$2:$E$49,'Líneas codificadas'!$A$2:$A$49,"Chilevisión",'Líneas codificadas'!$B$2:$B$49,"H1 2026",'Líneas codificadas'!$O$2:$O$49,"Transferencias del Estado")/SUMIFS('Líneas codificadas'!$E$2:$E$49,'Líneas codificadas'!$A$2:$A$49,"Chilevisión",'Líneas codificadas'!$B$2:$B$49,"H1 2026")) -> 0
B36: Total | C36: =IF(SUMIFS('Líneas codificadas'!$E$2:$E$49,'Líneas codificadas'!$A$2:$A$49,"Chilevisión",'Líneas codificadas'!$B$2:$B$49,"FY2024")=0,"n.d.",SUMIFS('Líneas codificadas'!$E$2:$E$49,'Líneas codificadas'!$A$2:$A$49,"Chilevisión",'Líneas codificadas'!$B$2:$B$49,"FY2024")/SUMIFS('Líneas codificadas'!$E$2:$E$49,'Líneas codificadas'!$A$2:$A$49,"Chilevisión",'Líneas codificadas'!$B$2:$B$49,"FY2024")) -> 1 | D36: =IF(SUMIFS('Líneas codificadas'!$E$2:$E$49,'Líneas codificadas'!$A$2:$A$49,"Chilevisión",'Líneas codificadas'!$B$2:$B$49,"FY2025")=0,"n.d.",SUMIFS('Líneas codificadas'!$E$2:$E$49,'Líneas codificadas'!$A$2:$A$49,"Chilevisión",'Líneas codificadas'!$B$2:$B$49,"FY2025")/SUMIFS('Líneas codificadas'!$E$2:$E$49,'Líneas codificadas'!$A$2:$A$49,"Chilevisión",'Líneas codificadas'!$B$2:$B$49,"FY2025")) -> 1 | E36: =IF(SUMIFS('Líneas codificadas'!$E$2:$E$49,'Líneas codificadas'!$A$2:$A$49,"Chilevisión",'Líneas codificadas'!$B$2:$B$49,"H1 2025")=0,"n.d.",SUMIFS('Líneas codificadas'!$E$2:$E$49,'Líneas codificadas'!$A$2:$A$49,"Chilevisión",'Líneas codificadas'!$B$2:$B$49,"H1 2025")/SUMIFS('Líneas codificadas'!$E$2:$E$49,'Líneas codificadas'!$A$2:$A$49,"Chilevisión",'Líneas codificadas'!$B$2:$B$49,"H1 2025")) -> 1 | F36: =IF(SUMIFS('Líneas codificadas'!$E$2:$E$49,'Líneas codificadas'!$A$2:$A$49,"Chilevisión",'Líneas codificadas'!$B$2:$B$49,"H1 2026")=0,"n.d.",SUMIFS('Líneas codificadas'!$E$2:$E$49,'Líneas codificadas'!$A$2:$A$49,"Chilevisión",'Líneas codificadas'!$B$2:$B$49,"H1 2026")/SUMIFS('Líneas codificadas'!$E$2:$E$49,'Líneas codificadas'!$A$2:$A$49,"Chilevisión",'Líneas codificadas'!$B$2:$B$49,"H1 2026")) -> 1
A38: NIVEL 2 — Común máximo (M$)
A39: Canal | B39: Categoría | C39: FY2024 | D39: FY2025 | E39: H1 2025 | F39: H1 2026
A40: TVN | B40: Publicidad | C40: =IF(SUMIFS('Líneas codificadas'!$E$2:$E$49,'Líneas codificadas'!$A$2:$A$49,"TVN",'Líneas codificadas'!$B$2:$B$49,"FY2024")=0,"n.d.",SUMIFS('Líneas codificadas'!$E$2:$E$49,'Líneas codificadas'!$A$2:$A$49,"TVN",'Líneas codificadas'!$B$2:$B$49,"FY2024",'Líneas codificadas'!$O$2:$O$49,"Publicidad")) -> 29763217 | D40: =IF(SUMIFS('Líneas codificadas'!$E$2:$E$49,'Líneas codificadas'!$A$2:$A$49,"TVN",'Líneas codificadas'!$B$2:$B$49,"FY2025")=0,"n.d.",SUMIFS('Líneas codificadas'!$E$2:$E$49,'Líneas codificadas'!$A$2:$A$49,"TVN",'Líneas codificadas'!$B$2:$B$49,"FY2025",'Líneas codificadas'!$O$2:$O$49,"Publicidad")) -> 28787675 | E40: =IF(SUMIFS('Líneas codificadas'!$E$2:$E$49,'Líneas codificadas'!$A$2:$A$49,"TVN",'Líneas codificadas'!$B$2:$B$49,"H1 2025")=0,"n.d.",SUMIFS('Líneas codificadas'!$E$2:$E$49,'Líneas codificadas'!$A$2:$A$49,"TVN",'Líneas codificadas'!$B$2:$B$49,"H1 2025",'Líneas codificadas'!$O$2:$O$49,"Publicidad")) -> 14095458 | F40: =IF(SUMIFS('Líneas codificadas'!$E$2:$E$49,'Líneas codificadas'!$A$2:$A$49,"TVN",'Líneas codificadas'!$B$2:$B$49,"H1 2026")=0,"n.d.",SUMIFS('Líneas codificadas'!$E$2:$E$49,'Líneas codificadas'!$A$2:$A$49,"TVN",'Líneas codificadas'!$B$2:$B$49,"H1 2026",'Líneas codificadas'!$O$2:$O$49,"Publicidad")) -> 12596474
B41: Otros ingresos operacionales | C41: =IF(SUMIFS('Líneas codificadas'!$E$2:$E$49,'Líneas codificadas'!$A$2:$A$49,"TVN",'Líneas codificadas'!$B$2:$B$49,"FY2024")=0,"n.d.",SUMIFS('Líneas codificadas'!$E$2:$E$49,'Líneas codificadas'!$A$2:$A$49,"TVN",'Líneas codificadas'!$B$2:$B$49,"FY2024",'Líneas codificadas'!$O$2:$O$49,"Otros ingresos operacionales")) -> 17086817 | D41: =IF(SUMIFS('Líneas codificadas'!$E$2:$E$49,'Líneas codificadas'!$A$2:$A$49,"TVN",'Líneas codificadas'!$B$2:$B$49,"FY2025")=0,"n.d.",SUMIFS('Líneas codificadas'!$E$2:$E$49,'Líneas codificadas'!$A$2:$A$49,"TVN",'Líneas codificadas'!$B$2:$B$49,"FY2025",'Líneas codificadas'!$O$2:$O$49,"Otros ingresos operacionales")) -> 17127723 | E41: =IF(SUMIFS('Líneas codificadas'!$E$2:$E$49,'Líneas codificadas'!$A$2:$A$49,"TVN",'Líneas codificadas'!$B$2:$B$49,"H1 2025")=0,"n.d.",SUMIFS('Líneas codificadas'!$E$2:$E$49,'Líneas codificadas'!$A$2:$A$49,"TVN",'Líneas codificadas'!$B$2:$B$49,"H1 2025",'Líneas codificadas'!$O$2:$O$49,"Otros ingresos operacionales")) -> 8141775 | F41: =IF(SUMIFS('Líneas codificadas'!$E$2:$E$49,'Líneas codificadas'!$A$2:$A$49,"TVN",'Líneas codificadas'!$B$2:$B$49,"H1 2026")=0,"n.d.",SUMIFS('Líneas codificadas'!$E$2:$E$49,'Líneas codificadas'!$A$2:$A$49,"TVN",'Líneas codificadas'!$B$2:$B$49,"H1 2026",'Líneas codificadas'!$O$2:$O$49,"Otros ingresos operacionales")) -> 7990951
B42: Transferencias del Estado | C42: =IF(SUMIFS('Líneas codificadas'!$E$2:$E$49,'Líneas codificadas'!$A$2:$A$49,"TVN",'Líneas codificadas'!$B$2:$B$49,"FY2024")=0,"n.d.",SUMIFS('Líneas codificadas'!$E$2:$E$49,'Líneas codificadas'!$A$2:$A$49,"TVN",'Líneas codificadas'!$B$2:$B$49,"FY2024",'Líneas codificadas'!$O$2:$O$49,"Transferencias del Estado")) -> 0 | D42: =IF(SUMIFS('Líneas codificadas'!$E$2:$E$49,'Líneas codificadas'!$A$2:$A$49,"TVN",'Líneas codificadas'!$B$2:$B$49,"FY2025")=0,"n.d.",SUMIFS('Líneas codificadas'!$E$2:$E$49,'Líneas codificadas'!$A$2:$A$49,"TVN",'Líneas codificadas'!$B$2:$B$49,"FY2025",'Líneas codificadas'!$O$2:$O$49,"Transferencias del Estado")) -> 2000000 | E42: =IF(SUMIFS('Líneas codificadas'!$E$2:$E$49,'Líneas codificadas'!$A$2:$A$49,"TVN",'Líneas codificadas'!$B$2:$B$49,"H1 2025")=0,"n.d.",SUMIFS('Líneas codificadas'!$E$2:$E$49,'Líneas codificadas'!$A$2:$A$49,"TVN",'Líneas codificadas'!$B$2:$B$49,"H1 2025",'Líneas codificadas'!$O$2:$O$49,"Transferencias del Estado")) -> 2000000 | F42: =IF(SUMIFS('Líneas codificadas'!$E$2:$E$49,'Líneas codificadas'!$A$2:$A$49,"TVN",'Líneas codificadas'!$B$2:$B$49,"H1 2026")=0,"n.d.",SUMIFS('Líneas codificadas'!$E$2:$E$49,'Líneas codificadas'!$A$2:$A$49,"TVN",'Líneas codificadas'!$B$2:$B$49,"H1 2026",'Líneas codificadas'!$O$2:$O$49,"Transferencias del Estado")) -> 1703714
B43: Total | C43: =IF(SUMIFS('Líneas codificadas'!$E$2:$E$49,'Líneas codificadas'!$A$2:$A$49,"TVN",'Líneas codificadas'!$B$2:$B$49,"FY2024")=0,"n.d.",SUMIFS('Líneas codificadas'!$E$2:$E$49,'Líneas codificadas'!$A$2:$A$49,"TVN",'Líneas codificadas'!$B$2:$B$49,"FY2024")) -> 46850034 | D43: =IF(SUMIFS('Líneas codificadas'!$E$2:$E$49,'Líneas codificadas'!$A$2:$A$49,"TVN",'Líneas codificadas'!$B$2:$B$49,"FY2025")=0,"n.d.",SUMIFS('Líneas codificadas'!$E$2:$E$49,'Líneas codificadas'!$A$2:$A$49,"TVN",'Líneas codificadas'!$B$2:$B$49,"FY2025")) -> 47915398 | E43: =IF(SUMIFS('Líneas codificadas'!$E$2:$E$49,'Líneas codificadas'!$A$2:$A$49,"TVN",'Líneas codificadas'!$B$2:$B$49,"H1 2025")=0,"n.d.",SUMIFS('Líneas codificadas'!$E$2:$E$49,'Líneas codificadas'!$A$2:$A$49,"TVN",'Líneas codificadas'!$B$2:$B$49,"H1 2025")) -> 24237233 | F43: =IF(SUMIFS('Líneas codificadas'!$E$2:$E$49,'Líneas codificadas'!$A$2:$A$49,"TVN",'Líneas codificadas'!$B$2:$B$49,"H1 2026")=0,"n.d.",SUMIFS('Líneas codificadas'!$E$2:$E$49,'Líneas codificadas'!$A$2:$A$49,"TVN",'Líneas codificadas'!$B$2:$B$49,"H1 2026")) -> 22291139
A44: Canal 13 | B44: Publicidad | C44: =IF(SUMIFS('Líneas codificadas'!$E$2:$E$49,'Líneas codificadas'!$A$2:$A$49,"Canal 13",'Líneas codificadas'!$B$2:$B$49,"FY2024")=0,"n.d.",SUMIFS('Líneas codificadas'!$E$2:$E$49,'Líneas codificadas'!$A$2:$A$49,"Canal 13",'Líneas codificadas'!$B$2:$B$49,"FY2024",'Líneas codificadas'!$O$2:$O$49,"Publicidad")) -> 59944830 | D44: =IF(SUMIFS('Líneas codificadas'!$E$2:$E$49,'Líneas codificadas'!$A$2:$A$49,"Canal 13",'Líneas codificadas'!$B$2:$B$49,"FY2025")=0,"n.d.",SUMIFS('Líneas codificadas'!$E$2:$E$49,'Líneas codificadas'!$A$2:$A$49,"Canal 13",'Líneas codificadas'!$B$2:$B$49,"FY2025",'Líneas codificadas'!$O$2:$O$49,"Publicidad")) -> 62568555 | E44: =IF(SUMIFS('Líneas codificadas'!$E$2:$E$49,'Líneas codificadas'!$A$2:$A$49,"Canal 13",'Líneas codificadas'!$B$2:$B$49,"H1 2025")=0,"n.d.",SUMIFS('Líneas codificadas'!$E$2:$E$49,'Líneas codificadas'!$A$2:$A$49,"Canal 13",'Líneas codificadas'!$B$2:$B$49,"H1 2025",'Líneas codificadas'!$O$2:$O$49,"Publicidad")) -> 28128285 | F44: =IF(SUMIFS('Líneas codificadas'!$E$2:$E$49,'Líneas codificadas'!$A$2:$A$49,"Canal 13",'Líneas codificadas'!$B$2:$B$49,"H1 2026")=0,"n.d.",SUMIFS('Líneas codificadas'!$E$2:$E$49,'Líneas codificadas'!$A$2:$A$49,"Canal 13",'Líneas codificadas'!$B$2:$B$49,"H1 2026",'Líneas codificadas'!$O$2:$O$49,"Publicidad")) -> 27207041
B45: Otros ingresos operacionales | C45: =IF(SUMIFS('Líneas codificadas'!$E$2:$E$49,'Líneas codificadas'!$A$2:$A$49,"Canal 13",'Líneas codificadas'!$B$2:$B$49,"FY2024")=0,"n.d.",SUMIFS('Líneas codificadas'!$E$2:$E$49,'Líneas codificadas'!$A$2:$A$49,"Canal 13",'Líneas codificadas'!$B$2:$B$49,"FY2024",'Líneas codificadas'!$O$2:$O$49,"Otros ingresos operacionales")) -> 18965459 | D45: =IF(SUMIFS('Líneas codificadas'!$E$2:$E$49,'Líneas codificadas'!$A$2:$A$49,"Canal 13",'Líneas codificadas'!$B$2:$B$49,"FY2025")=0,"n.d.",SUMIFS('Líneas codificadas'!$E$2:$E$49,'Líneas codificadas'!$A$2:$A$49,"Canal 13",'Líneas codificadas'!$B$2:$B$49,"FY2025",'Líneas codificadas'!$O$2:$O$49,"Otros ingresos operacionales")) -> 18980969 | E45: =IF(SUMIFS('Líneas codificadas'!$E$2:$E$49,'Líneas codificadas'!$A$2:$A$49,"Canal 13",'Líneas codificadas'!$B$2:$B$49,"H1 2025")=0,"n.d.",SUMIFS('Líneas codificadas'!$E$2:$E$49,'Líneas codificadas'!$A$2:$A$49,"Canal 13",'Líneas codificadas'!$B$2:$B$49,"H1 2025",'Líneas codificadas'!$O$2:$O$49,"Otros ingresos operacionales")) -> 9035090 | F45: =IF(SUMIFS('Líneas codificadas'!$E$2:$E$49,'Líneas codificadas'!$A$2:$A$49,"Canal 13",'Líneas codificadas'!$B$2:$B$49,"H1 2026")=0,"n.d.",SUMIFS('Líneas codificadas'!$E$2:$E$49,'Líneas codificadas'!$A$2:$A$49,"Canal 13",'Líneas codificadas'!$B$2:$B$49,"H1 2026",'Líneas codificadas'!$O$2:$O$49,"Otros ingresos operacionales")) -> 11182930
B46: Transferencias del Estado | C46: =IF(SUMIFS('Líneas codificadas'!$E$2:$E$49,'Líneas codificadas'!$A$2:$A$49,"Canal 13",'Líneas codificadas'!$B$2:$B$49,"FY2024")=0,"n.d.",SUMIFS('Líneas codificadas'!$E$2:$E$49,'Líneas codificadas'!$A$2:$A$49,"Canal 13",'Líneas codificadas'!$B$2:$B$49,"FY2024",'Líneas codificadas'!$O$2:$O$49,"Transferencias del Estado")) -> 0 | D46: =IF(SUMIFS('Líneas codificadas'!$E$2:$E$49,'Líneas codificadas'!$A$2:$A$49,"Canal 13",'Líneas codificadas'!$B$2:$B$49,"FY2025")=0,"n.d.",SUMIFS('Líneas codificadas'!$E$2:$E$49,'Líneas codificadas'!$A$2:$A$49,"Canal 13",'Líneas codificadas'!$B$2:$B$49,"FY2025",'Líneas codificadas'!$O$2:$O$49,"Transferencias del Estado")) -> 0 | E46: =IF(SUMIFS('Líneas codificadas'!$E$2:$E$49,'Líneas codificadas'!$A$2:$A$49,"Canal 13",'Líneas codificadas'!$B$2:$B$49,"H1 2025")=0,"n.d.",SUMIFS('Líneas codificadas'!$E$2:$E$49,'Líneas codificadas'!$A$2:$A$49,"Canal 13",'Líneas codificadas'!$B$2:$B$49,"H1 2025",'Líneas codificadas'!$O$2:$O$49,"Transferencias del Estado")) -> 0 | F46: =IF(SUMIFS('Líneas codificadas'!$E$2:$E$49,'Líneas codificadas'!$A$2:$A$49,"Canal 13",'Líneas codificadas'!$B$2:$B$49,"H1 2026")=0,"n.d.",SUMIFS('Líneas codificadas'!$E$2:$E$49,'Líneas codificadas'!$A$2:$A$49,"Canal 13",'Líneas codificadas'!$B$2:$B$49,"H1 2026",'Líneas codificadas'!$O$2:$O$49,"Transferencias del Estado")) -> 0
B47: Total | C47: =IF(SUMIFS('Líneas codificadas'!$E$2:$E$49,'Líneas codificadas'!$A$2:$A$49,"Canal 13",'Líneas codificadas'!$B$2:$B$49,"FY2024")=0,"n.d.",SUMIFS('Líneas codificadas'!$E$2:$E$49,'Líneas codificadas'!$A$2:$A$49,"Canal 13",'Líneas codificadas'!$B$2:$B$49,"FY2024")) -> 78910289 | D47: =IF(SUMIFS('Líneas codificadas'!$E$2:$E$49,'Líneas codificadas'!$A$2:$A$49,"Canal 13",'Líneas codificadas'!$B$2:$B$49,"FY2025")=0,"n.d.",SUMIFS('Líneas codificadas'!$E$2:$E$49,'Líneas codificadas'!$A$2:$A$49,"Canal 13",'Líneas codificadas'!$B$2:$B$49,"FY2025")) -> 81549524 | E47: =IF(SUMIFS('Líneas codificadas'!$E$2:$E$49,'Líneas codificadas'!$A$2:$A$49,"Canal 13",'Líneas codificadas'!$B$2:$B$49,"H1 2025")=0,"n.d.",SUMIFS('Líneas codificadas'!$E$2:$E$49,'Líneas codificadas'!$A$2:$A$49,"Canal 13",'Líneas codificadas'!$B$2:$B$49,"H1 2025")) -> 37163375 | F47: =IF(SUMIFS('Líneas codificadas'!$E$2:$E$49,'Líneas codificadas'!$A$2:$A$49,"Canal 13",'Líneas codificadas'!$B$2:$B$49,"H1 2026")=0,"n.d.",SUMIFS('Líneas codificadas'!$E$2:$E$49,'Líneas codificadas'!$A$2:$A$49,"Canal 13",'Líneas codificadas'!$B$2:$B$49,"H1 2026")) -> 38389971
A48: Mega | B48: Publicidad | C48: =IF(SUMIFS('Líneas codificadas'!$E$2:$E$49,'Líneas codificadas'!$A$2:$A$49,"Mega",'Líneas codificadas'!$B$2:$B$49,"FY2024")=0,"n.d.",SUMIFS('Líneas codificadas'!$E$2:$E$49,'Líneas codificadas'!$A$2:$A$49,"Mega",'Líneas codificadas'!$B$2:$B$49,"FY2024",'Líneas codificadas'!$O$2:$O$49,"Publicidad")) -> 77905105 | D48: =IF(SUMIFS('Líneas codificadas'!$E$2:$E$49,'Líneas codificadas'!$A$2:$A$49,"Mega",'Líneas codificadas'!$B$2:$B$49,"FY2025")=0,"n.d.",SUMIFS('Líneas codificadas'!$E$2:$E$49,'Líneas codificadas'!$A$2:$A$49,"Mega",'Líneas codificadas'!$B$2:$B$49,"FY2025",'Líneas codificadas'!$O$2:$O$49,"Publicidad")) -> 82713303 | E48: =IF(SUMIFS('Líneas codificadas'!$E$2:$E$49,'Líneas codificadas'!$A$2:$A$49,"Mega",'Líneas codificadas'!$B$2:$B$49,"H1 2025")=0,"n.d.",SUMIFS('Líneas codificadas'!$E$2:$E$49,'Líneas codificadas'!$A$2:$A$49,"Mega",'Líneas codificadas'!$B$2:$B$49,"H1 2025",'Líneas codificadas'!$O$2:$O$49,"Publicidad")) -> 39594862 | F48: =IF(SUMIFS('Líneas codificadas'!$E$2:$E$49,'Líneas codificadas'!$A$2:$A$49,"Mega",'Líneas codificadas'!$B$2:$B$49,"H1 2026")=0,"n.d.",SUMIFS('Líneas codificadas'!$E$2:$E$49,'Líneas codificadas'!$A$2:$A$49,"Mega",'Líneas codificadas'!$B$2:$B$49,"H1 2026",'Líneas codificadas'!$O$2:$O$49,"Publicidad")) -> 46331037
B49: Otros ingresos operacionales | C49: =IF(SUMIFS('Líneas codificadas'!$E$2:$E$49,'Líneas codificadas'!$A$2:$A$49,"Mega",'Líneas codificadas'!$B$2:$B$49,"FY2024")=0,"n.d.",SUMIFS('Líneas codificadas'!$E$2:$E$49,'Líneas codificadas'!$A$2:$A$49,"Mega",'Líneas codificadas'!$B$2:$B$49,"FY2024",'Líneas codificadas'!$O$2:$O$49,"Otros ingresos operacionales")) -> 25014746 | D49: =IF(SUMIFS('Líneas codificadas'!$E$2:$E$49,'Líneas codificadas'!$A$2:$A$49,"Mega",'Líneas codificadas'!$B$2:$B$49,"FY2025")=0,"n.d.",SUMIFS('Líneas codificadas'!$E$2:$E$49,'Líneas codificadas'!$A$2:$A$49,"Mega",'Líneas codificadas'!$B$2:$B$49,"FY2025",'Líneas codificadas'!$O$2:$O$49,"Otros ingresos operacionales")) -> 22126761 | E49: =IF(SUMIFS('Líneas codificadas'!$E$2:$E$49,'Líneas codificadas'!$A$2:$A$49,"Mega",'Líneas codificadas'!$B$2:$B$49,"H1 2025")=0,"n.d.",SUMIFS('Líneas codificadas'!$E$2:$E$49,'Líneas codificadas'!$A$2:$A$49,"Mega",'Líneas codificadas'!$B$2:$B$49,"H1 2025",'Líneas codificadas'!$O$2:$O$49,"Otros ingresos operacionales")) -> 14954549 | F49: =IF(SUMIFS('Líneas codificadas'!$E$2:$E$49,'Líneas codificadas'!$A$2:$A$49,"Mega",'Líneas codificadas'!$B$2:$B$49,"H1 2026")=0,"n.d.",SUMIFS('Líneas codificadas'!$E$2:$E$49,'Líneas codificadas'!$A$2:$A$49,"Mega",'Líneas codificadas'!$B$2:$B$49,"H1 2026",'Líneas codificadas'!$O$2:$O$49,"Otros ingresos operacionales")) -> 10103933
B50: Transferencias del Estado | C50: =IF(SUMIFS('Líneas codificadas'!$E$2:$E$49,'Líneas codificadas'!$A$2:$A$49,"Mega",'Líneas codificadas'!$B$2:$B$49,"FY2024")=0,"n.d.",SUMIFS('Líneas codificadas'!$E$2:$E$49,'Líneas codificadas'!$A$2:$A$49,"Mega",'Líneas codificadas'!$B$2:$B$49,"FY2024",'Líneas codificadas'!$O$2:$O$49,"Transferencias del Estado")) -> 0 | D50: =IF(SUMIFS('Líneas codificadas'!$E$2:$E$49,'Líneas codificadas'!$A$2:$A$49,"Mega",'Líneas codificadas'!$B$2:$B$49,"FY2025")=0,"n.d.",SUMIFS('Líneas codificadas'!$E$2:$E$49,'Líneas codificadas'!$A$2:$A$49,"Mega",'Líneas codificadas'!$B$2:$B$49,"FY2025",'Líneas codificadas'!$O$2:$O$49,"Transferencias del Estado")) -> 0 | E50: =IF(SUMIFS('Líneas codificadas'!$E$2:$E$49,'Líneas codificadas'!$A$2:$A$49,"Mega",'Líneas codificadas'!$B$2:$B$49,"H1 2025")=0,"n.d.",SUMIFS('Líneas codificadas'!$E$2:$E$49,'Líneas codificadas'!$A$2:$A$49,"Mega",'Líneas codificadas'!$B$2:$B$49,"H1 2025",'Líneas codificadas'!$O$2:$O$49,"Transferencias del Estado")) -> 0 | F50: =IF(SUMIFS('Líneas codificadas'!$E$2:$E$49,'Líneas codificadas'!$A$2:$A$49,"Mega",'Líneas codificadas'!$B$2:$B$49,"H1 2026")=0,"n.d.",SUMIFS('Líneas codificadas'!$E$2:$E$49,'Líneas codificadas'!$A$2:$A$49,"Mega",'Líneas codificadas'!$B$2:$B$49,"H1 2026",'Líneas codificadas'!$O$2:$O$49,"Transferencias del Estado")) -> 0
B51: Total | C51: =IF(SUMIFS('Líneas codificadas'!$E$2:$E$49,'Líneas codificadas'!$A$2:$A$49,"Mega",'Líneas codificadas'!$B$2:$B$49,"FY2024")=0,"n.d.",SUMIFS('Líneas codificadas'!$E$2:$E$49,'Líneas codificadas'!$A$2:$A$49,"Mega",'Líneas codificadas'!$B$2:$B$49,"FY2024")) -> 102919851 | D51: =IF(SUMIFS('Líneas codificadas'!$E$2:$E$49,'Líneas codificadas'!$A$2:$A$49,"Mega",'Líneas codificadas'!$B$2:$B$49,"FY2025")=0,"n.d.",SUMIFS('Líneas codificadas'!$E$2:$E$49,'Líneas codificadas'!$A$2:$A$49,"Mega",'Líneas codificadas'!$B$2:$B$49,"FY2025")) -> 104840064 | E51: =IF(SUMIFS('Líneas codificadas'!$E$2:$E$49,'Líneas codificadas'!$A$2:$A$49,"Mega",'Líneas codificadas'!$B$2:$B$49,"H1 2025")=0,"n.d.",SUMIFS('Líneas codificadas'!$E$2:$E$49,'Líneas codificadas'!$A$2:$A$49,"Mega",'Líneas codificadas'!$B$2:$B$49,"H1 2025")) -> 54549411 | F51: =IF(SUMIFS('Líneas codificadas'!$E$2:$E$49,'Líneas codificadas'!$A$2:$A$49,"Mega",'Líneas codificadas'!$B$2:$B$49,"H1 2026")=0,"n.d.",SUMIFS('Líneas codificadas'!$E$2:$E$49,'Líneas codificadas'!$A$2:$A$49,"Mega",'Líneas codificadas'!$B$2:$B$49,"H1 2026")) -> 56434970
A52: Chilevisión | B52: Publicidad | C52: =IF(SUMIFS('Líneas codificadas'!$E$2:$E$49,'Líneas codificadas'!$A$2:$A$49,"Chilevisión",'Líneas codificadas'!$B$2:$B$49,"FY2024")=0,"n.d.",SUMIFS('Líneas codificadas'!$E$2:$E$49,'Líneas codificadas'!$A$2:$A$49,"Chilevisión",'Líneas codificadas'!$B$2:$B$49,"FY2024",'Líneas codificadas'!$O$2:$O$49,"Publicidad")) -> 66752603 | D52: =IF(SUMIFS('Líneas codificadas'!$E$2:$E$49,'Líneas codificadas'!$A$2:$A$49,"Chilevisión",'Líneas codificadas'!$B$2:$B$49,"FY2025")=0,"n.d.",SUMIFS('Líneas codificadas'!$E$2:$E$49,'Líneas codificadas'!$A$2:$A$49,"Chilevisión",'Líneas codificadas'!$B$2:$B$49,"FY2025",'Líneas codificadas'!$O$2:$O$49,"Publicidad")) -> 64981856 | E52: =IF(SUMIFS('Líneas codificadas'!$E$2:$E$49,'Líneas codificadas'!$A$2:$A$49,"Chilevisión",'Líneas codificadas'!$B$2:$B$49,"H1 2025")=0,"n.d.",SUMIFS('Líneas codificadas'!$E$2:$E$49,'Líneas codificadas'!$A$2:$A$49,"Chilevisión",'Líneas codificadas'!$B$2:$B$49,"H1 2025",'Líneas codificadas'!$O$2:$O$49,"Publicidad")) -> 33494199 | F52: =IF(SUMIFS('Líneas codificadas'!$E$2:$E$49,'Líneas codificadas'!$A$2:$A$49,"Chilevisión",'Líneas codificadas'!$B$2:$B$49,"H1 2026")=0,"n.d.",SUMIFS('Líneas codificadas'!$E$2:$E$49,'Líneas codificadas'!$A$2:$A$49,"Chilevisión",'Líneas codificadas'!$B$2:$B$49,"H1 2026",'Líneas codificadas'!$O$2:$O$49,"Publicidad")) -> 32933666
B53: Otros ingresos operacionales | C53: =IF(SUMIFS('Líneas codificadas'!$E$2:$E$49,'Líneas codificadas'!$A$2:$A$49,"Chilevisión",'Líneas codificadas'!$B$2:$B$49,"FY2024")=0,"n.d.",SUMIFS('Líneas codificadas'!$E$2:$E$49,'Líneas codificadas'!$A$2:$A$49,"Chilevisión",'Líneas codificadas'!$B$2:$B$49,"FY2024",'Líneas codificadas'!$O$2:$O$49,"Otros ingresos operacionales")) -> 6564923 | D53: =IF(SUMIFS('Líneas codificadas'!$E$2:$E$49,'Líneas codificadas'!$A$2:$A$49,"Chilevisión",'Líneas codificadas'!$B$2:$B$49,"FY2025")=0,"n.d.",SUMIFS('Líneas codificadas'!$E$2:$E$49,'Líneas codificadas'!$A$2:$A$49,"Chilevisión",'Líneas codificadas'!$B$2:$B$49,"FY2025",'Líneas codificadas'!$O$2:$O$49,"Otros ingresos operacionales")) -> 7516324 | E53: =IF(SUMIFS('Líneas codificadas'!$E$2:$E$49,'Líneas codificadas'!$A$2:$A$49,"Chilevisión",'Líneas codificadas'!$B$2:$B$49,"H1 2025")=0,"n.d.",SUMIFS('Líneas codificadas'!$E$2:$E$49,'Líneas codificadas'!$A$2:$A$49,"Chilevisión",'Líneas codificadas'!$B$2:$B$49,"H1 2025",'Líneas codificadas'!$O$2:$O$49,"Otros ingresos operacionales")) -> 1732348 | F53: =IF(SUMIFS('Líneas codificadas'!$E$2:$E$49,'Líneas codificadas'!$A$2:$A$49,"Chilevisión",'Líneas codificadas'!$B$2:$B$49,"H1 2026")=0,"n.d.",SUMIFS('Líneas codificadas'!$E$2:$E$49,'Líneas codificadas'!$A$2:$A$49,"Chilevisión",'Líneas codificadas'!$B$2:$B$49,"H1 2026",'Líneas codificadas'!$O$2:$O$49,"Otros ingresos operacionales")) -> 3297691
B54: Transferencias del Estado | C54: =IF(SUMIFS('Líneas codificadas'!$E$2:$E$49,'Líneas codificadas'!$A$2:$A$49,"Chilevisión",'Líneas codificadas'!$B$2:$B$49,"FY2024")=0,"n.d.",SUMIFS('Líneas codificadas'!$E$2:$E$49,'Líneas codificadas'!$A$2:$A$49,"Chilevisión",'Líneas codificadas'!$B$2:$B$49,"FY2024",'Líneas codificadas'!$O$2:$O$49,"Transferencias del Estado")) -> 0 | D54: =IF(SUMIFS('Líneas codificadas'!$E$2:$E$49,'Líneas codificadas'!$A$2:$A$49,"Chilevisión",'Líneas codificadas'!$B$2:$B$49,"FY2025")=0,"n.d.",SUMIFS('Líneas codificadas'!$E$2:$E$49,'Líneas codificadas'!$A$2:$A$49,"Chilevisión",'Líneas codificadas'!$B$2:$B$49,"FY2025",'Líneas codificadas'!$O$2:$O$49,"Transferencias del Estado")) -> 0 | E54: =IF(SUMIFS('Líneas codificadas'!$E$2:$E$49,'Líneas codificadas'!$A$2:$A$49,"Chilevisión",'Líneas codificadas'!$B$2:$B$49,"H1 2025")=0,"n.d.",SUMIFS('Líneas codificadas'!$E$2:$E$49,'Líneas codificadas'!$A$2:$A$49,"Chilevisión",'Líneas codificadas'!$B$2:$B$49,"H1 2025",'Líneas codificadas'!$O$2:$O$49,"Transferencias del Estado")) -> 0 | F54: =IF(SUMIFS('Líneas codificadas'!$E$2:$E$49,'Líneas codificadas'!$A$2:$A$49,"Chilevisión",'Líneas codificadas'!$B$2:$B$49,"H1 2026")=0,"n.d.",SUMIFS('Líneas codificadas'!$E$2:$E$49,'Líneas codificadas'!$A$2:$A$49,"Chilevisión",'Líneas codificadas'!$B$2:$B$49,"H1 2026",'Líneas codificadas'!$O$2:$O$49,"Transferencias del Estado")) -> 0
B55: Total | C55: =IF(SUMIFS('Líneas codificadas'!$E$2:$E$49,'Líneas codificadas'!$A$2:$A$49,"Chilevisión",'Líneas codificadas'!$B$2:$B$49,"FY2024")=0,"n.d.",SUMIFS('Líneas codificadas'!$E$2:$E$49,'Líneas codificadas'!$A$2:$A$49,"Chilevisión",'Líneas codificadas'!$B$2:$B$49,"FY2024")) -> 73317526 | D55: =IF(SUMIFS('Líneas codificadas'!$E$2:$E$49,'Líneas codificadas'!$A$2:$A$49,"Chilevisión",'Líneas codificadas'!$B$2:$B$49,"FY2025")=0,"n.d.",SUMIFS('Líneas codificadas'!$E$2:$E$49,'Líneas codificadas'!$A$2:$A$49,"Chilevisión",'Líneas codificadas'!$B$2:$B$49,"FY2025")) -> 72498180 | E55: =IF(SUMIFS('Líneas codificadas'!$E$2:$E$49,'Líneas codificadas'!$A$2:$A$49,"Chilevisión",'Líneas codificadas'!$B$2:$B$49,"H1 2025")=0,"n.d.",SUMIFS('Líneas codificadas'!$E$2:$E$49,'Líneas codificadas'!$A$2:$A$49,"Chilevisión",'Líneas codificadas'!$B$2:$B$49,"H1 2025")) -> 35226547 | F55: =IF(SUMIFS('Líneas codificadas'!$E$2:$E$49,'Líneas codificadas'!$A$2:$A$49,"Chilevisión",'Líneas codificadas'!$B$2:$B$49,"H1 2026")=0,"n.d.",SUMIFS('Líneas codificadas'!$E$2:$E$49,'Líneas codificadas'!$A$2:$A$49,"Chilevisión",'Líneas codificadas'!$B$2:$B$49,"H1 2026")) -> 36231357
A57: Reglas de asignación (idénticas para los cuatro canales):
A58: • Publicidad = toda línea que la nota rotula como publicidad: TVN 'publicidad en TV abierta'; Canal 13 'pantalla abierta' + 'otras plataformas'; Mega 'TV e internet' + 'radial y cable'; Chilevisión 'publicidad' (TV abierta + comisión TV paga).
A59: • Transferencias del Estado = subvención NTV (solo TVN, desde 2025). En los canales privados es un cero estructural, no un dato faltante.
A60: • Otros ingresos operacionales = el resto de ingresos de actividades ordinarias: señales, contenidos, plataformas, suscripciones, fees, arriendos, venta de activos, concursos, publicidad digital que el canal no rotula como publicidad.
A61: Por qué no se puede desagregar más de forma común:
A62: • Publicidad digital: solo Canal 13 la separa; Mega la junta con TV; Chilevisión y TVN la esconden en otros ingresos.
A63: • Publicidad en radio/cable: solo Mega la separa; Chilevisión la incluye dentro de 'publicidad' (comisión TV paga).
A64: • Venta de contenidos/señales: solo Mega tiene una línea pura; Canal 13, TVN y Chilevisión la mezclan con arriendos, activos, fees o publicidad digital.
A65: Advertencia: en Nivel 2 'Publicidad' no mide exactamente lo mismo en todos (Canal 13 y Mega incluyen digital; Mega incluye radio). Es la definición común más fina que no requiere supuestos. Chilevisión H1-2025 usa el comparativo reclasificado de 2026.

Sheet Tabla Napoli (rangos)
A1: Composición de ingresos de la TV abierta chilena en rangos (piso – techo), a la manera de Napoli (2003), Tabla 1.1
A2: Los rangos reflejan líneas de la nota de ingresos que mezclan categorías (ver 'Líneas codificadas'). Cuando piso = techo, la clasificación es exacta. Todas las cifras provienen de estados financieros (CMF).
A4: % venta de audiencias
A5: Canal | B5: FY2024 | C5: FY2025 | D5: H1 2025 | E5: H1 2026 | F5: Nota
A6: TVN | B6: =IF(Rangos!N10=Rangos!O10,TEXT(Rangos!N10,"0.0%"),TEXT(Rangos!N10,"0.0%")&" – "&TEXT(Rangos!O10,"0.0%")) -> 63.5% – 100.0% | C6: =IF(Rangos!N11=Rangos!O11,TEXT(Rangos!N11,"0.0%"),TEXT(Rangos!N11,"0.0%")&" – "&TEXT(Rangos!O11,"0.0%")) -> 60.1% – 95.8% | D6: =IF(Rangos!N12=Rangos!O12,TEXT(Rangos!N12,"0.0%"),TEXT(Rangos!N12,"0.0%")&" – "&TEXT(Rangos!O12,"0.0%")) -> 58.2% – 91.7% | E6: =IF(Rangos!N13=Rangos!O13,TEXT(Rangos!N13,"0.0%"),TEXT(Rangos!N13,"0.0%")&" – "&TEXT(Rangos!O13,"0.0%")) -> 56.5% – 92.4% | F6: EEFF. Piso = publicidad TV abierta; techo suma 'otros ingresos' (podría contener publicidad digital). Subvención NTV aislada como Fuera (2025–26).
A7: Canal 13 | B7: =IF(Rangos!N2=Rangos!O2,TEXT(Rangos!N2,"0.0%"),TEXT(Rangos!N2,"0.0%")&" – "&TEXT(Rangos!O2,"0.0%")) -> 76.0% | C7: =IF(Rangos!N3=Rangos!O3,TEXT(Rangos!N3,"0.0%"),TEXT(Rangos!N3,"0.0%")&" – "&TEXT(Rangos!O3,"0.0%")) -> 76.7% | D7: =IF(Rangos!N4=Rangos!O4,TEXT(Rangos!N4,"0.0%"),TEXT(Rangos!N4,"0.0%")&" – "&TEXT(Rangos!O4,"0.0%")) -> 75.7% | E7: =IF(Rangos!N5=Rangos!O5,TEXT(Rangos!N5,"0.0%"),TEXT(Rangos!N5,"0.0%")&" – "&TEXT(Rangos!O5,"0.0%")) -> 70.9% | F7: Audiencias exacta (dos líneas puras). La incertidumbre está entre Contenidos y Fuera (arriendos, venta de activos).
A8: Mega | B8: =IF(Rangos!N6=Rangos!O6,TEXT(Rangos!N6,"0.0%"),TEXT(Rangos!N6,"0.0%")&" – "&TEXT(Rangos!O6,"0.0%")) -> 75.7% | C8: =IF(Rangos!N7=Rangos!O7,TEXT(Rangos!N7,"0.0%"),TEXT(Rangos!N7,"0.0%")&" – "&TEXT(Rangos!O7,"0.0%")) -> 78.9% | D8: =IF(Rangos!N14=Rangos!O14,TEXT(Rangos!N14,"0.0%"),TEXT(Rangos!N14,"0.0%")&" – "&TEXT(Rangos!O14,"0.0%")) -> 72.6% | E8: =IF(Rangos!N16=Rangos!O16,TEXT(Rangos!N16,"0.0%"),TEXT(Rangos!N16,"0.0%")&" – "&TEXT(Rangos!O16,"0.0%")) -> 82.1% | F8: Exacto (tres líneas puras). Incluye radios y cable; ver fila de perímetro TV.
A9: Chilevisión | B9: =IF(Rangos!N8=Rangos!O8,TEXT(Rangos!N8,"0.0%"),TEXT(Rangos!N8,"0.0%")&" – "&TEXT(Rangos!O8,"0.0%")) -> 91.0% – 100.0% | C9: =IF(Rangos!N9=Rangos!O9,TEXT(Rangos!N9,"0.0%"),TEXT(Rangos!N9,"0.0%")&" – "&TEXT(Rangos!O9,"0.0%")) -> 89.6% – 100.0% | D9: =IF(Rangos!N17=Rangos!O17,TEXT(Rangos!N17,"0.0%"),TEXT(Rangos!N17,"0.0%")&" – "&TEXT(Rangos!O17,"0.0%")) -> 95.1% – 100.0% | E9: =IF(Rangos!N19=Rangos!O19,TEXT(Rangos!N19,"0.0%"),TEXT(Rangos!N19,"0.0%")&" – "&TEXT(Rangos!O19,"0.0%")) -> 90.9% – 100.0% | F9: 'Nuevos negocios' mezcla publicidad digital, señales/contenido, fees y concursos → rango en las tres categorías. H1-2025 según comparativo 2026 (reclasificado).
A11: % venta de contenidos
A12: Canal | B12: FY2024 | C12: FY2025 | D12: H1 2025 | E12: H1 2026
A13: TVN | B13: =IF(Rangos!P10=Rangos!Q10,TEXT(Rangos!P10,"0.0%"),TEXT(Rangos!P10,"0.0%")&" – "&TEXT(Rangos!Q10,"0.0%")) -> 0.0% – 36.5% | C13: =IF(Rangos!P11=Rangos!Q11,TEXT(Rangos!P11,"0.0%"),TEXT(Rangos!P11,"0.0%")&" – "&TEXT(Rangos!Q11,"0.0%")) -> 0.0% – 35.7% | D13: =IF(Rangos!P12=Rangos!Q12,TEXT(Rangos!P12,"0.0%"),TEXT(Rangos!P12,"0.0%")&" – "&TEXT(Rangos!Q12,"0.0%")) -> 0.0% – 33.6% | E13: =IF(Rangos!P13=Rangos!Q13,TEXT(Rangos!P13,"0.0%"),TEXT(Rangos!P13,"0.0%")&" – "&TEXT(Rangos!Q13,"0.0%")) -> 0.0% – 35.8%
A14: Canal 13 | B14: =IF(Rangos!P2=Rangos!Q2,TEXT(Rangos!P2,"0.0%"),TEXT(Rangos!P2,"0.0%")&" – "&TEXT(Rangos!Q2,"0.0%")) -> 0.0% – 24.0% | C14: =IF(Rangos!P3=Rangos!Q3,TEXT(Rangos!P3,"0.0%"),TEXT(Rangos!P3,"0.0%")&" – "&TEXT(Rangos!Q3,"0.0%")) -> 0.0% – 23.3% | D14: =IF(Rangos!P4=Rangos!Q4,TEXT(Rangos!P4,"0.0%"),TEXT(Rangos!P4,"0.0%")&" – "&TEXT(Rangos!Q4,"0.0%")) -> 0.0% – 24.3% | E14: =IF(Rangos!P5=Rangos!Q5,TEXT(Rangos!P5,"0.0%"),TEXT(Rangos!P5,"0.0%")&" – "&TEXT(Rangos!Q5,"0.0%")) -> 0.0% – 29.1%
A15: Mega | B15: =IF(Rangos!P6=Rangos!Q6,TEXT(Rangos!P6,"0.0%"),TEXT(Rangos!P6,"0.0%")&" – "&TEXT(Rangos!Q6,"0.0%")) -> 24.3% | C15: =IF(Rangos!P7=Rangos!Q7,TEXT(Rangos!P7,"0.0%"),TEXT(Rangos!P7,"0.0%")&" – "&TEXT(Rangos!Q7,"0.0%")) -> 21.1% | D15: =IF(Rangos!P14=Rangos!Q14,TEXT(Rangos!P14,"0.0%"),TEXT(Rangos!P14,"0.0%")&" – "&TEXT(Rangos!Q14,"0.0%")) -> 27.4% | E15: =IF(Rangos!P16=Rangos!Q16,TEXT(Rangos!P16,"0.0%"),TEXT(Rangos!P16,"0.0%")&" – "&TEXT(Rangos!Q16,"0.0%")) -> 17.9%
A16: Chilevisión | B16: =IF(Rangos!P8=Rangos!Q8,TEXT(Rangos!P8,"0.0%"),TEXT(Rangos!P8,"0.0%")&" – "&TEXT(Rangos!Q8,"0.0%")) -> 0.0% – 9.0% | C16: =IF(Rangos!P9=Rangos!Q9,TEXT(Rangos!P9,"0.0%"),TEXT(Rangos!P9,"0.0%")&" – "&TEXT(Rangos!Q9,"0.0%")) -> 0.0% – 10.4% | D16: =IF(Rangos!P17=Rangos!Q17,TEXT(Rangos!P17,"0.0%"),TEXT(Rangos!P17,"0.0%")&" – "&TEXT(Rangos!Q17,"0.0%")) -> 0.0% – 4.9% | E16: =IF(Rangos!P19=Rangos!Q19,TEXT(Rangos!P19,"0.0%"),TEXT(Rangos!P19,"0.0%")&" – "&TEXT(Rangos!Q19,"0.0%")) -> 0.0% – 9.1%
A18: % fuera de Napoli (arriendos, activos, fees, aportes)
A19: Canal | B19: FY2024 | C19: FY2025 | D19: H1 2025 | E19: H1 2026
A20: TVN | B20: =IF(Rangos!R10=Rangos!S10,TEXT(Rangos!R10,"0.0%"),TEXT(Rangos!R10,"0.0%")&" – "&TEXT(Rangos!S10,"0.0%")) -> 0.0% – 36.5% | C20: =IF(Rangos!R11=Rangos!S11,TEXT(Rangos!R11,"0.0%"),TEXT(Rangos!R11,"0.0%")&" – "&TEXT(Rangos!S11,"0.0%")) -> 4.2% – 39.9% | D20: =IF(Rangos!R12=Rangos!S12,TEXT(Rangos!R12,"0.0%"),TEXT(Rangos!R12,"0.0%")&" – "&TEXT(Rangos!S12,"0.0%")) -> 8.3% – 41.8% | E20: =IF(Rangos!R13=Rangos!S13,TEXT(Rangos!R13,"0.0%"),TEXT(Rangos!R13,"0.0%")&" – "&TEXT(Rangos!S13,"0.0%")) -> 7.6% – 43.5%
A21: Canal 13 | B21: =IF(Rangos!R2=Rangos!S2,TEXT(Rangos!R2,"0.0%"),TEXT(Rangos!R2,"0.0%")&" – "&TEXT(Rangos!S2,"0.0%")) -> 0.0% – 24.0% | C21: =IF(Rangos!R3=Rangos!S3,TEXT(Rangos!R3,"0.0%"),TEXT(Rangos!R3,"0.0%")&" – "&TEXT(Rangos!S3,"0.0%")) -> 0.0% – 23.3% | D21: =IF(Rangos!R4=Rangos!S4,TEXT(Rangos!R4,"0.0%"),TEXT(Rangos!R4,"0.0%")&" – "&TEXT(Rangos!S4,"0.0%")) -> 0.0% – 24.3% | E21: =IF(Rangos!R5=Rangos!S5,TEXT(Rangos!R5,"0.0%"),TEXT(Rangos!R5,"0.0%")&" – "&TEXT(Rangos!S5,"0.0%")) -> 0.0% – 29.1%
A22: Mega | B22: =IF(Rangos!R6=Rangos!S6,TEXT(Rangos!R6,"0.0%"),TEXT(Rangos!R6,"0.0%")&" – "&TEXT(Rangos!S6,"0.0%")) -> 0.0% | C22: =IF(Rangos!R7=Rangos!S7,TEXT(Rangos!R7,"0.0%"),TEXT(Rangos!R7,"0.0%")&" – "&TEXT(Rangos!S7,"0.0%")) -> 0.0% | D22: =IF(Rangos!R14=Rangos!S14,TEXT(Rangos!R14,"0.0%"),TEXT(Rangos!R14,"0.0%")&" – "&TEXT(Rangos!S14,"0.0%")) -> 0.0% | E22: =IF(Rangos!R16=Rangos!S16,TEXT(Rangos!R16,"0.0%"),TEXT(Rangos!R16,"0.0%")&" – "&TEXT(Rangos!S16,"0.0%")) -> 0.0%
A23: Chilevisión | B23: =IF(Rangos!R8=Rangos!S8,TEXT(Rangos!R8,"0.0%"),TEXT(Rangos!R8,"0.0%")&" – "&TEXT(Rangos!S8,"0.0%")) -> 0.0% – 9.0% | C23: =IF(Rangos!R9=Rangos!S9,TEXT(Rangos!R9,"0.0%"),TEXT(Rangos!R9,"0.0%")&" – "&TEXT(Rangos!S9,"0.0%")) -> 0.0% – 10.4% | D23: =IF(Rangos!R17=Rangos!S17,TEXT(Rangos!R17,"0.0%"),TEXT(Rangos!R17,"0.0%")&" – "&TEXT(Rangos!S17,"0.0%")) -> 0.0% – 4.9% | E23: =IF(Rangos!R19=Rangos!S19,TEXT(Rangos!R19,"0.0%"),TEXT(Rangos!R19,"0.0%")&" – "&TEXT(Rangos!S19,"0.0%")) -> 0.0% – 9.1%
A25: % venta de audiencias, perímetro TV (excluye publicidad radial/cable) — piso
A26: Canal | B26: FY2024 | C26: FY2025 | D26: H1 2025 | E26: H1 2026
A27: TVN | B27: =Rangos!W10 -> 0.63528699 | C27: =Rangos!W11 -> 0.60080217 | D27: =Rangos!W12 -> 0.58156218 | E27: =Rangos!W13 -> 0.56508885
A28: Canal 13 | B28: =Rangos!W2 -> 0.75965797 | C28: =Rangos!W3 -> 0.76724611 | D28: =Rangos!W4 -> 0.75688188 | E28: =Rangos!W5 -> 0.70870179
A29: Mega | B29: =Rangos!W6 -> 0.73743975 | C29: =Rangos!W7 -> 0.77254802 | D29: =Rangos!W14 -> 0.70791159 | E29: =Rangos!W16 -> 0.80648092
A30: Chilevisión | B30: =Rangos!W8 -> 0.91045902 | C30: =Rangos!W9 -> 0.89632396 | D30: =Rangos!W17 -> 0.95082266 | E30: =Rangos!W19 -> 0.9089824
A32: Nota Mega: los estados individuales de Megamedia S.A. (Oficio Circular 498, Anexo 3) informan ingresos de M$96.666.662 (2025) y M$94.456.363 (2024), sin desglose. La diferencia con el consolidado (≈M$8,2 mil millones) es cercana a la publicidad radial y cable, lo que respalda la variante 'perímetro TV'.
A33: Referencia Napoli (EE.UU., c. 2001): broadcast television 100% / 0%; cable television networks 60% / 40%.

Sheet Tabla Napoli (punto)
A1: Composición de ingresos de los principales canales de TV abierta en Chile, a la manera de Napoli (2003), Tabla 1.1
A2: Venta de audiencias = toda la publicidad (TV, digital, radio/cable). Contenidos + otros = retransmisión/cableoperadores, señales, licencias, suscripciones, más ingresos no audiovisuales (arriendos, venta de activos, fees, aportes estatales). Todas las cifras provienen de estados financieros.
A4: % de ingresos por venta de audiencias (toda la publicidad)
A5: Canal | B5: FY2024 | C5: FY2025 | D5: H1 2025 | E5: H1 2026 | F5: Nota
A6: TVN | B6: =IF(ISNA(MATCH("TVN|FY2024",Datos!$A$2:$A$19,0)),"n.d.",IF(ISNUMBER(INDEX(Datos!$L$2:$L$19,MATCH("TVN|FY2024",Datos!$A$2:$A$19,0))),INDEX(Datos!$L$2:$L$19,MATCH("TVN|FY2024",Datos!$A$2:$A$19,0)),"n.d.")) -> 0.63528699 | C6: =IF(ISNA(MATCH("TVN|FY2025",Datos!$A$2:$A$19,0)),"n.d.",IF(ISNUMBER(INDEX(Datos!$L$2:$L$19,MATCH("TVN|FY2025",Datos!$A$2:$A$19,0))),INDEX(Datos!$L$2:$L$19,MATCH("TVN|FY2025",Datos!$A$2:$A$19,0)),"n.d.")) -> 0.60080217 | D6: =IF(ISNA(MATCH("TVN|H1 2025",Datos!$A$2:$A$19,0)),"n.d.",IF(ISNUMBER(INDEX(Datos!$L$2:$L$19,MATCH("TVN|H1 2025",Datos!$A$2:$A$19,0))),INDEX(Datos!$L$2:$L$19,MATCH("TVN|H1 2025",Datos!$A$2:$A$19,0)),"n.d.")) -> 0.58156218 | E6: =IF(ISNA(MATCH("TVN|H1 2026",Datos!$A$2:$A$19,0)),"n.d.",IF(ISNUMBER(INDEX(Datos!$L$2:$L$19,MATCH("TVN|H1 2026",Datos!$A$2:$A$19,0))),INDEX(Datos!$L$2:$L$19,MATCH("TVN|H1 2026",Datos!$A$2:$A$19,0)),"n.d.")) -> 0.56508885 | F6: EEFF. Publicidad solo TV abierta; 'otros ingresos' = señal internacional + servicios. 2025–26 incluyen subvención NTV.
A7: Canal 13 | B7: =IF(ISNA(MATCH("Canal 13|FY2024",Datos!$A$2:$A$19,0)),"n.d.",IF(ISNUMBER(INDEX(Datos!$L$2:$L$19,MATCH("Canal 13|FY2024",Datos!$A$2:$A$19,0))),INDEX(Datos!$L$2:$L$19,MATCH("Canal 13|FY2024",Datos!$A$2:$A$19,0)),"n.d.")) -> 0.75965797 | C7: =IF(ISNA(MATCH("Canal 13|FY2025",Datos!$A$2:$A$19,0)),"n.d.",IF(ISNUMBER(INDEX(Datos!$L$2:$L$19,MATCH("Canal 13|FY2025",Datos!$A$2:$A$19,0))),INDEX(Datos!$L$2:$L$19,MATCH("Canal 13|FY2025",Datos!$A$2:$A$19,0)),"n.d.")) -> 0.76724611 | D7: =IF(ISNA(MATCH("Canal 13|H1 2025",Datos!$A$2:$A$19,0)),"n.d.",IF(ISNUMBER(INDEX(Datos!$L$2:$L$19,MATCH("Canal 13|H1 2025",Datos!$A$2:$A$19,0))),INDEX(Datos!$L$2:$L$19,MATCH("Canal 13|H1 2025",Datos!$A$2:$A$19,0)),"n.d.")) -> 0.75688188 | E7: =IF(ISNA(MATCH("Canal 13|H1 2026",Datos!$A$2:$A$19,0)),"n.d.",IF(ISNUMBER(INDEX(Datos!$L$2:$L$19,MATCH("Canal 13|H1 2026",Datos!$A$2:$A$19,0))),INDEX(Datos!$L$2:$L$19,MATCH("Canal 13|H1 2026",Datos!$A$2:$A$19,0)),"n.d.")) -> 0.70870179 | F7: EEFF completos. H1 2026: suben 'otros ingresos de explotación' (+23,8%).
A8: Mega | B8: =IF(ISNA(MATCH("Mega|FY2024",Datos!$A$2:$A$19,0)),"n.d.",IF(ISNUMBER(INDEX(Datos!$L$2:$L$19,MATCH("Mega|FY2024",Datos!$A$2:$A$19,0))),INDEX(Datos!$L$2:$L$19,MATCH("Mega|FY2024",Datos!$A$2:$A$19,0)),"n.d.")) -> 0.75694926 | C8: =IF(ISNA(MATCH("Mega|FY2025",Datos!$A$2:$A$19,0)),"n.d.",IF(ISNUMBER(INDEX(Datos!$L$2:$L$19,MATCH("Mega|FY2025",Datos!$A$2:$A$19,0))),INDEX(Datos!$L$2:$L$19,MATCH("Mega|FY2025",Datos!$A$2:$A$19,0)),"n.d.")) -> 0.78894747 | D8: =IF(ISNA(MATCH("Mega|H1 2025",Datos!$A$2:$A$19,0)),"n.d.",IF(ISNUMBER(INDEX(Datos!$L$2:$L$19,MATCH("Mega|H1 2025",Datos!$A$2:$A$19,0))),INDEX(Datos!$L$2:$L$19,MATCH("Mega|H1 2025",Datos!$A$2:$A$19,0)),"n.d.")) -> 0.72585315 | E8: =IF(ISNA(MATCH("Mega|H1 2026",Datos!$A$2:$A$19,0)),"n.d.",IF(ISNUMBER(INDEX(Datos!$L$2:$L$19,MATCH("Mega|H1 2026",Datos!$A$2:$A$19,0))),INDEX(Datos!$L$2:$L$19,MATCH("Mega|H1 2026",Datos!$A$2:$A$19,0)),"n.d.")) -> 0.82096326 | F8: Consolidado Megamedia, incluye radios y cable.
A9: Chilevisión | B9: =IF(ISNA(MATCH("Chilevisión|FY2024",Datos!$A$2:$A$19,0)),"n.d.",IF(ISNUMBER(INDEX(Datos!$L$2:$L$19,MATCH("Chilevisión|FY2024",Datos!$A$2:$A$19,0))),INDEX(Datos!$L$2:$L$19,MATCH("Chilevisión|FY2024",Datos!$A$2:$A$19,0)),"n.d.")) -> 0.91045902 | C9: =IF(ISNA(MATCH("Chilevisión|FY2025",Datos!$A$2:$A$19,0)),"n.d.",IF(ISNUMBER(INDEX(Datos!$L$2:$L$19,MATCH("Chilevisión|FY2025",Datos!$A$2:$A$19,0))),INDEX(Datos!$L$2:$L$19,MATCH("Chilevisión|FY2025",Datos!$A$2:$A$19,0)),"n.d.")) -> 0.89632396 | D9: =IF(ISNA(MATCH("Chilevisión|H1 2025",Datos!$A$2:$A$19,0)),"n.d.",IF(ISNUMBER(INDEX(Datos!$L$2:$L$19,MATCH("Chilevisión|H1 2025",Datos!$A$2:$A$19,0))),INDEX(Datos!$L$2:$L$19,MATCH("Chilevisión|H1 2025",Datos!$A$2:$A$19,0)),"n.d.")) -> 0.95082266 | E9: =IF(ISNA(MATCH("Chilevisión|H1 2026",Datos!$A$2:$A$19,0)),"n.d.",IF(ISNUMBER(INDEX(Datos!$L$2:$L$19,MATCH("Chilevisión|H1 2026",Datos!$A$2:$A$19,0))),INDEX(Datos!$L$2:$L$19,MATCH("Chilevisión|H1 2026",Datos!$A$2:$A$19,0)),"n.d.")) -> 0.9089824 | F9: Publicidad digital va en 'nuevos negocios' → % subestimado. Q1 2026 (prensa): 90,9%.
A11: % de ingresos por venta de contenidos + otros
A12: Canal | B12: FY2024 | C12: FY2025 | D12: H1 2025 | E12: H1 2026 | F12: Nota
A13: TVN | B13: =IF(ISNA(MATCH("TVN|FY2024",Datos!$A$2:$A$19,0)),"n.d.",IF(ISNUMBER(INDEX(Datos!$M$2:$M$19,MATCH("TVN|FY2024",Datos!$A$2:$A$19,0))),INDEX(Datos!$M$2:$M$19,MATCH("TVN|FY2024",Datos!$A$2:$A$19,0)),"n.d.")) -> 0.36471301 | C13: =IF(ISNA(MATCH("TVN|FY2025",Datos!$A$2:$A$19,0)),"n.d.",IF(ISNUMBER(INDEX(Datos!$M$2:$M$19,MATCH("TVN|FY2025",Datos!$A$2:$A$19,0))),INDEX(Datos!$M$2:$M$19,MATCH("TVN|FY2025",Datos!$A$2:$A$19,0)),"n.d.")) -> 0.39919783 | D13: =IF(ISNA(MATCH("TVN|H1 2025",Datos!$A$2:$A$19,0)),"n.d.",IF(ISNUMBER(INDEX(Datos!$M$2:$M$19,MATCH("TVN|H1 2025",Datos!$A$2:$A$19,0))),INDEX(Datos!$M$2:$M$19,MATCH("TVN|H1 2025",Datos!$A$2:$A$19,0)),"n.d.")) -> 0.41843782 | E13: =IF(ISNA(MATCH("TVN|H1 2026",Datos!$A$2:$A$19,0)),"n.d.",IF(ISNUMBER(INDEX(Datos!$M$2:$M$19,MATCH("TVN|H1 2026",Datos!$A$2:$A$19,0))),INDEX(Datos!$M$2:$M$19,MATCH("TVN|H1 2026",Datos!$A$2:$A$19,0)),"n.d.")) -> 0.43491115
A14: Canal 13 | B14: =IF(ISNA(MATCH("Canal 13|FY2024",Datos!$A$2:$A$19,0)),"n.d.",IF(ISNUMBER(INDEX(Datos!$M$2:$M$19,MATCH("Canal 13|FY2024",Datos!$A$2:$A$19,0))),INDEX(Datos!$M$2:$M$19,MATCH("Canal 13|FY2024",Datos!$A$2:$A$19,0)),"n.d.")) -> 0.24034203 | C14: =IF(ISNA(MATCH("Canal 13|FY2025",Datos!$A$2:$A$19,0)),"n.d.",IF(ISNUMBER(INDEX(Datos!$M$2:$M$19,MATCH("Canal 13|FY2025",Datos!$A$2:$A$19,0))),INDEX(Datos!$M$2:$M$19,MATCH("Canal 13|FY2025",Datos!$A$2:$A$19,0)),"n.d.")) -> 0.23275389 | D14: =IF(ISNA(MATCH("Canal 13|H1 2025",Datos!$A$2:$A$19,0)),"n.d.",IF(ISNUMBER(INDEX(Datos!$M$2:$M$19,MATCH("Canal 13|H1 2025",Datos!$A$2:$A$19,0))),INDEX(Datos!$M$2:$M$19,MATCH("Canal 13|H1 2025",Datos!$A$2:$A$19,0)),"n.d.")) -> 0.24311812 | E14: =IF(ISNA(MATCH("Canal 13|H1 2026",Datos!$A$2:$A$19,0)),"n.d.",IF(ISNUMBER(INDEX(Datos!$M$2:$M$19,MATCH("Canal 13|H1 2026",Datos!$A$2:$A$19,0))),INDEX(Datos!$M$2:$M$19,MATCH("Canal 13|H1 2026",Datos!$A$2:$A$19,0)),"n.d.")) -> 0.29129821
A15: Mega | B15: =IF(ISNA(MATCH("Mega|FY2024",Datos!$A$2:$A$19,0)),"n.d.",IF(ISNUMBER(INDEX(Datos!$M$2:$M$19,MATCH("Mega|FY2024",Datos!$A$2:$A$19,0))),INDEX(Datos!$M$2:$M$19,MATCH("Mega|FY2024",Datos!$A$2:$A$19,0)),"n.d.")) -> 0.24305074 | C15: =IF(ISNA(MATCH("Mega|FY2025",Datos!$A$2:$A$19,0)),"n.d.",IF(ISNUMBER(INDEX(Datos!$M$2:$M$19,MATCH("Mega|FY2025",Datos!$A$2:$A$19,0))),INDEX(Datos!$M$2:$M$19,MATCH("Mega|FY2025",Datos!$A$2:$A$19,0)),"n.d.")) -> 0.21105253 | D15: =IF(ISNA(MATCH("Mega|H1 2025",Datos!$A$2:$A$19,0)),"n.d.",IF(ISNUMBER(INDEX(Datos!$M$2:$M$19,MATCH("Mega|H1 2025",Datos!$A$2:$A$19,0))),INDEX(Datos!$M$2:$M$19,MATCH("Mega|H1 2025",Datos!$A$2:$A$19,0)),"n.d.")) -> 0.27414685 | E15: =IF(ISNA(MATCH("Mega|H1 2026",Datos!$A$2:$A$19,0)),"n.d.",IF(ISNUMBER(INDEX(Datos!$M$2:$M$19,MATCH("Mega|H1 2026",Datos!$A$2:$A$19,0))),INDEX(Datos!$M$2:$M$19,MATCH("Mega|H1 2026",Datos!$A$2:$A$19,0)),"n.d.")) -> 0.17903674
A16: Chilevisión | B16: =IF(ISNA(MATCH("Chilevisión|FY2024",Datos!$A$2:$A$19,0)),"n.d.",IF(ISNUMBER(INDEX(Datos!$M$2:$M$19,MATCH("Chilevisión|FY2024",Datos!$A$2:$A$19,0))),INDEX(Datos!$M$2:$M$19,MATCH("Chilevisión|FY2024",Datos!$A$2:$A$19,0)),"n.d.")) -> 0.089540978 | C16: =IF(ISNA(MATCH("Chilevisión|FY2025",Datos!$A$2:$A$19,0)),"n.d.",IF(ISNUMBER(INDEX(Datos!$M$2:$M$19,MATCH("Chilevisión|FY2025",Datos!$A$2:$A$19,0))),INDEX(Datos!$M$2:$M$19,MATCH("Chilevisión|FY2025",Datos!$A$2:$A$19,0)),"n.d.")) -> 0.10367604 | D16: =IF(ISNA(MATCH("Chilevisión|H1 2025",Datos!$A$2:$A$19,0)),"n.d.",IF(ISNUMBER(INDEX(Datos!$M$2:$M$19,MATCH("Chilevisión|H1 2025",Datos!$A$2:$A$19,0))),INDEX(Datos!$M$2:$M$19,MATCH("Chilevisión|H1 2025",Datos!$A$2:$A$19,0)),"n.d.")) -> 0.049177343 | E16: =IF(ISNA(MATCH("Chilevisión|H1 2026",Datos!$A$2:$A$19,0)),"n.d.",IF(ISNUMBER(INDEX(Datos!$M$2:$M$19,MATCH("Chilevisión|H1 2026",Datos!$A$2:$A$19,0))),INDEX(Datos!$M$2:$M$19,MATCH("Chilevisión|H1 2026",Datos!$A$2:$A$19,0)),"n.d.")) -> 0.091017596
A18: % de ingresos por publicidad televisiva (núcleo 'broadcast')
A19: Canal | B19: FY2024 | C19: FY2025 | D19: H1 2025 | E19: H1 2026 | F19: Nota
A20: TVN | B20: =IF(ISNA(MATCH("TVN|FY2024",Datos!$A$2:$A$19,0)),"n.d.",IF(ISNUMBER(INDEX(Datos!$N$2:$N$19,MATCH("TVN|FY2024",Datos!$A$2:$A$19,0))),INDEX(Datos!$N$2:$N$19,MATCH("TVN|FY2024",Datos!$A$2:$A$19,0)),"n.d.")) -> 0.63528699 | C20: =IF(ISNA(MATCH("TVN|FY2025",Datos!$A$2:$A$19,0)),"n.d.",IF(ISNUMBER(INDEX(Datos!$N$2:$N$19,MATCH("TVN|FY2025",Datos!$A$2:$A$19,0))),INDEX(Datos!$N$2:$N$19,MATCH("TVN|FY2025",Datos!$A$2:$A$19,0)),"n.d.")) -> 0.60080217 | D20: =IF(ISNA(MATCH("TVN|H1 2025",Datos!$A$2:$A$19,0)),"n.d.",IF(ISNUMBER(INDEX(Datos!$N$2:$N$19,MATCH("TVN|H1 2025",Datos!$A$2:$A$19,0))),INDEX(Datos!$N$2:$N$19,MATCH("TVN|H1 2025",Datos!$A$2:$A$19,0)),"n.d.")) -> 0.58156218 | E20: =IF(ISNA(MATCH("TVN|H1 2026",Datos!$A$2:$A$19,0)),"n.d.",IF(ISNUMBER(INDEX(Datos!$N$2:$N$19,MATCH("TVN|H1 2026",Datos!$A$2:$A$19,0))),INDEX(Datos!$N$2:$N$19,MATCH("TVN|H1 2026",Datos!$A$2:$A$19,0)),"n.d.")) -> 0.56508885
A21: Canal 13 | B21: =IF(ISNA(MATCH("Canal 13|FY2024",Datos!$A$2:$A$19,0)),"n.d.",IF(ISNUMBER(INDEX(Datos!$N$2:$N$19,MATCH("Canal 13|FY2024",Datos!$A$2:$A$19,0))),INDEX(Datos!$N$2:$N$19,MATCH("Canal 13|FY2024",Datos!$A$2:$A$19,0)),"n.d.")) -> 0.72617401 | C21: =IF(ISNA(MATCH("Canal 13|FY2025",Datos!$A$2:$A$19,0)),"n.d.",IF(ISNUMBER(INDEX(Datos!$N$2:$N$19,MATCH("Canal 13|FY2025",Datos!$A$2:$A$19,0))),INDEX(Datos!$N$2:$N$19,MATCH("Canal 13|FY2025",Datos!$A$2:$A$19,0)),"n.d.")) -> 0.73515241 | D21: =IF(ISNA(MATCH("Canal 13|H1 2025",Datos!$A$2:$A$19,0)),"n.d.",IF(ISNUMBER(INDEX(Datos!$N$2:$N$19,MATCH("Canal 13|H1 2025",Datos!$A$2:$A$19,0))),INDEX(Datos!$N$2:$N$19,MATCH("Canal 13|H1 2025",Datos!$A$2:$A$19,0)),"n.d.")) -> 0.7227304 | E21: =IF(ISNA(MATCH("Canal 13|H1 2026",Datos!$A$2:$A$19,0)),"n.d.",IF(ISNUMBER(INDEX(Datos!$N$2:$N$19,MATCH("Canal 13|H1 2026",Datos!$A$2:$A$19,0))),INDEX(Datos!$N$2:$N$19,MATCH("Canal 13|H1 2026",Datos!$A$2:$A$19,0)),"n.d.")) -> 0.68149301
A22: Mega | B22: =IF(ISNA(MATCH("Mega|FY2024",Datos!$A$2:$A$19,0)),"n.d.",IF(ISNUMBER(INDEX(Datos!$N$2:$N$19,MATCH("Mega|FY2024",Datos!$A$2:$A$19,0))),INDEX(Datos!$N$2:$N$19,MATCH("Mega|FY2024",Datos!$A$2:$A$19,0)),"n.d.")) -> 0.68264436 | C22: =IF(ISNA(MATCH("Mega|FY2025",Datos!$A$2:$A$19,0)),"n.d.",IF(ISNUMBER(INDEX(Datos!$N$2:$N$19,MATCH("Mega|FY2025",Datos!$A$2:$A$19,0))),INDEX(Datos!$N$2:$N$19,MATCH("Mega|FY2025",Datos!$A$2:$A$19,0)),"n.d.")) -> 0.71684675 | D22: =IF(ISNA(MATCH("Mega|H1 2025",Datos!$A$2:$A$19,0)),"n.d.",IF(ISNUMBER(INDEX(Datos!$N$2:$N$19,MATCH("Mega|H1 2025",Datos!$A$2:$A$19,0))),INDEX(Datos!$N$2:$N$19,MATCH("Mega|H1 2025",Datos!$A$2:$A$19,0)),"n.d.")) -> 0.66442804 | E22: =IF(ISNA(MATCH("Mega|H1 2026",Datos!$A$2:$A$19,0)),"n.d.",IF(ISNUMBER(INDEX(Datos!$N$2:$N$19,MATCH("Mega|H1 2026",Datos!$A$2:$A$19,0))),INDEX(Datos!$N$2:$N$19,MATCH("Mega|H1 2026",Datos!$A$2:$A$19,0)),"n.d.")) -> 0.74612652
A23: Chilevisión | B23: =IF(ISNA(MATCH("Chilevisión|FY2024",Datos!$A$2:$A$19,0)),"n.d.",IF(ISNUMBER(INDEX(Datos!$N$2:$N$19,MATCH("Chilevisión|FY2024",Datos!$A$2:$A$19,0))),INDEX(Datos!$N$2:$N$19,MATCH("Chilevisión|FY2024",Datos!$A$2:$A$19,0)),"n.d.")) -> 0.91045902 | C23: =IF(ISNA(MATCH("Chilevisión|FY2025",Datos!$A$2:$A$19,0)),"n.d.",IF(ISNUMBER(INDEX(Datos!$N$2:$N$19,MATCH("Chilevisión|FY2025",Datos!$A$2:$A$19,0))),INDEX(Datos!$N$2:$N$19,MATCH("Chilevisión|FY2025",Datos!$A$2:$A$19,0)),"n.d.")) -> 0.89632396 | D23: =IF(ISNA(MATCH("Chilevisión|H1 2025",Datos!$A$2:$A$19,0)),"n.d.",IF(ISNUMBER(INDEX(Datos!$N$2:$N$19,MATCH("Chilevisión|H1 2025",Datos!$A$2:$A$19,0))),INDEX(Datos!$N$2:$N$19,MATCH("Chilevisión|H1 2025",Datos!$A$2:$A$19,0)),"n.d.")) -> 0.95082266 | E23: =IF(ISNA(MATCH("Chilevisión|H1 2026",Datos!$A$2:$A$19,0)),"n.d.",IF(ISNUMBER(INDEX(Datos!$N$2:$N$19,MATCH("Chilevisión|H1 2026",Datos!$A$2:$A$19,0))),INDEX(Datos!$N$2:$N$19,MATCH("Chilevisión|H1 2026",Datos!$A$2:$A$19,0)),"n.d.")) -> 0.9089824
A25: Referencia Napoli (EE.UU., c. 2001): broadcast television 100% / 0%; cable television networks 60% / 40%.
A26: n.d. = sin cifra de publicidad para ese período. Mega: 'Publicidad TV' incluye internet (la nota no los separa).

Sheet Datos
A1: Clave | B1: Canal | C1: Período | D1: Tipo | E1: Fuente del dato | F1: Ingresos ordinarios (M$) | G1: Publicidad TV (M$) | H1: Publicidad digital (M$) | I1: Publicidad radio/cable (M$) | J1: Venta de audiencias total (M$) | K1: Contenidos + otros (M$) | L1: % Audiencias | M1: % Contenidos + otros | N1: % Publicidad TV | O1: Fuente | P1: Nota
A2: =B2&"|"&C2 -> TVN|FY2024 | B2: TVN | C2: FY2024 | D2: Anual | E2: EEFF | F2: 46850034 | G2: 29763217 | J2: =IF(G2="","",SUM(G2:I2)) -> 29763217 | K2: =IF(J2="","",F2-J2) -> 17086817 | L2: =IF(J2="","",J2/F2) -> 0.63528699 | M2: =IF(J2="","",1-L2) -> 0.36471301 | N2: =IF(G2="","",G2/F2) -> 0.63528699 | O2: EEFF Televisión Nacional de Chile al 31-dic-2024, Nota 21 a) | P2: 'Otros ingresos' 17.086.817: principalmente venta de señal internacional a operadores de TV pago y otros servicios derivados de la actividad televisiva. Sin subvención NTV. 2023 (ref.): publicidad 34.655.366; otros 17.370.782; total 52.026.148.
A3: =B3&"|"&C3 -> TVN|FY2025 | B3: TVN | C3: FY2025 | D3: Anual | E3: EEFF | F3: 47915398 | G3: 28787675 | J3: =IF(G3="","",SUM(G3:I3)) -> 28787675 | K3: =IF(J3="","",F3-J3) -> 19127723 | L3: =IF(J3="","",J3/F3) -> 0.60080217 | M3: =IF(J3="","",1-L3) -> 0.39919783 | N3: =IF(G3="","",G3/F3) -> 0.60080217 | O3: EEFF Televisión Nacional de Chile al 31-dic-2025, Nota 22 a) y Nota 1 (subvención NTV) | P3: Otros ingresos 19.127.723, que incluyen M$2.000.000 de subvención estatal NTV (Ley 19.132 art. 37). Publicidad = total − otros (tabla de la nota con fuente ilegible en el PDF; cifras de texto y comparativos confirman).
A4: =B4&"|"&C4 -> TVN|H1 2025 | B4: TVN | C4: H1 2025 | D4: Semestral | E4: EEFF | F4: 24237233 | G4: 14095458 | J4: =IF(G4="","",SUM(G4:I4)) -> 14095458 | K4: =IF(J4="","",F4-J4) -> 10141775 | L4: =IF(J4="","",J4/F4) -> 0.58156218 | M4: =IF(J4="","",1-L4) -> 0.41843782 | N4: =IF(G4="","",G4/F4) -> 0.58156218 | O4: EEFF intermedios Televisión Nacional de Chile al 30-jun-2026, Nota 22 a) | P4: Comparativo EEFF jun-2026: otros ingresos 8.141.775 + subvención NTV 2.000.000.
A5: =B5&"|"&C5 -> TVN|H1 2026 | B5: TVN | C5: H1 2026 | D5: Semestral | E5: EEFF | F5: 22291139 | G5: 12596474 | J5: =IF(G5="","",SUM(G5:I5)) -> 12596474 | K5: =IF(J5="","",F5-J5) -> 9694665 | L5: =IF(J5="","",J5/F5) -> 0.56508885 | M5: =IF(J5="","",1-L5) -> 0.43491115 | N5: =IF(G5="","",G5/F5) -> 0.56508885 | O5: EEFF intermedios Televisión Nacional de Chile al 30-jun-2026, Nota 22 a) | P5: Otros ingresos 7.990.951 + subvención NTV 1.703.714.
A6: =B6&"|"&C6 -> Canal 13|FY2024 | B6: Canal 13 | C6: FY2024 | D6: Anual | E6: EEFF | F6: 78910289 | G6: 57302601 | H6: 2642229 | I6: 0 | J6: =IF(G6="","",SUM(G6:I6)) -> 59944830 | K6: =IF(J6="","",F6-J6) -> 18965459 | L6: =IF(J6="","",J6/F6) -> 0.75965797 | M6: =IF(J6="","",1-L6) -> 0.24034203 | N6: =IF(G6="","",G6/F6) -> 0.72617401 | O6: EEFF Canal 13 SpA al 31-dic-2024 (auditor EY), Nota 20 'Ingresos de actividades ordinarias'; coincide con el comparativo de los EEFF 2025 | P6: Sin reexpresión: EEFF 2024 y comparativo 2025 coinciden. 2023 (referencia): pantalla abierta 52.680.675; otras plataformas 3.244.433; otros 16.137.671; total 72.062.779. 'Otros ingresos de explotación' 18.965.459 incluye cableoperadores, digital no publicitario, nuevas señales, venta de contenidos, venta de activos y arriendos.
A7: =B7&"|"&C7 -> Canal 13|FY2025 | B7: Canal 13 | C7: FY2025 | D7: Anual | E7: EEFF | F7: 81549524 | G7: 59951329 | H7: 2617226 | I7: 0 | J7: =IF(G7="","",SUM(G7:I7)) -> 62568555 | K7: =IF(J7="","",F7-J7) -> 18980969 | L7: =IF(J7="","",J7/F7) -> 0.76724611 | M7: =IF(J7="","",1-L7) -> 0.23275389 | N7: =IF(G7="","",G7/F7) -> 0.73515241 | O7: EEFF Canal 13 SpA al 31-dic-2025 (auditor EY), Nota 21 'Ingresos de actividades ordinarias', p. 58 | P7: Otros ingresos de explotación 18.980.969 (misma composición).
A8: =B8&"|"&C8 -> Canal 13|H1 2025 | B8: Canal 13 | C8: H1 2025 | D8: Semestral | E8: EEFF | F8: 37163375 | G8: 26859101 | H8: 1269184 | I8: 0 | J8: =IF(G8="","",SUM(G8:I8)) -> 28128285 | K8: =IF(J8="","",F8-J8) -> 9035090 | L8: =IF(J8="","",J8/F8) -> 0.75688188 | M8: =IF(J8="","",1-L8) -> 0.24311812 | N8: =IF(G8="","",G8/F8) -> 0.7227304 | O8: EEFF intermedios Canal 13 SpA al 30-jun-2026 (no auditados), Nota 21, p. 62 | P8: Comparativo de EEFF jun-2026. Otros ingresos de explotación 9.035.090.
A9: =B9&"|"&C9 -> Canal 13|H1 2026 | B9: Canal 13 | C9: H1 2026 | D9: Semestral | E9: EEFF | F9: 38389971 | G9: 26162497 | H9: 1044544 | I9: 0 | J9: =IF(G9="","",SUM(G9:I9)) -> 27207041 | K9: =IF(J9="","",F9-J9) -> 11182930 | L9: =IF(J9="","",J9/F9) -> 0.70870179 | M9: =IF(J9="","",1-L9) -> 0.29129821 | N9: =IF(G9="","",G9/F9) -> 0.68149301 | O9: EEFF intermedios Canal 13 SpA al 30-jun-2026 (no auditados), Nota 21, p. 62 | P9: Otros ingresos de explotación 11.182.930 (+23,8%); el análisis razonado lo atribuye a 'otros negocios' y ventas en plataformas digitales. Q2-2026 solo: 6.503.584.
A10: =B10&"|"&C10 -> Mega|FY2024 | B10: Mega | C10: FY2024 | D10: Anual | E10: EEFF | F10: 102919851 | G10: 70257656 | I10: 7647449 | J10: =IF(G10="","",SUM(G10:I10)) -> 77905105 | K10: =IF(J10="","",F10-J10) -> 25014746 | L10: =IF(J10="","",J10/F10) -> 0.75694926 | M10: =IF(J10="","",1-L10) -> 0.24305074 | N10: =IF(G10="","",G10/F10) -> 0.68264436 | O10: EEFF consolidados Megamedia S.A. y subsidiarias al 31-dic-2025 (auditor Deloitte), Nota 7 a), p. 37 | P10: Consolidado Megamedia. Publicidad TV + internet no se separa (va en col. TV). 'Plataformas, suscripciones y contenidos' 25.014.746 (de ello 7.064.725 ventas al extranjero). Radio y cable = publicidad radial y canal de cable.
A11: =B11&"|"&C11 -> Mega|FY2025 | B11: Mega | C11: FY2025 | D11: Anual | E11: EEFF | F11: 104840064 | G11: 75154259 | I11: 7559044 | J11: =IF(G11="","",SUM(G11:I11)) -> 82713303 | K11: =IF(J11="","",F11-J11) -> 22126761 | L11: =IF(J11="","",J11/F11) -> 0.78894747 | M11: =IF(J11="","",1-L11) -> 0.21105253 | N11: =IF(G11="","",G11/F11) -> 0.71684675 | O11: EEFF consolidados Megamedia S.A. y subsidiarias al 31-dic-2025 (auditor Deloitte), Nota 7 a), p. 37 | P11: Plataformas, suscripciones y contenidos 22.126.761 (2.436.336 al extranjero). Nota: cifras de 94.456/96.666 citadas en prensa no corresponden al consolidado.
A12: =B12&"|"&C12 -> Mega|H1 2025 | B12: Mega | C12: H1 2025 | D12: Semestral | E12: EEFF | F12: 54549411 | G12: 36244158 | I12: 3350704 | J12: =IF(G12="","",SUM(G12:I12)) -> 39594862 | K12: =IF(J12="","",F12-J12) -> 14954549 | L12: =IF(J12="","",J12/F12) -> 0.72585315 | M12: =IF(J12="","",1-L12) -> 0.27414685 | N12: =IF(G12="","",G12/F12) -> 0.66442804 | O12: EEFF intermedios consolidados Megamedia S.A. al 30-jun-2026, Nota 7 a) | P12: Comparativo EEFF jun-2026. Plataformas y contenidos 14.954.549.
A13: =B13&"|"&C13 -> Mega|Q1 2026 | B13: Mega | C13: Q1 2026 | D13: Trimestral | E13: EEFF | F13: 30354736 | G13: 22647735 | I13: 2197367 | J13: =IF(G13="","",SUM(G13:I13)) -> 24845102 | K13: =IF(J13="","",F13-J13) -> 5509634 | L13: =IF(J13="","",J13/F13) -> 0.81849178 | M13: =IF(J13="","",1-L13) -> 0.18150822 | N13: =IF(G13="","",G13/F13) -> 0.74610219 | O13: EEFF intermedios consolidados Megamedia S.A. al 31-mar-2026, Nota 7 a) | P13: Plataformas y contenidos 5.509.634.
A14: =B14&"|"&C14 -> Mega|H1 2026 | B14: Mega | C14: H1 2026 | D14: Semestral | E14: EEFF | F14: 56434970 | G14: 42107628 | I14: 4223409 | J14: =IF(G14="","",SUM(G14:I14)) -> 46331037 | K14: =IF(J14="","",F14-J14) -> 10103933 | L14: =IF(J14="","",J14/F14) -> 0.82096326 | M14: =IF(J14="","",1-L14) -> 0.17903674 | N14: =IF(G14="","",G14/F14) -> 0.74612652 | O14: EEFF intermedios consolidados Megamedia S.A. al 30-jun-2026, Nota 7 a) | P14: Plataformas y contenidos 10.103.933 (−32,4% a/a); publicidad TV+internet +16,2%.
A15: =B15&"|"&C15 -> Chilevisión|FY2024 | B15: Chilevisión | C15: FY2024 | D15: Anual | E15: EEFF | F15: 73317526 | G15: 66752603 | J15: =IF(G15="","",SUM(G15:I15)) -> 66752603 | K15: =IF(J15="","",F15-J15) -> 6564923 | L15: =IF(J15="","",J15/F15) -> 0.91045902 | M15: =IF(J15="","",1-L15) -> 0.089540978 | N15: =IF(G15="","",G15/F15) -> 0.91045902 | O15: EEFF Red de Televisión Chilevisión S.A. al 31-dic-2025, Nota 20, p. 45 | P15: Comparativo de EEFF 2025. 'Publicidad' = TV abierta + comisión TV paga. 'Nuevos negocios' 6.564.923 incluye fee de administración, publicidad por internet, venta de señales y contenido (no separables).
A16: =B16&"|"&C16 -> Chilevisión|FY2025 | B16: Chilevisión | C16: FY2025 | D16: Anual | E16: EEFF | F16: 72498180 | G16: 64981856 | J16: =IF(G16="","",SUM(G16:I16)) -> 64981856 | K16: =IF(J16="","",F16-J16) -> 7516324 | L16: =IF(J16="","",J16/F16) -> 0.89632396 | M16: =IF(J16="","",1-L16) -> 0.10367604 | N16: =IF(G16="","",G16/F16) -> 0.89632396 | O16: EEFF Red de Televisión Chilevisión S.A. al 31-dic-2025, Nota 20, p. 45 | P16: Nuevos negocios 7.516.324. La publicidad digital está dentro de nuevos negocios → % audiencias subestimado.
A17: =B17&"|"&C17 -> Chilevisión|H1 2025 | B17: Chilevisión | C17: H1 2025 | D17: Semestral | E17: EEFF | F17: 35226547 | G17: 33494199 | J17: =IF(G17="","",SUM(G17:I17)) -> 33494199 | K17: =IF(J17="","",F17-J17) -> 1732348 | L17: =IF(J17="","",J17/F17) -> 0.95082266 | M17: =IF(J17="","",1-L17) -> 0.049177343 | N17: =IF(G17="","",G17/F17) -> 0.95082266 | O17: EEFF intermedios Red de Televisión Chilevisión S.A. al 30-jun-2026, Nota 20 | P17: Comparativo EEFF jun-2026: nuevos negocios 1.732.348. OJO: los EEFF a sep-2025 implican para H1-2025 publicidad 31.256.166 y nuevos negocios 3.970.381 (mismo total). El comparativo 2026 traslada ~M$2.238.033 de nuevos negocios a publicidad sin nota explicativa. Se usa el comparativo 2026 por consistencia con H1-2026; FY2024/FY2025 siguen la clasificación anterior.
A18: =B18&"|"&C18 -> Chilevisión|Q1 2026 | B18: Chilevisión | C18: Q1 2026 | D18: Trimestral | E18: EEFF | F18: 15107634 | G18: 13733801 | J18: =IF(G18="","",SUM(G18:I18)) -> 13733801 | K18: =IF(J18="","",F18-J18) -> 1373833 | L18: =IF(J18="","",J18/F18) -> 0.90906366 | M18: =IF(J18="","",1-L18) -> 0.090936344 | N18: =IF(G18="","",G18/F18) -> 0.90906366 | O18: EEFF intermedios Red de Televisión Chilevisión S.A. al 31-mar-2026, Nota 20 | P18: Nuevos negocios 1.373.833.
A19: =B19&"|"&C19 -> Chilevisión|H1 2026 | B19: Chilevisión | C19: H1 2026 | D19: Semestral | E19: EEFF | F19: 36231357 | G19: 32933666 | J19: =IF(G19="","",SUM(G19:I19)) -> 32933666 | K19: =IF(J19="","",F19-J19) -> 3297691 | L19: =IF(J19="","",J19/F19) -> 0.9089824 | M19: =IF(J19="","",1-L19) -> 0.091017596 | N19: =IF(G19="","",G19/F19) -> 0.9089824 | O19: EEFF intermedios Red de Televisión Chilevisión S.A. al 30-jun-2026, Nota 20 | P19: Nuevos negocios 3.297.691 (+90% a/a); la empresa lo atribuye a negocios digitales y distribución.
B21: Leyenda: azul = cifra de la fuente; negro = fórmula. Filas en fondo salmón = cifra de prensa (en M$ = millones×1.000), a reemplazar con EEFF. M$ = miles de pesos nominales.

Sheet Líneas codificadas
A1: Canal | B1: Período | C1: Fuente | D1: Línea (texto de la nota) | E1: Monto (M$) | F1: Código Napoli principal | G1: Pureza | H1: ¿Puede ser Audiencias? | I1: ¿Puede ser Contenidos? | J1: ¿Puede ser Fuera? | K1: Medio | L1: Justificación | M1: Documento | N1: Nivel 1 (básico) | O1: Nivel 2 (común máximo)
A2: Canal 13 | B2: FY2024 | C2: EEFF | D2: Ingresos de Publicidad Pantalla abierta | E2: 57302601 | F2: Audiencias | G2: Pura | H2: S | I2: N | J2: N | K2: TV abierta | L2: Venta de espacios publicitarios en señal abierta. | M2: EEFF Canal 13 SpA dic-2024, Nota 20 | N2: Publicidad | O2: Publicidad
A3: Canal 13 | B3: FY2024 | C3: EEFF | D3: Ingresos de Publicidad Otras plataformas | E3: 2642229 | F3: Audiencias | G3: Pura | H3: S | I3: N | J3: N | K3: Digital | L3: Publicidad en sitios y plataformas digitales del canal. | M3: EEFF Canal 13 SpA dic-2024, Nota 20 | N3: Publicidad | O3: Publicidad
A4: Canal 13 | B4: FY2024 | C4: EEFF | D4: Otros ingresos de explotación | E4: 18965459 | F4: Contenidos | G4: Mixta | H4: N | I4: S | J4: S | K4: Mixto | L4: Según nota (a): cableoperadores, digital no publicitario, nuevas señales y venta de contenidos (Contenidos) + venta de activos, arriendos y servicios a productoras (Fuera). Código principal = Contenidos por declaración del análisis razonado. | M4: EEFF Canal 13 SpA dic-2024, Nota 20 | N4: Otros ingresos | O4: Otros ingresos operacionales
A5: Canal 13 | B5: FY2025 | C5: EEFF | D5: Ingresos de Publicidad Pantalla abierta | E5: 59951329 | F5: Audiencias | G5: Pura | H5: S | I5: N | J5: N | K5: TV abierta | L5: Venta de espacios publicitarios en señal abierta. | M5: EEFF Canal 13 SpA dic-2025, Nota 21 | N5: Publicidad | O5: Publicidad
A6: Canal 13 | B6: FY2025 | C6: EEFF | D6: Ingresos de Publicidad Otras plataformas | E6: 2617226 | F6: Audiencias | G6: Pura | H6: S | I6: N | J6: N | K6: Digital | L6: Publicidad en sitios y plataformas digitales del canal. | M6: EEFF Canal 13 SpA dic-2025, Nota 21 | N6: Publicidad | O6: Publicidad
A7: Canal 13 | B7: FY2025 | C7: EEFF | D7: Otros ingresos de explotación | E7: 18980969 | F7: Contenidos | G7: Mixta | H7: N | I7: S | J7: S | K7: Mixto | L7: Según nota (a): cableoperadores, digital no publicitario, nuevas señales y venta de contenidos (Contenidos) + venta de activos, arriendos y servicios a productoras (Fuera). Código principal = Contenidos por declaración del análisis razonado. | M7: EEFF Canal 13 SpA dic-2025, Nota 21 | N7: Otros ingresos | O7: Otros ingresos operacionales
A8: Canal 13 | B8: H1 2025 | C8: EEFF | D8: Ingresos de Publicidad Pantalla abierta | E8: 26859101 | F8: Audiencias | G8: Pura | H8: S | I8: N | J8: N | K8: TV abierta | L8: Venta de espacios publicitarios en señal abierta. | M8: EEFF Canal 13 SpA jun-2026, Nota 21 | N8: Publicidad | O8: Publicidad
A9: Canal 13 | B9: H1 2025 | C9: EEFF | D9: Ingresos de Publicidad Otras plataformas | E9: 1269184 | F9: Audiencias | G9: Pura | H9: S | I9: N | J9: N | K9: Digital | L9: Publicidad en sitios y plataformas digitales del canal. | M9: EEFF Canal 13 SpA jun-2026, Nota 21 | N9: Publicidad | O9: Publicidad
A10: Canal 13 | B10: H1 2025 | C10: EEFF | D10: Otros ingresos de explotación | E10: 9035090 | F10: Contenidos | G10: Mixta | H10: N | I10: S | J10: S | K10: Mixto | L10: Según nota (a): cableoperadores, digital no publicitario, nuevas señales y venta de contenidos (Contenidos) + venta de activos, arriendos y servicios a productoras (Fuera). Código principal = Contenidos por declaración del análisis razonado. | M10: EEFF Canal 13 SpA jun-2026, Nota 21 | N10: Otros ingresos | O10: Otros ingresos operacionales
A11: Canal 13 | B11: H1 2026 | C11: EEFF | D11: Ingresos de Publicidad Pantalla abierta | E11: 26162497 | F11: Audiencias | G11: Pura | H11: S | I11: N | J11: N | K11: TV abierta | L11: Venta de espacios publicitarios en señal abierta. | M11: EEFF Canal 13 SpA jun-2026, Nota 21 | N11: Publicidad | O11: Publicidad
A12: Canal 13 | B12: H1 2026 | C12: EEFF | D12: Ingresos de Publicidad Otras plataformas | E12: 1044544 | F12: Audiencias | G12: Pura | H12: S | I12: N | J12: N | K12: Digital | L12: Publicidad en sitios y plataformas digitales del canal. | M12: EEFF Canal 13 SpA jun-2026, Nota 21 | N12: Publicidad | O12: Publicidad
A13: Canal 13 | B13: H1 2026 | C13: EEFF | D13: Otros ingresos de explotación | E13: 11182930 | F13: Contenidos | G13: Mixta | H13: N | I13: S | J13: S | K13: Mixto | L13: Según nota (a): cableoperadores, digital no publicitario, nuevas señales y venta de contenidos (Contenidos) + venta de activos, arriendos y servicios a productoras (Fuera). Código principal = Contenidos por declaración del análisis razonado. | M13: EEFF Canal 13 SpA jun-2026, Nota 21 | N13: Otros ingresos | O13: Otros ingresos operacionales
... A49: Chilevisión | B49: H1 2026 | C49: EEFF | D49: Ingresos nuevos negocios | E49: 3297691 | F49: Contenidos | G49: Mixta | H49: S | I49: S | J49: S | K49: Mixto | L49: Según política contable 2026: venta de publicidad por internet (Audiencias), venta de señales y licencias de contenido (Contenidos), fee de administración cost-plus y concursos telefónicos/por internet (Fuera). Código principal = Contenidos. | M49: EEFF Chilevisión jun-2026, Nota 20 | N49: Otros ingresos | O49: Otros ingresos operacionales
A51: Celdas amarillas = decisiones de codificación editables (listas desplegables). Regla: una línea Pura tiene una sola 'S' coincidente con su código; una Mixta marca 'S' en cada categoría que su descripción admite. Pisos/techos en hoja 'Rangos' se recalculan solos.
A52: Filas de prensa (fondo salmón): la línea 'Resto' es el residuo total − publicidad, marcado Mixto con las tres categorías posibles. Mega H1 2026 y CHV H1 2026 no se codifican: la prensa no da publicidad.

Sheet Rangos
A1: Canal | B1: Período | C1: Fuente | D1: Total (M$) | E1: Aud. piso | F1: Aud. techo | G1: Cont. piso | H1: Cont. techo | I1: Fuera piso | J1: Fuera techo | K1: Aud. punto | L1: Cont. punto | M1: Fuera punto | N1: % Aud. piso | O1: % Aud. techo | P1: % Cont. piso | Q1: % Cont. techo | R1: % Fuera piso | S1: % Fuera techo | T1: % Aud. punto | U1: % Cont. punto | V1: Radio/cable (M$) | W1: % Aud. perímetro TV (piso) | X1: Cuadre vs hoja Datos (M$)
A2: Canal 13 | B2: FY2024 | C2: EEFF | D2: =SUMIFS('Líneas codificadas'!$E$2:$E$49,'Líneas codificadas'!$A$2:$A$49,$A2,'Líneas codificadas'!$B$2:$B$49,$B2) -> 78910289 | E2: =SUMIFS('Líneas codificadas'!$E$2:$E$49,'Líneas codificadas'!$A$2:$A$49,$A2,'Líneas codificadas'!$B$2:$B$49,$B2,'Líneas codificadas'!$F$2:$F$49,"Audiencias",'Líneas codificadas'!$G$2:$G$49,"Pura") -> 59944830 | F2: =SUMIFS('Líneas codificadas'!$E$2:$E$49,'Líneas codificadas'!$A$2:$A$49,$A2,'Líneas codificadas'!$B$2:$B$49,$B2,'Líneas codificadas'!$H$2:$H$49,"S") -> 59944830 | G2: =SUMIFS('Líneas codificadas'!$E$2:$E$49,'Líneas codificadas'!$A$2:$A$49,$A2,'Líneas codificadas'!$B$2:$B$49,$B2,'Líneas codificadas'!$F$2:$F$49,"Contenidos",'Líneas codificadas'!$G$2:$G$49,"Pura") -> 0 | H2: =SUMIFS('Líneas codificadas'!$E$2:$E$49,'Líneas codificadas'!$A$2:$A$49,$A2,'Líneas codificadas'!$B$2:$B$49,$B2,'Líneas codificadas'!$I$2:$I$49,"S") -> 18965459 | I2: =SUMIFS('Líneas codificadas'!$E$2:$E$49,'Líneas codificadas'!$A$2:$A$49,$A2,'Líneas codificadas'!$B$2:$B$49,$B2,'Líneas codificadas'!$F$2:$F$49,"Fuera de Napoli",'Líneas codificadas'!$G$2:$G$49,"Pura") -> 0 | J2: =SUMIFS('Líneas codificadas'!$E$2:$E$49,'Líneas codificadas'!$A$2:$A$49,$A2,'Líneas codificadas'!$B$2:$B$49,$B2,'Líneas codificadas'!$J$2:$J$49,"S") -> 18965459 | K2: =SUMIFS('Líneas codificadas'!$E$2:$E$49,'Líneas codificadas'!$A$2:$A$49,$A2,'Líneas codificadas'!$B$2:$B$49,$B2,'Líneas codificadas'!$F$2:$F$49,"Audiencias") -> 59944830 | L2: =SUMIFS('Líneas codificadas'!$E$2:$E$49,'Líneas codificadas'!$A$2:$A$49,$A2,'Líneas codificadas'!$B$2:$B$49,$B2,'Líneas codificadas'!$F$2:$F$49,"Contenidos") -> 18965459 | M2: =SUMIFS('Líneas codificadas'!$E$2:$E$49,'Líneas codificadas'!$A$2:$A$49,$A2,'Líneas codificadas'!$B$2:$B$49,$B2,'Líneas codificadas'!$F$2:$F$49,"Fuera de Napoli") -> 0 | N2: =IF($D2=0,"",E2/$D2) -> 0.75965797 | O2: =IF($D2=0,"",F2/$D2) -> 0.75965797 | P2: =IF($D2=0,"",G2/$D2) -> 0 | Q2: =IF($D2=0,"",H2/$D2) -> 0.24034203 | R2: =IF($D2=0,"",I2/$D2) -> 0 | S2: =IF($D2=0,"",J2/$D2) -> 0.24034203 | T2: =IF($D2=0,"",K2/$D2) -> 0.75965797 | U2: =IF($D2=0,"",L2/$D2) -> 0.24034203 | V2: =SUMIFS('Líneas codificadas'!$E$2:$E$49,'Líneas codificadas'!$A$2:$A$49,$A2,'Líneas codificadas'!$B$2:$B$49,$B2,'Líneas codificadas'!$K$2:$K$49,"Radio/cable") -> 0 | W2: =IF(($D2-V2)=0,"",(E2-V2)/($D2-V2)) -> 0.75965797 | X2: =D2-INDEX(Datos!$F$2:$F$19,MATCH(A2&"|"&B2,Datos!$A$2:$A$19,0)) -> 0
A3: Canal 13 | B3: FY2025 | C3: EEFF | D3: =SUMIFS('Líneas codificadas'!$E$2:$E$49,'Líneas codificadas'!$A$2:$A$49,$A3,'Líneas codificadas'!$B$2:$B$49,$B3) -> 81549524 | E3: =SUMIFS('Líneas codificadas'!$E$2:$E$49,'Líneas codificadas'!$A$2:$A$49,$A3,'Líneas codificadas'!$B$2:$B$49,$B3,'Líneas codificadas'!$F$2:$F$49,"Audiencias",'Líneas codificadas'!$G$2:$G$49,"Pura") -> 62568555 | F3: =SUMIFS('Líneas codificadas'!$E$2:$E$49,'Líneas codificadas'!$A$2:$A$49,$A3,'Líneas codificadas'!$B$2:$B$49,$B3,'Líneas codificadas'!$H$2:$H$49,"S") -> 62568555 | G3: =SUMIFS('Líneas codificadas'!$E$2:$E$49,'Líneas codificadas'!$A$2:$A$49,$A3,'Líneas codificadas'!$B$2:$B$49,$B3,'Líneas codificadas'!$F$2:$F$49,"Contenidos",'Líneas codificadas'!$G$2:$G$49,"Pura") -> 0 | H3: =SUMIFS('Líneas codificadas'!$E$2:$E$49,'Líneas codificadas'!$A$2:$A$49,$A3,'Líneas codificadas'!$B$2:$B$49,$B3,'Líneas codificadas'!$I$2:$I$49,"S") -> 18980969 | I3: =SUMIFS('Líneas codificadas'!$E$2:$E$49,'Líneas codificadas'!$A$2:$A$49,$A3,'Líneas codificadas'!$B$2:$B$49,$B3,'Líneas codificadas'!$F$2:$F$49,"Fuera de Napoli",'Líneas codificadas'!$G$2:$G$49,"Pura") -> 0 | J3: =SUMIFS('Líneas codificadas'!$E$2:$E$49,'Líneas codificadas'!$A$2:$A$49,$A3,'Líneas codificadas'!$B$2:$B$49,$B3,'Líneas codificadas'!$J$2:$J$49,"S") -> 18980969 | K3: =SUMIFS('Líneas codificadas'!$E$2:$E$49,'Líneas codificadas'!$A$2:$A$49,$A3,'Líneas codificadas'!$B$2:$B$49,$B3,'Líneas codificadas'!$F$2:$F$49,"Audiencias") -> 62568555 | L3: =SUMIFS('Líneas codificadas'!$E$2:$E$49,'Líneas codificadas'!$A$2:$A$49,$A3,'Líneas codificadas'!$B$2:$B$49,$B3,'Líneas codificadas'!$F$2:$F$49,"Contenidos") -> 18980969 | M3: =SUMIFS('Líneas codificadas'!$E$2:$E$49,'Líneas codificadas'!$A$2:$A$49,$A3,'Líneas codificadas'!$B$2:$B$49,$B3,'Líneas codificadas'!$F$2:$F$49,"Fuera de Napoli") -> 0 | N3: =IF($D3=0,"",E3/$D3) -> 0.76724611 | O3: =IF($D3=0,"",F3/$D3) -> 0.76724611 | P3: =IF($D3=0,"",G3/$D3) -> 0 | Q3: =IF($D3=0,"",H3/$D3) -> 0.23275389 | R3: =IF($D3=0,"",I3/$D3) -> 0 | S3: =IF($D3=0,"",J3/$D3) -> 0.23275389 | T3: =IF($D3=0,"",K3/$D3) -> 0.76724611 | U3: =IF($D3=0,"",L3/$D3) -> 0.23275389 | V3: =SUMIFS('Líneas codificadas'!$E$2:$E$49,'Líneas codificadas'!$A$2:$A$49,$A3,'Líneas codificadas'!$B$2:$B$49,$B3,'Líneas codificadas'!$K$2:$K$49,"Radio/cable") -> 0 | W3: =IF(($D3-V3)=0,"",(E3-V3)/($D3-V3)) -> 0.76724611 | X3: =D3-INDEX(Datos!$F$2:$F$19,MATCH(A3&"|"&B3,Datos!$A$2:$A$19,0)) -> 0
A4: Canal 13 | B4: H1 2025 | C4: EEFF | D4: =SUMIFS('Líneas codificadas'!$E$2:$E$49,'Líneas codificadas'!$A$2:$A$49,$A4,'Líneas codificadas'!$B$2:$B$49,$B4) -> 37163375 | E4: =SUMIFS('Líneas codificadas'!$E$2:$E$49,'Líneas codificadas'!$A$2:$A$49,$A4,'Líneas codificadas'!$B$2:$B$49,$B4,'Líneas codificadas'!$F$2:$F$49,"Audiencias",'Líneas codificadas'!$G$2:$G$49,"Pura") -> 28128285 | F4: =SUMIFS('Líneas codificadas'!$E$2:$E$49,'Líneas codificadas'!$A$2:$A$49,$A4,'Líneas codificadas'!$B$2:$B$49,$B4,'Líneas codificadas'!$H$2:$H$49,"S") -> 28128285 | G4: =SUMIFS('Líneas codificadas'!$E$2:$E$49,'Líneas codificadas'!$A$2:$A$49,$A4,'Líneas codificadas'!$B$2:$B$49,$B4,'Líneas codificadas'!$F$2:$F$49,"Contenidos",'Líneas codificadas'!$G$2:$G$49,"Pura") -> 0 | H4: =SUMIFS('Líneas codificadas'!$E$2:$E$49,'Líneas codificadas'!$A$2:$A$49,$A4,'Líneas codificadas'!$B$2:$B$49,$B4,'Líneas codificadas'!$I$2:$I$49,"S") -> 9035090 | I4: =SUMIFS('Líneas codificadas'!$E$2:$E$49,'Líneas codificadas'!$A$2:$A$49,$A4,'Líneas codificadas'!$B$2:$B$49,$B4,'Líneas codificadas'!$F$2:$F$49,"Fuera de Napoli",'Líneas codificadas'!$G$2:$G$49,"Pura") -> 0 | J4: =SUMIFS('Líneas codificadas'!$E$2:$E$49,'Líneas codificadas'!$A$2:$A$49,$A4,'Líneas codificadas'!$B$2:$B$49,$B4,'Líneas codificadas'!$J$2:$J$49,"S") -> 9035090 | K4: =SUMIFS('Líneas codificadas'!$E$2:$E$49,'Líneas codificadas'!$A$2:$A$49,$A4,'Líneas codificadas'!$B$2:$B$49,$B4,'Líneas codificadas'!$F$2:$F$49,"Audiencias") -> 28128285 | L4: =SUMIFS('Líneas codificadas'!$E$2:$E$49,'Líneas codificadas'!$A$2:$A$49,$A4,'Líneas codificadas'!$B$2:$B$49,$B4,'Líneas codificadas'!$F$2:$F$49,"Contenidos") -> 9035090 | M4: =SUMIFS('Líneas codificadas'!$E$2:$E$49,'Líneas codificadas'!$A$2:$A$49,$A4,'Líneas codificadas'!$B$2:$B$49,$B4,'Líneas codificadas'!$F$2:$F$49,"Fuera de Napoli") -> 0 | N4: =IF($D4=0,"",E4/$D4) -> 0.75688188 | O4: =IF($D4=0,"",F4/$D4) -> 0.75688188 | P4: =IF($D4=0,"",G4/$D4) -> 0 | Q4: =IF($D4=0,"",H4/$D4) -> 0.24311812 | R4: =IF($D4=0,"",I4/$D4) -> 0 | S4: =IF($D4=0,"",J4/$D4) -> 0.24311812 | T4: =IF($D4=0,"",K4/$D4) -> 0.75688188 | U4: =IF($D4=0,"",L4/$D4) -> 0.24311812 | V4: =SUMIFS('Líneas codificadas'!$E$2:$E$49,'Líneas codificadas'!$A$2:$A$49,$A4,'Líneas codificadas'!$B$2:$B$49,$B4,'Líneas codificadas'!$K$2:$K$49,"Radio/cable") -> 0 | W4: =IF(($D4-V4)=0,"",(E4-V4)/($D4-V4)) -> 0.75688188 | X4: =D4-INDEX(Datos!$F$2:$F$19,MATCH(A4&"|"&B4,Datos!$A$2:$A$19,0)) -> 0
A5: Canal 13 | B5: H1 2026 | C5: EEFF | D5: =SUMIFS('Líneas codificadas'!$E$2:$E$49,'Líneas codificadas'!$A$2:$A$49,$A5,'Líneas codificadas'!$B$2:$B$49,$B5) -> 38389971 | E5: =SUMIFS('Líneas codificadas'!$E$2:$E$49,'Líneas codificadas'!$A$2:$A$49,$A5,'Líneas codificadas'!$B$2:$B$49,$B5,'Líneas codificadas'!$F$2:$F$49,"Audiencias",'Líneas codificadas'!$G$2:$G$49,"Pura") -> 27207041 | F5: =SUMIFS('Líneas codificadas'!$E$2:$E$49,'Líneas codificadas'!$A$2:$A$49,$A5,'Líneas codificadas'!$B$2:$B$49,$B5,'Líneas codificadas'!$H$2:$H$49,"S") -> 27207041 | G5: =SUMIFS('Líneas codificadas'!$E$2:$E$49,'Líneas codificadas'!$A$2:$A$49,$A5,'Líneas codificadas'!$B$2:$B$49,$B5,'Líneas codificadas'!$F$2:$F$49,"Contenidos",'Líneas codificadas'!$G$2:$G$49,"Pura") -> 0 | H5: =SUMIFS('Líneas codificadas'!$E$2:$E$49,'Líneas codificadas'!$A$2:$A$49,$A5,'Líneas codificadas'!$B$2:$B$49,$B5,'Líneas codificadas'!$I$2:$I$49,"S") -> 11182930 | I5: =SUMIFS('Líneas codificadas'!$E$2:$E$49,'Líneas codificadas'!$A$2:$A$49,$A5,'Líneas codificadas'!$B$2:$B$49,$B5,'Líneas codificadas'!$F$2:$F$49,"Fuera de Napoli",'Líneas codificadas'!$G$2:$G$49,"Pura") -> 0 | J5: =SUMIFS('Líneas codificadas'!$E$2:$E$49,'Líneas codificadas'!$A$2:$A$49,$A5,'Líneas codificadas'!$B$2:$B$49,$B5,'Líneas codificadas'!$J$2:$J$49,"S") -> 11182930 | K5: =SUMIFS('Líneas codificadas'!$E$2:$E$49,'Líneas codificadas'!$A$2:$A$49,$A5,'Líneas codificadas'!$B$2:$B$49,$B5,'Líneas codificadas'!$F$2:$F$49,"Audiencias") -> 27207041 | L5: =SUMIFS('Líneas codificadas'!$E$2:$E$49,'Líneas codificadas'!$A$2:$A$49,$A5,'Líneas codificadas'!$B$2:$B$49,$B5,'Líneas codificadas'!$F$2:$F$49,"Contenidos") -> 11182930 | M5: =SUMIFS('Líneas codificadas'!$E$2:$E$49,'Líneas codificadas'!$A$2:$A$49,$A5,'Líneas codificadas'!$B$2:$B$49,$B5,'Líneas codificadas'!$F$2:$F$49,"Fuera de Napoli") -> 0 | N5: =IF($D5=0,"",E5/$D5) -> 0.70870179 | O5: =IF($D5=0,"",F5/$D5) -> 0.70870179 | P5: =IF($D5=0,"",G5/$D5) -> 0 | Q5: =IF($D5=0,"",H5/$D5) -> 0.29129821 | R5: =IF($D5=0,"",I5/$D5) -> 0 | S5: =IF($D5=0,"",J5/$D5) -> 0.29129821 | T5: =IF($D5=0,"",K5/$D5) -> 0.70870179 | U5: =IF($D5=0,"",L5/$D5) -> 0.29129821 | V5: =SUMIFS('Líneas codificadas'!$E$2:$E$49,'Líneas codificadas'!$A$2:$A$49,$A5,'Líneas codificadas'!$B$2:$B$49,$B5,'Líneas codificadas'!$K$2:$K$49,"Radio/cable") -> 0 | W5: =IF(($D5-V5)=0,"",(E5-V5)/($D5-V5)) -> 0.70870179 | X5: =D5-INDEX(Datos!$F$2:$F$19,MATCH(A5&"|"&B5,Datos!$A$2:$A$19,0)) -> 0
A6: Mega | B6: FY2024 | C6: EEFF | D6: =SUMIFS('Líneas codificadas'!$E$2:$E$49,'Líneas codificadas'!$A$2:$A$49,$A6,'Líneas codificadas'!$B$2:$B$49,$B6) -> 102919851 | E6: =SUMIFS('Líneas codificadas'!$E$2:$E$49,'Líneas codificadas'!$A$2:$A$49,$A6,'Líneas codificadas'!$B$2:$B$49,$B6,'Líneas codificadas'!$F$2:$F$49,"Audiencias",'Líneas codificadas'!$G$2:$G$49,"Pura") -> 77905105 | F6: =SUMIFS('Líneas codificadas'!$E$2:$E$49,'Líneas codificadas'!$A$2:$A$49,$A6,'Líneas codificadas'!$B$2:$B$49,$B6,'Líneas codificadas'!$H$2:$H$49,"S") -> 77905105 | G6: =SUMIFS('Líneas codificadas'!$E$2:$E$49,'Líneas codificadas'!$A$2:$A$49,$A6,'Líneas codificadas'!$B$2:$B$49,$B6,'Líneas codificadas'!$F$2:$F$49,"Contenidos",'Líneas codificadas'!$G$2:$G$49,"Pura") -> 25014746 | H6: =SUMIFS('Líneas codificadas'!$E$2:$E$49,'Líneas codificadas'!$A$2:$A$49,$A6,'Líneas codificadas'!$B$2:$B$49,$B6,'Líneas codificadas'!$I$2:$I$49,"S") -> 25014746 | I6: =SUMIFS('Líneas codificadas'!$E$2:$E$49,'Líneas codificadas'!$A$2:$A$49,$A6,'Líneas codificadas'!$B$2:$B$49,$B6,'Líneas codificadas'!$F$2:$F$49,"Fuera de Napoli",'Líneas codificadas'!$G$2:$G$49,"Pura") -> 0 | J6: =SUMIFS('Líneas codificadas'!$E$2:$E$49,'Líneas codificadas'!$A$2:$A$49,$A6,'Líneas codificadas'!$B$2:$B$49,$B6,'Líneas codificadas'!$J$2:$J$49,"S") -> 0 | K6: =SUMIFS('Líneas codificadas'!$E$2:$E$49,'Líneas codificadas'!$A$2:$A$49,$A6,'Líneas codificadas'!$B$2:$B$49,$B6,'Líneas codificadas'!$F$2:$F$49,"Audiencias") -> 77905105 | L6: =SUMIFS('Líneas codificadas'!$E$2:$E$49,'Líneas codificadas'!$A$2:$A$49,$A6,'Líneas codificadas'!$B$2:$B$49,$B6,'Líneas codificadas'!$F$2:$F$49,"Contenidos") -> 25014746 | M6: =SUMIFS('Líneas codificadas'!$E$2:$E$49,'Líneas codificadas'!$A$2:$A$49,$A6,'Líneas codificadas'!$B$2:$B$49,$B6,'Líneas codificadas'!$F$2:$F$49,"Fuera de Napoli") -> 0 | N6: =IF($D6=0,"",E6/$D6) -> 0.75694926 | O6: =IF($D6=0,"",F6/$D6) -> 0.75694926 | P6: =IF($D6=0,"",G6/$D6) -> 0.24305074 | Q6: =IF($D6=0,"",H6/$D6) -> 0.24305074 | R6: =IF($D6=0,"",I6/$D6) -> 0 | S6: =IF($D6=0,"",J6/$D6) -> 0 | T6: =IF($D6=0,"",K6/$D6) -> 0.75694926 | U6: =IF($D6=0,"",L6/$D6) -> 0.24305074 | V6: =SUMIFS('Líneas codificadas'!$E$2:$E$49,'Líneas codificadas'!$A$2:$A$49,$A6,'Líneas codificadas'!$B$2:$B$49,$B6,'Líneas codificadas'!$K$2:$K$49,"Radio/cable") -> 7647449 | W6: =IF(($D6-V6)=0,"",(E6-V6)/($D6-V6)) -> 0.73743975 | X6: =D6-INDEX(Datos!$F$2:$F$19,MATCH(A6&"|"&B6,Datos!$A$2:$A$19,0)) -> 0
A7: Mega | B7: FY2025 | C7: EEFF | D7: =SUMIFS('Líneas codificadas'!$E$2:$E$49,'Líneas codificadas'!$A$2:$A$49,$A7,'Líneas codificadas'!$B$2:$B$49,$B7) -> 104840064 | E7: =SUMIFS('Líneas codificadas'!$E$2:$E$49,'Líneas codificadas'!$A$2:$A$49,$A7,'Líneas codificadas'!$B$2:$B$49,$B7,'Líneas codificadas'!$F$2:$F$49,"Audiencias",'Líneas codificadas'!$G$2:$G$49,"Pura") -> 82713303 | F7: =SUMIFS('Líneas codificadas'!$E$2:$E$49,'Líneas codificadas'!$A$2:$A$49,$A7,'Líneas codificadas'!$B$2:$B$49,$B7,'Líneas codificadas'!$H$2:$H$49,"S") -> 82713303 | G7: =SUMIFS('Líneas codificadas'!$E$2:$E$49,'Líneas codificadas'!$A$2:$A$49,$A7,'Líneas codificadas'!$B$2:$B$49,$B7,'Líneas codificadas'!$F$2:$F$49,"Contenidos",'Líneas codificadas'!$G$2:$G$49,"Pura") -> 22126761 | H7: =SUMIFS('Líneas codificadas'!$E$2:$E$49,'Líneas codificadas'!$A$2:$A$49,$A7,'Líneas codificadas'!$B$2:$B$49,$B7,'Líneas codificadas'!$I$2:$I$49,"S") -> 22126761 | I7: =SUMIFS('Líneas codificadas'!$E$2:$E$49,'Líneas codificadas'!$A$2:$A$49,$A7,'Líneas codificadas'!$B$2:$B$49,$B7,'Líneas codificadas'!$F$2:$F$49,"Fuera de Napoli",'Líneas codificadas'!$G$2:$G$49,"Pura") -> 0 | J7: =SUMIFS('Líneas codificadas'!$E$2:$E$49,'Líneas codificadas'!$A$2:$A$49,$A7,'Líneas codificadas'!$B$2:$B$49,$B7,'Líneas codificadas'!$J$2:$J$49,"S") -> 0 | K7: =SUMIFS('Líneas codificadas'!$E$2:$E$49,'Líneas codificadas'!$A$2:$A$49,$A7,'Líneas codificadas'!$B$2:$B$49,$B7,'Líneas codificadas'!$F$2:$F$49,"Audiencias") -> 82713303 | L7: =SUMIFS('Líneas codificadas'!$E$2:$E$49,'Líneas codificadas'!$A$2:$A$49,$A7,'Líneas codificadas'!$B$2:$B$49,$B7,'Líneas codificadas'!$F$2:$F$49,"Contenidos") -> 22126761 | M7: =SUMIFS('Líneas codificadas'!$E$2:$E$49,'Líneas codificadas'!$A$2:$A$49,$A7,'Líneas codificadas'!$B$2:$B$49,$B7,'Líneas codificadas'!$F$2:$F$49,"Fuera de Napoli") -> 0 | N7: =IF($D7=0,"",E7/$D7) -> 0.78894747 | O7: =IF($D7=0,"",F7/$D7) -> 0.78894747 | P7: =IF($D7=0,"",G7/$D7) -> 0.21105253 | Q7: =IF($D7=0,"",H7/$D7) -> 0.21105253 | R7: =IF($D7=0,"",I7/$D7) -> 0 | S7: =IF($D7=0,"",J7/$D7) -> 0 | T7: =IF($D7=0,"",K7/$D7) -> 0.78894747 | U7: =IF($D7=0,"",L7/$D7) -> 0.21105253 | V7: =SUMIFS('Líneas codificadas'!$E$2:$E$49,'Líneas codificadas'!$A$2:$A$49,$A7,'Líneas codificadas'!$B$2:$B$49,$B7,'Líneas codificadas'!$K$2:$K$49,"Radio/cable") -> 7559044 | W7: =IF(($D7-V7)=0,"",(E7-V7)/($D7-V7)) -> 0.77254802 | X7: =D7-INDEX(Datos!$F$2:$F$19,MATCH(A7&"|"&B7,Datos!$A$2:$A$19,0)) -> 0
A8: Chilevisión | B8: FY2024 | C8: EEFF | D8: =SUMIFS('Líneas codificadas'!$E$2:$E$49,'Líneas codificadas'!$A$2:$A$49,$A8,'Líneas codificadas'!$B$2:$B$49,$B8) -> 73317526 | E8: =SUMIFS('Líneas codificadas'!$E$2:$E$49,'Líneas codificadas'!$A$2:$A$49,$A8,'Líneas codificadas'!$B$2:$B$49,$B8,'Líneas codificadas'!$F$2:$F$49,"Audiencias",'Líneas codificadas'!$G$2:$G$49,"Pura") -> 66752603 | F8: =SUMIFS('Líneas codificadas'!$E$2:$E$49,'Líneas codificadas'!$A$2:$A$49,$A8,'Líneas codificadas'!$B$2:$B$49,$B8,'Líneas codificadas'!$H$2:$H$49,"S") -> 73317526 | G8: =SUMIFS('Líneas codificadas'!$E$2:$E$49,'Líneas codificadas'!$A$2:$A$49,$A8,'Líneas codificadas'!$B$2:$B$49,$B8,'Líneas codificadas'!$F$2:$F$49,"Contenidos",'Líneas codificadas'!$G$2:$G$49,"Pura") -> 0 | H8: =SUMIFS('Líneas codificadas'!$E$2:$E$49,'Líneas codificadas'!$A$2:$A$49,$A8,'Líneas codificadas'!$B$2:$B$49,$B8,'Líneas codificadas'!$I$2:$I$49,"S") -> 6564923 | I8: =SUMIFS('Líneas codificadas'!$E$2:$E$49,'Líneas codificadas'!$A$2:$A$49,$A8,'Líneas codificadas'!$B$2:$B$49,$B8,'Líneas codificadas'!$F$2:$F$49,"Fuera de Napoli",'Líneas codificadas'!$G$2:$G$49,"Pura") -> 0 | J8: =SUMIFS('Líneas codificadas'!$E$2:$E$49,'Líneas codificadas'!$A$2:$A$49,$A8,'Líneas codificadas'!$B$2:$B$49,$B8,'Líneas codificadas'!$J$2:$J$49,"S") -> 6564923 | K8: =SUMIFS('Líneas codificadas'!$E$2:$E$49,'Líneas codificadas'!$A$2:$A$49,$A8,'Líneas codificadas'!$B$2:$B$49,$B8,'Líneas codificadas'!$F$2:$F$49,"Audiencias") -> 66752603 | L8: =SUMIFS('Líneas codificadas'!$E$2:$E$49,'Líneas codificadas'!$A$2:$A$49,$A8,'Líneas codificadas'!$B$2:$B$49,$B8,'Líneas codificadas'!$F$2:$F$49,"Contenidos") -> 6564923 | M8: =SUMIFS('Líneas codificadas'!$E$2:$E$49,'Líneas codificadas'!$A$2:$A$49,$A8,'Líneas codificadas'!$B$2:$B$49,$B8,'Líneas codificadas'!$F$2:$F$49,"Fuera de Napoli") -> 0 | N8: =IF($D8=0,"",E8/$D8) -> 0.91045902 | O8: =IF($D8=0,"",F8/$D8) -> 1 | P8: =IF($D8=0,"",G8/$D8) -> 0 | Q8: =IF($D8=0,"",H8/$D8) -> 0.089540978 | R8: =IF($D8=0,"",I8/$D8) -> 0 | S8: =IF($D8=0,"",J8/$D8) -> 0.089540978 | T8: =IF($D8=0,"",K8/$D8) -> 0.91045902 | U8: =IF($D8=0,"",L8/$D8) -> 0.089540978 | V8: =SUMIFS('Líneas codificadas'!$E$2:$E$49,'Líneas codificadas'!$A$2:$A$49,$A8,'Líneas codificadas'!$B$2:$B$49,$B8,'Líneas codificadas'!$K$2:$K$49,"Radio/cable") -> 0 | W8: =IF(($D8-V8)=0,"",(E8-V8)/($D8-V8)) -> 0.91045902 | X8: =D8-INDEX(Datos!$F$2:$F$19,MATCH(A8&"|"&B8,Datos!$A$2:$A$19,0)) -> 0
A9: Chilevisión | B9: FY2025 | C9: EEFF | D9: =SUMIFS('Líneas codificadas'!$E$2:$E$49,'Líneas codificadas'!$A$2:$A$49,$A9,'Líneas codificadas'!$B$2:$B$49,$B9) -> 72498180 | E9: =SUMIFS('Líneas codificadas'!$E$2:$E$49,'Líneas codificadas'!$A$2:$A$49,$A9,'Líneas codificadas'!$B$2:$B$49,$B9,'Líneas codificadas'!$F$2:$F$49,"Audiencias",'Líneas codificadas'!$G$2:$G$49,"Pura") -> 64981856 | F9: =SUMIFS('Líneas codificadas'!$E$2:$E$49,'Líneas codificadas'!$A$2:$A$49,$A9,'Líneas codificadas'!$B$2:$B$49,$B9,'Líneas codificadas'!$H$2:$H$49,"S") -> 72498180 | G9: =SUMIFS('Líneas codificadas'!$E$2:$E$49,'Líneas codificadas'!$A$2:$A$49,$A9,'Líneas codificadas'!$B$2:$B$49,$B9,'Líneas codificadas'!$F$2:$F$49,"Contenidos",'Líneas codificadas'!$G$2:$G$49,"Pura") -> 0 | H9: =SUMIFS('Líneas codificadas'!$E$2:$E$49,'Líneas codificadas'!$A$2:$A$49,$A9,'Líneas codificadas'!$B$2:$B$49,$B9,'Líneas codificadas'!$I$2:$I$49,"S") -> 7516324 | I9: =SUMIFS('Líneas codificadas'!$E$2:$E$49,'Líneas codificadas'!$A$2:$A$49,$A9,'Líneas codificadas'!$B$2:$B$49,$B9,'Líneas codificadas'!$F$2:$F$49,"Fuera de Napoli",'Líneas codificadas'!$G$2:$G$49,"Pura") -> 0 | J9: =SUMIFS('Líneas codificadas'!$E$2:$E$49,'Líneas codificadas'!$A$2:$A$49,$A9,'Líneas codificadas'!$B$2:$B$49,$B9,'Líneas codificadas'!$J$2:$J$49,"S") -> 7516324 | K9: =SUMIFS('Líneas codificadas'!$E$2:$E$49,'Líneas codificadas'!$A$2:$A$49,$A9,'Líneas codificadas'!$B$2:$B$49,$B9,'Líneas codificadas'!$F$2:$F$49,"Audiencias") -> 64981856 | L9: =SUMIFS('Líneas codificadas'!$E$2:$E$49,'Líneas codificadas'!$A$2:$A$49,$A9,'Líneas codificadas'!$B$2:$B$49,$B9,'Líneas codificadas'!$F$2:$F$49,"Contenidos") -> 7516324 | M9: =SUMIFS('Líneas codificadas'!$E$2:$E$49,'Líneas codificadas'!$A$2:$A$49,$A9,'Líneas codificadas'!$B$2:$B$49,$B9,'Líneas codificadas'!$F$2:$F$49,"Fuera de Napoli") -> 0 | N9: =IF($D9=0,"",E9/$D9) -> 0.89632396 | O9: =IF($D9=0,"",F9/$D9) -> 1 | P9: =IF($D9=0,"",G9/$D9) -> 0 | Q9: =IF($D9=0,"",H9/$D9) -> 0.10367604 | R9: =IF($D9=0,"",I9/$D9) -> 0 | S9: =IF($D9=0,"",J9/$D9) -> 0.10367604 | T9: =IF($D9=0,"",K9/$D9) -> 0.89632396 | U9: =IF($D9=0,"",L9/$D9) -> 0.10367604 | V9: =SUMIFS('Líneas codificadas'!$E$2:$E$49,'Líneas codificadas'!$A$2:$A$49,$A9,'Líneas codificadas'!$B$2:$B$49,$B9,'Líneas codificadas'!$K$2:$K$49,"Radio/cable") -> 0 | W9: =IF(($D9-V9)=0,"",(E9-V9)/($D9-V9)) -> 0.89632396 | X9: =D9-INDEX(Datos!$F$2:$F$19,MATCH(A9&"|"&B9,Datos!$A$2:$A$19,0)) -> 0
A10: TVN | B10: FY2024 | C10: EEFF | D10: =SUMIFS('Líneas codificadas'!$E$2:$E$49,'Líneas codificadas'!$A$2:$A$49,$A10,'Líneas codificadas'!$B$2:$B$49,$B10) -> 46850034 | E10: =SUMIFS('Líneas codificadas'!$E$2:$E$49,'Líneas codificadas'!$A$2:$A$49,$A10,'Líneas codificadas'!$B$2:$B$49,$B10,'Líneas codificadas'!$F$2:$F$49,"Audiencias",'Líneas codificadas'!$G$2:$G$49,"Pura") -> 29763217 | F10: =SUMIFS('Líneas codificadas'!$E$2:$E$49,'Líneas codificadas'!$A$2:$A$49,$A10,'Líneas codificadas'!$B$2:$B$49,$B10,'Líneas codificadas'!$H$2:$H$49,"S") -> 46850034 | G10: =SUMIFS('Líneas codificadas'!$E$2:$E$49,'Líneas codificadas'!$A$2:$A$49,$A10,'Líneas codificadas'!$B$2:$B$49,$B10,'Líneas codificadas'!$F$2:$F$49,"Contenidos",'Líneas codificadas'!$G$2:$G$49,"Pura") -> 0 | H10: =SUMIFS('Líneas codificadas'!$E$2:$E$49,'Líneas codificadas'!$A$2:$A$49,$A10,'Líneas codificadas'!$B$2:$B$49,$B10,'Líneas codificadas'!$I$2:$I$49,"S") -> 17086817 | I10: =SUMIFS('Líneas codificadas'!$E$2:$E$49,'Líneas codificadas'!$A$2:$A$49,$A10,'Líneas codificadas'!$B$2:$B$49,$B10,'Líneas codificadas'!$F$2:$F$49,"Fuera de Napoli",'Líneas codificadas'!$G$2:$G$49,"Pura") -> 0 | J10: =SUMIFS('Líneas codificadas'!$E$2:$E$49,'Líneas codificadas'!$A$2:$A$49,$A10,'Líneas codificadas'!$B$2:$B$49,$B10,'Líneas codificadas'!$J$2:$J$49,"S") -> 17086817 | K10: =SUMIFS('Líneas codificadas'!$E$2:$E$49,'Líneas codificadas'!$A$2:$A$49,$A10,'Líneas codificadas'!$B$2:$B$49,$B10,'Líneas codificadas'!$F$2:$F$49,"Audiencias") -> 29763217 | L10: =SUMIFS('Líneas codificadas'!$E$2:$E$49,'Líneas codificadas'!$A$2:$A$49,$A10,'Líneas codificadas'!$B$2:$B$49,$B10,'Líneas codificadas'!$F$2:$F$49,"Contenidos") -> 17086817 | M10: =SUMIFS('Líneas codificadas'!$E$2:$E$49,'Líneas codificadas'!$A$2:$A$49,$A10,'Líneas codificadas'!$B$2:$B$49,$B10,'Líneas codificadas'!$F$2:$F$49,"Fuera de Napoli") -> 0 | N10: =IF($D10=0,"",E10/$D10) -> 0.63528699 | O10: =IF($D10=0,"",F10/$D10) -> 1 | P10: =IF($D10=0,"",G10/$D10) -> 0 | Q10: =IF($D10=0,"",H10/$D10) -> 0.36471301 | R10: =IF($D10=0,"",I10/$D10) -> 0 | S10: =IF($D10=0,"",J10/$D10) -> 0.36471301 | T10: =IF($D10=0,"",K10/$D10) -> 0.63528699 | U10: =IF($D10=0,"",L10/$D10) -> 0.36471301 | V10: =SUMIFS('Líneas codificadas'!$E$2:$E$49,'Líneas codificadas'!$A$2:$A$49,$A10,'Líneas codificadas'!$B$2:$B$49,$B10,'Líneas codificadas'!$K$2:$K$49,"Radio/cable") -> 0 | W10: =IF(($D10-V10)=0,"",(E10-V10)/($D10-V10)) -> 0.63528699 | X10: =D10-INDEX(Datos!$F$2:$F$19,MATCH(A10&"|"&B10,Datos!$A$2:$A$19,0)) -> 0
A11: TVN | B11: FY2025 | C11: EEFF | D11: =SUMIFS('Líneas codificadas'!$E$2:$E$49,'Líneas codificadas'!$A$2:$A$49,$A11,'Líneas codificadas'!$B$2:$B$49,$B11) -> 47915398 | E11: =SUMIFS('Líneas codificadas'!$E$2:$E$49,'Líneas codificadas'!$A$2:$A$49,$A11,'Líneas codificadas'!$B$2:$B$49,$B11,'Líneas codificadas'!$F$2:$F$49,"Audiencias",'Líneas codificadas'!$G$2:$G$49,"Pura") -> 28787675 | F11: =SUMIFS('Líneas codificadas'!$E$2:$E$49,'Líneas codificadas'!$A$2:$A$49,$A11,'Líneas codificadas'!$B$2:$B$49,$B11,'Líneas codificadas'!$H$2:$H$49,"S") -> 45915398 | G11: =SUMIFS('Líneas codificadas'!$E$2:$E$49,'Líneas codificadas'!$A$2:$A$49,$A11,'Líneas codificadas'!$B$2:$B$49,$B11,'Líneas codificadas'!$F$2:$F$49,"Contenidos",'Líneas codificadas'!$G$2:$G$49,"Pura") -> 0 | H11: =SUMIFS('Líneas codificadas'!$E$2:$E$49,'Líneas codificadas'!$A$2:$A$49,$A11,'Líneas codificadas'!$B$2:$B$49,$B11,'Líneas codificadas'!$I$2:$I$49,"S") -> 17127723 | I11: =SUMIFS('Líneas codificadas'!$E$2:$E$49,'Líneas codificadas'!$A$2:$A$49,$A11,'Líneas codificadas'!$B$2:$B$49,$B11,'Líneas codificadas'!$F$2:$F$49,"Fuera de Napoli",'Líneas codificadas'!$G$2:$G$49,"Pura") -> 2000000 | J11: =SUMIFS('Líneas codificadas'!$E$2:$E$49,'Líneas codificadas'!$A$2:$A$49,$A11,'Líneas codificadas'!$B$2:$B$49,$B11,'Líneas codificadas'!$J$2:$J$49,"S") -> 19127723 | K11: =SUMIFS('Líneas codificadas'!$E$2:$E$49,'Líneas codificadas'!$A$2:$A$49,$A11,'Líneas codificadas'!$B$2:$B$49,$B11,'Líneas codificadas'!$F$2:$F$49,"Audiencias") -> 28787675 | L11: =SUMIFS('Líneas codificadas'!$E$2:$E$49,'Líneas codificadas'!$A$2:$A$49,$A11,'Líneas codificadas'!$B$2:$B$49,$B11,'Líneas codificadas'!$F$2:$F$49,"Contenidos") -> 17127723 | M11: =SUMIFS('Líneas codificadas'!$E$2:$E$49,'Líneas codificadas'!$A$2:$A$49,$A11,'Líneas codificadas'!$B$2:$B$49,$B11,'Líneas codificadas'!$F$2:$F$49,"Fuera de Napoli") -> 2000000 | N11: =IF($D11=0,"",E11/$D11) -> 0.60080217 | O11: =IF($D11=0,"",F11/$D11) -> 0.95825976 | P11: =IF($D11=0,"",G11/$D11) -> 0 | Q11: =IF($D11=0,"",H11/$D11) -> 0.3574576 | R11: =IF($D11=0,"",I11/$D11) -> 0.041740236 | S11: =IF($D11=0,"",J11/$D11) -> 0.39919783 | T11: =IF($D11=0,"",K11/$D11) -> 0.60080217 | U11: =IF($D11=0,"",L11/$D11) -> 0.3574576 | V11: =SUMIFS('Líneas codificadas'!$E$2:$E$49,'Líneas codificadas'!$A$2:$A$49,$A11,'Líneas codificadas'!$B$2:$B$49,$B11,'Líneas codificadas'!$K$2:$K$49,"Radio/cable") -> 0 | W11: =IF(($D11-V11)=0,"",(E11-V11)/($D11-V11)) -> 0.60080217 | X11: =D11-INDEX(Datos!$F$2:$F$19,MATCH(A11&"|"&B11,Datos!$A$2:$A$19,0)) -> 0
A12: TVN | B12: H1 2025 | C12: EEFF | D12: =SUMIFS('Líneas codificadas'!$E$2:$E$49,'Líneas codificadas'!$A$2:$A$49,$A12,'Líneas codificadas'!$B$2:$B$49,$B12) -> 24237233 | E12: =SUMIFS('Líneas codificadas'!$E$2:$E$49,'Líneas codificadas'!$A$2:$A$49,$A12,'Líneas codificadas'!$B$2:$B$49,$B12,'Líneas codificadas'!$F$2:$F$49,"Audiencias",'Líneas codificadas'!$G$2:$G$49,"Pura") -> 14095458 | F12: =SUMIFS('Líneas codificadas'!$E$2:$E$49,'Líneas codificadas'!$A$2:$A$49,$A12,'Líneas codificadas'!$B$2:$B$49,$B12,'Líneas codificadas'!$H$2:$H$49,"S") -> 22237233 | G12: =SUMIFS('Líneas codificadas'!$E$2:$E$49,'Líneas codificadas'!$A$2:$A$49,$A12,'Líneas codificadas'!$B$2:$B$49,$B12,'Líneas codificadas'!$F$2:$F$49,"Contenidos",'Líneas codificadas'!$G$2:$G$49,"Pura") -> 0 | H12: =SUMIFS('Líneas codificadas'!$E$2:$E$49,'Líneas codificadas'!$A$2:$A$49,$A12,'Líneas codificadas'!$B$2:$B$49,$B12,'Líneas codificadas'!$I$2:$I$49,"S") -> 8141775 | I12: =SUMIFS('Líneas codificadas'!$E$2:$E$49,'Líneas codificadas'!$A$2:$A$49,$A12,'Líneas codificadas'!$B$2:$B$49,$B12,'Líneas codificadas'!$F$2:$F$49,"Fuera de Napoli",'Líneas codificadas'!$G$2:$G$49,"Pura") -> 2000000 | J12: =SUMIFS('Líneas codificadas'!$E$2:$E$49,'Líneas codificadas'!$A$2:$A$49,$A12,'Líneas codificadas'!$B$2:$B$49,$B12,'Líneas codificadas'!$J$2:$J$49,"S") -> 10141775 | K12: =SUMIFS('Líneas codificadas'!$E$2:$E$49,'Líneas codificadas'!$A$2:$A$49,$A12,'Líneas codificadas'!$B$2:$B$49,$B12,'Líneas codificadas'!$F$2:$F$49,"Audiencias") -> 14095458 | L12: =SUMIFS('Líneas codificadas'!$E$2:$E$49,'Líneas codificadas'!$A$2:$A$49,$A12,'Líneas codificadas'!$B$2:$B$49,$B12,'Líneas codificadas'!$F$2:$F$49,"Contenidos") -> 8141775 | M12: =SUMIFS('Líneas codificadas'!$E$2:$E$49,'Líneas codificadas'!$A$2:$A$49,$A12,'Líneas codificadas'!$B$2:$B$49,$B12,'Líneas codificadas'!$F$2:$F$49,"Fuera de Napoli") -> 2000000 | N12: =IF($D12=0,"",E12/$D12) -> 0.58156218 | O12: =IF($D12=0,"",F12/$D12) -> 0.91748233 | P12: =IF($D12=0,"",G12/$D12) -> 0 | Q12: =IF($D12=0,"",H12/$D12) -> 0.33592015 | R12: =IF($D12=0,"",I12/$D12) -> 0.08251767 | S12: =IF($D12=0,"",J12/$D12) -> 0.41843782 | T12: =IF($D12=0,"",K12/$D12) -> 0.58156218 | U12: =IF($D12=0,"",L12/$D12) -> 0.33592015 | V12: =SUMIFS('Líneas codificadas'!$E$2:$E$49,'Líneas codificadas'!$A$2:$A$49,$A12,'Líneas codificadas'!$B$2:$B$49,$B12,'Líneas codificadas'!$K$2:$K$49,"Radio/cable") -> 0 | W12: =IF(($D12-V12)=0,"",(E12-V12)/($D12-V12)) -> 0.58156218 | X12: =D12-INDEX(Datos!$F$2:$F$19,MATCH(A12&"|"&B12,Datos!$A$2:$A$19,0)) -> 0
A13: TVN | B13: H1 2026 | C13: EEFF | D13: =SUMIFS('Líneas codificadas'!$E$2:$E$49,'Líneas codificadas'!$A$2:$A$49,$A13,'Líneas codificadas'!$B$2:$B$49,$B13) -> 22291139 | E13: =SUMIFS('Líneas codificadas'!$E$2:$E$49,'Líneas codificadas'!$A$2:$A$49,$A13,'Líneas codificadas'!$B$2:$B$49,$B13,'Líneas codificadas'!$F$2:$F$49,"Audiencias",'Líneas codificadas'!$G$2:$G$49,"Pura") -> 12596474 | F13: =SUMIFS('Líneas codificadas'!$E$2:$E$49,'Líneas codificadas'!$A$2:$A$49,$A13,'Líneas codificadas'!$B$2:$B$49,$B13,'Líneas codificadas'!$H$2:$H$49,"S") -> 20587425 | G13: =SUMIFS('Líneas codificadas'!$E$2:$E$49,'Líneas codificadas'!$A$2:$A$49,$A13,'Líneas codificadas'!$B$2:$B$49,$B13,'Líneas codificadas'!$F$2:$F$49,"Contenidos",'Líneas codificadas'!$G$2:$G$49,"Pura") -> 0 | H13: =SUMIFS('Líneas codificadas'!$E$2:$E$49,'Líneas codificadas'!$A$2:$A$49,$A13,'Líneas codificadas'!$B$2:$B$49,$B13,'Líneas codificadas'!$I$2:$I$49,"S") -> 7990951 | I13: =SUMIFS('Líneas codificadas'!$E$2:$E$49,'Líneas codificadas'!$A$2:$A$49,$A13,'Líneas codificadas'!$B$2:$B$49,$B13,'Líneas codificadas'!$F$2:$F$49,"Fuera de Napoli",'Líneas codificadas'!$G$2:$G$49,"Pura") -> 1703714 | J13: =SUMIFS('Líneas codificadas'!$E$2:$E$49,'Líneas codificadas'!$A$2:$A$49,$A13,'Líneas codificadas'!$B$2:$B$49,$B13,'Líneas codificadas'!$J$2:$J$49,"S") -> 9694665 | K13: =SUMIFS('Líneas codificadas'!$E$2:$E$49,'Líneas codificadas'!$A$2:$A$49,$A13,'Líneas codificadas'!$B$2:$B$49,$B13,'Líneas codificadas'!$F$2:$F$49,"Audiencias") -> 12596474 | L13: =SUMIFS('Líneas codificadas'!$E$2:$E$49,'Líneas codificadas'!$A$2:$A$49,$A13,'Líneas codificadas'!$B$2:$B$49,$B13,'Líneas codificadas'!$F$2:$F$49,"Contenidos") -> 7990951 | M13: =SUMIFS('Líneas codificadas'!$E$2:$E$49,'Líneas codificadas'!$A$2:$A$49,$A13,'Líneas codificadas'!$B$2:$B$49,$B13,'Líneas codificadas'!$F$2:$F$49,"Fuera de Napoli") -> 1703714 | N13: =IF($D13=0,"",E13/$D13) -> 0.56508885 | O13: =IF($D13=0,"",F13/$D13) -> 0.9235699 | P13: =IF($D13=0,"",G13/$D13) -> 0 | Q13: =IF($D13=0,"",H13/$D13) -> 0.35848105 | R13: =IF($D13=0,"",I13/$D13) -> 0.076430101 | S13: =IF($D13=0,"",J13/$D13) -> 0.43491115 | T13: =IF($D13=0,"",K13/$D13) -> 0.56508885 | U13: =IF($D13=0,"",L13/$D13) -> 0.35848105 | V13: =SUMIFS('Líneas codificadas'!$E$2:$E$49,'Líneas codificadas'!$A$2:$A$49,$A13,'Líneas codificadas'!$B$2:$B$49,$B13,'Líneas codificadas'!$K$2:$K$49,"Radio/cable") -> 0 | W13: =IF(($D13-V13)=0,"",(E13-V13)/($D13-V13)) -> 0.56508885 | X13: =D13-INDEX(Datos!$F$2:$F$19,MATCH(A13&"|"&B13,Datos!$A$2:$A$19,0)) -> 0
... A19: Chilevisión | B19: H1 2026 | C19: EEFF | D19: =SUMIFS('Líneas codificadas'!$E$2:$E$49,'Líneas codificadas'!$A$2:$A$49,$A19,'Líneas codificadas'!$B$2:$B$49,$B19) -> 36231357 | E19: =SUMIFS('Líneas codificadas'!$E$2:$E$49,'Líneas codificadas'!$A$2:$A$49,$A19,'Líneas codificadas'!$B$2:$B$49,$B19,'Líneas codificadas'!$F$2:$F$49,"Audiencias",'Líneas codificadas'!$G$2:$G$49,"Pura") -> 32933666 | F19: =SUMIFS('Líneas codificadas'!$E$2:$E$49,'Líneas codificadas'!$A$2:$A$49,$A19,'Líneas codificadas'!$B$2:$B$49,$B19,'Líneas codificadas'!$H$2:$H$49,"S") -> 36231357 | G19: =SUMIFS('Líneas codificadas'!$E$2:$E$49,'Líneas codificadas'!$A$2:$A$49,$A19,'Líneas codificadas'!$B$2:$B$49,$B19,'Líneas codificadas'!$F$2:$F$49,"Contenidos",'Líneas codificadas'!$G$2:$G$49,"Pura") -> 0 | H19: =SUMIFS('Líneas codificadas'!$E$2:$E$49,'Líneas codificadas'!$A$2:$A$49,$A19,'Líneas codificadas'!$B$2:$B$49,$B19,'Líneas codificadas'!$I$2:$I$49,"S") -> 3297691 | I19: =SUMIFS('Líneas codificadas'!$E$2:$E$49,'Líneas codificadas'!$A$2:$A$49,$A19,'Líneas codificadas'!$B$2:$B$49,$B19,'Líneas codificadas'!$F$2:$F$49,"Fuera de Napoli",'Líneas codificadas'!$G$2:$G$49,"Pura") -> 0 | J19: =SUMIFS('Líneas codificadas'!$E$2:$E$49,'Líneas codificadas'!$A$2:$A$49,$A19,'Líneas codificadas'!$B$2:$B$49,$B19,'Líneas codificadas'!$J$2:$J$49,"S") -> 3297691 | K19: =SUMIFS('Líneas codificadas'!$E$2:$E$49,'Líneas codificadas'!$A$2:$A$49,$A19,'Líneas codificadas'!$B$2:$B$49,$B19,'Líneas codificadas'!$F$2:$F$49,"Audiencias") -> 32933666 | L19: =SUMIFS('Líneas codificadas'!$E$2:$E$49,'Líneas codificadas'!$A$2:$A$49,$A19,'Líneas codificadas'!$B$2:$B$49,$B19,'Líneas codificadas'!$F$2:$F$49,"Contenidos") -> 3297691 | M19: =SUMIFS('Líneas codificadas'!$E$2:$E$49,'Líneas codificadas'!$A$2:$A$49,$A19,'Líneas codificadas'!$B$2:$B$49,$B19,'Líneas codificadas'!$F$2:$F$49,"Fuera de Napoli") -> 0 | N19: =IF($D19=0,"",E19/$D19) -> 0.9089824 | O19: =IF($D19=0,"",F19/$D19) -> 1 | P19: =IF($D19=0,"",G19/$D19) -> 0 | Q19: =IF($D19=0,"",H19/$D19) -> 0.091017596 | R19: =IF($D19=0,"",I19/$D19) -> 0 | S19: =IF($D19=0,"",J19/$D19) -> 0.091017596 | T19: =IF($D19=0,"",K19/$D19) -> 0.9089824 | U19: =IF($D19=0,"",L19/$D19) -> 0.091017596 | V19: =SUMIFS('Líneas codificadas'!$E$2:$E$49,'Líneas codificadas'!$A$2:$A$49,$A19,'Líneas codificadas'!$B$2:$B$49,$B19,'Líneas codificadas'!$K$2:$K$49,"Radio/cable") -> 0 | W19: =IF(($D19-V19)=0,"",(E19-V19)/($D19-V19)) -> 0.9089824 | X19: =D19-INDEX(Datos!$F$2:$F$19,MATCH(A19&"|"&B19,Datos!$A$2:$A$19,0)) -> 0
A21: Piso = suma de líneas Puras con ese código. Techo = suma de líneas que pueden ser de esa categoría (Puras + Mixtas marcadas 'S'). Punto = asigna cada línea a su código principal. Perímetro TV = excluye publicidad radial/cable del numerador y del denominador. Cuadre debe ser 0.

Sheet Mapeo de líneas
A1: Canal | B1: Línea en la nota de ingresos | C1: Categoría asignada | D1: Comentario
A2: Canal 13 | B2: Ingresos de Publicidad Pantalla abierta | C2: Audiencias – TV
A3: Canal 13 | B3: Ingresos de Publicidad Otras plataformas | C3: Audiencias – digital
A4: Canal 13 | B4: Otros ingresos de explotación | C4: Contenidos + otros | D4: Mezcla cableoperadores (13C, 13REC), digital no publicitario, nuevas señales, venta de contenidos, venta de activos, arriendos y servicios a productoras.
A5: Mega | B5: Ingresos por publicidad de televisión e internet | C5: Audiencias – TV (incl. internet) | D5: Neto de comisiones de agencia.
A6: Mega | B6: Ingresos por publicidad radial y cable | C6: Audiencias – radio/cable | D6: Radios del grupo y canal de cable; es venta de audiencias, pero no de TV abierta.
A7: Mega | B7: Ingresos por ventas en plataformas y contenidos | C7: Contenidos + otros | D7: Plataformas, suscripciones, venta de contenidos (nacional y extranjero). Es lo más cercano a 'content sales' puro.
A8: Chilevisión | B8: Ingresos por publicidad | C8: Audiencias – TV | D8: TV abierta + comisión por TV paga.
A9: Chilevisión | B9: Ingresos nuevos negocios | C9: Contenidos + otros | D9: Incluye fee de administración (cost-plus), publicidad por internet, venta de señales y contenido. Contiene algo de venta de audiencias (internet) no separable.
A10: TVN | B10: Ingresos por publicidad en televisión abierta | C10: Audiencias – TV
A11: TVN | B11: Otros ingresos | C11: Contenidos + otros | D11: Principalmente venta de señal internacional a operadores de TV pago y otros servicios derivados de la actividad televisiva.
A12: TVN | B12: Subvención NTV | C12: Fuera de Napoli | D12: Transferencia estatal; desde 2025 (M$2.000.000 en 2025; M$1.703.714 en H1 2026).

Sheet Pendientes EEFF
A1: Canal | B1: Archivo faltante | C1: Para qué
A2: Recibidos | B2: Todos los EEFF necesarios recibidos. CHV sep-2025 a jun-2026; Mega dic-2024 a jun-2026; TVN trimestrales mar-2024 a jun-2026; C13 dic-2024, dic-2025 y jun-2026; Mega dic-2025 y dic-2024; CHV dic-2025 | C2: Integrados en esta versión

Sheet Mercado AAM
A1: Contraste con la inversión publicitaria en TV abierta (AAM)
A2: Ojo: AAM mide inversión de avisadores reportada por agencias; los canales informan ingresos netos de comisiones y descuentos. Sirve como control de plausibilidad, no para imputar.
A4: Concepto | B4: H1 2025 | C4: H1 2026 | D4: Fuente
A5: Inversión publicitaria total (MM$) | B5: 466787 | C5: 497769 | D5: AAM vía Insider Latam (ago-2025) y Publimark (2026)
A6: Participación TV abierta | B6: 0.239 | C6: 0.223 | D6: AAM
A7: Inversión en TV abierta (MM$) | B7: =B5*B6 -> 111562.09 | C7: =C5*C6 -> 111002.49 | D7: Cálculo
A8: Canal 13: publicidad pantalla abierta (MM$) | B8: =26859101/1000 -> 26859.101 | C8: =26162497/1000 -> 26162.497 | D8: EEFF C13 jun-2026, Nota 21
A9: TVN: publicidad TV abierta (MM$) | B9: =14095458/1000 -> 14095.458 | C9: =12596474/1000 -> 12596.474 | D9: EEFF TVN jun-2026, Nota 22 a)
A10: Mega: publicidad TV + internet (MM$) | B10: =36244158/1000 -> 36244.158 | C10: =42107628/1000 -> 42107.628 | D10: EEFF Megamedia jun-2026, Nota 7 a)
A11: Chilevisión: publicidad (MM$) | B11: =33494199/1000 -> 33494.199 | C11: =32933666/1000 -> 32933.666 | D11: EEFF Chilevisión jun-2026, Nota 20 (TV abierta + comisión TV paga)
A12: Suma de los cuatro canales (MM$) | B12: =SUM(B8:B11) -> 110692.92 | C12: =IF(COUNT(C8:C11)=4,SUM(C8:C11),"incompleto") -> 113800.26 | D12: Cálculo
A13: Cobertura: suma canales / inversión AAM TV abierta | B13: =B12/B7 -> 0.99220903 | C13: =IF(ISNUMBER(C12),C12/C7,"") -> 1.0252046 | D13: Cálculo. Puede superar 100%: Mega incluye publicidad por internet en su línea.
A14: Residuo AAM para Chilevisión + otros canales (MM$) | B14: =B7-B8-B9-B10 -> 34363.376 | C14: =C7-C8-C9-C10 -> 30135.888 | D14: Cálculo (incluye La Red, TV+, regionales y diferencias de medición; Mega incluye internet)
A16: AAM 2025 (año): inversión total +4%; TV abierta ~23% de participación, +0,7%; TV pago -24,9%; radio -0,8% (Publimark).
